Workbook

Sheet Budget Tracker
A1: BAS BUDGET TRACKER 24-25
D5: Summary:
D6: Total Income:
D7: =D34 -> 11064 | E7: * | G7: P&L:
G8: Bank Statement | H8: Unkown | I8: Tasty Event | J8: Football | K8: Puppy Yoga | L8: Padel | M8: Eid Event
D9: Total Expenses: | G9: =D25 -> 5084 | H9: =D20 -> 0 | I9: =D21 -> 2100 | J9: =D22 -> 1560 | K9: =D23 -> 220 | L9: =D24 -> 600 | M9: =D26 -> 1500
D10: =L34 -> -13071 | E10: * | G10: =L25 -> 6771 | H10: =L20 -> 0 | I10: =L21 -> 1460 | J10: =L22 -> 500 | K10: =L23 -> 1190 | L10: =L24 -> 1080 | M10: =L26 -> 2070
G11: =G9-G10 -> -1687 | H11: =H9-H10 -> 0 | I11: =I9-I10 -> 640 | J11: =J9-J10 -> 1060 | K11: =K9-K10 -> -970 | L11: =L9-L10 -> -480 | M11: =M9-M10 -> -570
D12: Cash Balance:
D13: =D10+D7 -> -2007 | E13: *
C15: * | D15: All these are estimates based off the excel shared
B18: Income: | H18: EXPENSES:
B19: ITEM: | D19: Amount: | H19: ITEM: | J19: Due Date: | L19: Amount:
B20: Unkown | D20: 0 | H20: Unkown | J20: =TODAY() -> 45894 | L20: 0
B21: Tasty Event | D21: =SUM('Tasty Event'!D2:D3) -> 2100 | H21: Tasty Event | J21: =TODAY() -> 45894 | L21: =SUM('Income Tracker'!H60:H65) -> 1460
B22: Football | D22: =Football!D3 -> 1560 | H22: Football | J22: =TODAY() -> 45894 | L22: =SUM('Income Tracker'!H69) -> 500
B23: Puppy Yoga | D23: ='Puppy Yoga'!C5 -> 220 | H23: Puppy Yoga | J23: =TODAY() -> 45894 | L23: =SUM('Income Tracker'!H70:H71) -> 1190
B24: Padel | D24: =Padel!D2 -> 600 | H24: Padel | J24: =TODAY() -> 45894 | L24: =SUM('Income Tracker'!H80:H83) -> 1080
B25: Bank Statement | D25: =SUM('Bank Statment'!B2:B21) -> 5084 | H25: Bank Statement | J25: =TODAY() -> 45894 | L25: =SUM('Income Tracker'!H29:H59) -> 6771
B26: Eid Event | D26: ='Eid Event'!C8 -> 1500 | H26: Eid Event | J26: =TODAY() -> 45894 | L26: =SUM('Income Tracker'!H73:H78) -> 2070
B27: N/A | D27: 0 | H27: N/A | J27: =TODAY() -> 45894 | L27: 0
B28: N/A | D28: 0 | H28: N/A | J28: =TODAY() -> 45894 | L28: 0
B29: N/A | D29: 0 | H29: N/A | J29: =TODAY() -> 45894 | L29: 0
B30: N/A | D30: 0 | H30: N/A | J30: =TODAY() -> 45894 | L30: 0
B31: N/A | D31: 0 | H31: N/A | J31: =TODAY() -> 45894 | L31: 0
B32: N/A | D32: 0 | H32: N/A | J32: =TODAY() -> 45894 | L32: 0
B33: N/A | D33: 0 | H33: N/A | J33: =TODAY() -> 45894 | L33: 0
B34: Total | D34: =SUM(D20:E33) -> 11064 | H34: Total | L34: =-SUM(L20:M33) -> -13071
B40: Sources:
B41: Unkown
B42: Tasty Event
B43: Football
B44: Puppy Yoga
B45: Eid Event
B46: Padel
B47: Bank Statement
B48: N/A

Sheet Income Tracker
A1: BAS INCOME TRACKER 24-25
A3: Sources:
A4: Unkown | G4: Total Income: | H4: Total Expenses:
A5: Tasty Event | G5: =SUM(G9:G1048576) -> 11064 | H5: =-SUM(H29:H1048576) -> -13071
A6: Football
A7: Puppy Yoga
A8: Eid Event | C8: Item | D8: Description | G8: Incoming | H8: Outgoing
A9: Padel | C9: Bank Statement | G9: 300 | H9: 0
A10: Bank Statement | C10: Bank Statement | G10: 220 | H10: 0
A11: N/A | C11: Bank Statement | G11: 120 | H11: 0
C12: Bank Statement | G12: 120 | H12: 0
C13: Bank Statement | G13: 640 | H13: 0
C14: Bank Statement | G14: 200 | H14: 0
C15: Bank Statement | G15: 75 | H15: 0
C16: Bank Statement | G16: 50 | H16: 0
C17: Bank Statement | G17: 200 | H17: 0
C18: Bank Statement | G18: 300 | H18: 0
C19: Bank Statement | G19: 60 | H19: 0
C20: Bank Statement | G20: 90 | H20: 0
C21: Bank Statement | G21: 180 | H21: 0
C22: Bank Statement | G22: 859 | H22: 0
C23: Bank Statement | G23: 100 | H23: 0
... C66: Tasty Event | G66: 1500 | H66: 0
C67: Tasty Event | G67: 600 | H67: 0 | M67: 1560
C68: Football | G68: 1560 | H68: 0
C69: Football | G69: 0 | H69: 500
C70: Puppy Yoga | G70: 0 | H70: 990
C71: Puppy Yoga | G71: 0 | H71: 200
C72: Puppy Yoga | G72: 220 | H72: 0
C73: Eid Event | G73: 0 | H73: 1000
C74: Eid Event | G74: 0 | H74: 520
C75: Eid Event | G75: 0 | H75: 200
C76: Eid Event | G76: 0 | H76: 150
C77: Eid Event | G77: 0 | H77: 150
C78: Eid Event | G78: 0 | H78: 50
C79: Eid Event | G79: 1500 | H79: 0
... C84: Padel | G84: 600 | H84: 0

Sheet Bank Statment
A1: BOFA statment for BAS account | B1: IN | C1: OUT
A2: This is the copy of our statment of accounts from BOFA | B2: 300 | C2: -70
A3: In and Out are not explicitly expenses and revenues | B3: 220 | C3: -3
A4: They are also transfers from personal to BAS accounts, zelles... | B4: 120 | C4: -20
A5: Sources are lost! not sure how this can help you - but incase you want to use | B5: 120 | C5: -800
A6: *the next pages are some of our events in specific if you'd like to use that | B6: 640 | C6: -66
B7: 200 | C7: -29
B8: 75 | C8: -200
B9: 50 | C9: -100
B10: 200 | C10: -200
B11: 300 | C11: -90
B12: 60 | C12: -156
B13: 90 | C13: -40
B14: 180 | C14: -100
B15: 859 | C15: -205
B16: 100 | C16: -300
B17: 60 | C17: -215
B18: 638 | C18: -500
... B21: 200 | C21: -50
C22: -10
C23: -200
C24: -40
C25: 877
C26: -250
C27: -20
C28: -10
C29: -10
C30: -80
C31: -520
C32: -1300

Sheet Tasty Event
A1: Tasty Event | B1: OUT | D1: IN
A2: Space rental, Drinks, and liquor lincense | B2: 520 | C2: Ticket revenue | D2: 1500 | E2: Not yet recieved by portalys
A3: Merch | B3: 160 | C3: Drink Revenue | D3: 600
A4: DJ set | B4: 250
A5: Posters | B5: 100
A6: Neon Light | B6: 230
A7: Bar tender | B7: 200

Sheet Football
C1: not sure about player number, it added overtime
A2: IN | B2: Ticket | C2: Players | D2: Ticket Revenue
B3: 30 | C3: 52 | D3: 1560
A5: OUT | B5: Pitch Rental | C5: Bibs and Trophy and snacks
B6: 200-300 | C6: max 200 | D6: not so sure about the numbers here
B7: 300 | C7: 200

Sheet Puppy Yoga
A1: Puppy Yoga
A2: OUT | B2: Stickers+Enevelopes and Printing + Poster | C2: Rental
B3: 200 | C3: 990
A4: IN | C4: Puupy Yoga Profit
C5: 220

Sheet Eid Event
A1: OUT | B1: Ammount | C1: Outlet
B2: 1000 | C2: Catering SAJ
B3: 520 | C3: Rental roof
B4: 200 | C4: Saxophonist
B5: 150 | C5: Speakers
B6: 150 | C6: Drinks
B7: 50 | C7: Posters
A8: IN | B8: Ticket revenue | C8: 1500
A10: LOSS EVENT

Sheet Padel
A1: OUT | C1: IN
A2: 800 | B2: Courts Rental | C2: Ticket Revenue Estimate | D2: 600
A3: 80 | B3: Rackets and Balls
A4: 100 | B4: Snacks
A5: 100 | B5: Posters
