Workbook
Name BaseYear: [1]Controls!$C$23
Name DateHeader: [1]Controls!$E$27
Name DollarHeader: [1]Controls!$E$20
Name FX: #REF!
Name Selling_Price: '[4]Base Case'!$B$11
Name taxtable: #REF!
Name Variable_Cost_per_unit: '[4]Base Case'!$B$12

Sheet General Info
G3: General Information
B8: Table of Contents
B9: 1 | C9: Tear Sheet
B10: =+B9+1 -> 2 | C10: =Summary!F3 -> Valuation Summary
B11: =+B10+1 -> 3 | C11: ='Actuals FS'!D3 -> Historic Financial Statements
B12: =+B11+1 -> 4 | C12: ='HWMS Model'!F2 -> AMZN Quarterly Sales Forecasting: Holt-Winters Multiplicative Seasonal (HWMS) Model
B13: =+B12+1 -> 5 | C13: =Revenue!D2 -> Revenue Breakdown & Projections
B14: =+B13+1 -> 6 | C14: =Scenarios!C3 -> Scenario Assumptions
B15: =+B14+1 -> 7 | C15: =Multiples!C3 -> Relative Multiples Valuation Model Based on Selected Industry Peers
B16: =+B15+1 -> 8 | C16: ='Forecasted FS'!C3 -> Forecasted Financial Statements
B17: =+B16+1 -> 9 | C17: =WACC!B3 -> Weighted Average Cost of Capital
B18: =+B17+1 -> 10 | C18: =DCF!C3 -> Discounted Cash Flows Model
B19: =+B18+1 -> 11 | C19: =References!B7 -> References
B21: Appendix
B22: =Appendix!B8 -> 1 | C22: =Appendix!C8 -> Financial Statements
B23: =Appendix!B9 -> 2 | C23: =Appendix!C9 -> Financial Ratios Analysis
B24: =Appendix!B10 -> 3 | C24: =Appendix!C10 -> Operating Margin Target Based on Management Expectations
B25: =Appendix!B11 -> 4 | C25: =Appendix!C11 -> Depreciation & Amortization Schedule
B26: =Appendix!B12 -> 5 | C26: =Appendix!C12 -> Summary of Corporate Bonds
B27: =Appendix!B13 -> 6 | C27: =Appendix!C13 -> Scenario Summary
B28: =Appendix!B14 -> 7 | C28: =Appendix!C14 -> Industry Peers Market Information
B29: =Appendix!B15 -> 8 | C29: =Appendix!C15 -> Industry Peers Financial Information
B30: =Appendix!B16 -> 9 | C30: =Appendix!C16 -> 10 year Historic S&P Returns
B31: =Appendix!B17 -> 10 | C31: =Appendix!C17 -> AMZN Historic Daily Stock Prices from 12/12/205 to date (12/12/2025)
B32: =Appendix!B18 -> 11 | C32: =Appendix!C18 -> 10 year Historic Yield to Maturity of US 10 year Treasury Bill
B33: =Appendix!B19 -> 12 | C33: =Appendix!C19 -> Country Corporate Income Tax Rate
... B38: =Appendix!B24 -> 17 | C38: =Appendix!C24 -> Abbreviations
B40: General information for the reader:
B41: - Forward looking statements were elaborated by the author for academic purposes
B42: - Assumptions made are referenced in each tab under "NOTES"
B43: - This report serves as supporting evidence to the written report that exhibits the authors conclusions and insights

Sheet Tear Sheet
B8: Recommendation: | C8: BUY | D8: Price: | E8: ='AMZN daily'!G8 -> 226.19 | G8: (12/12/2025) | J8: Target Price: | K8: =DCF!I49 -> 292.99442
B11: GICS Sector: Consumer Discretionary | D11: Business Summary: Amazon is a global leader in e-commerce, cloud computing, online advertising, digital streaming, and artificial intelligence.
B12: Sub-Sector: Broadline Retail
B13: NAICS Industry: Electronic Shopping
C14: and Mail-Order Houses
B16: Key Stock Statistics
B18: Market Capitalization (BN) | C18: 2418.02 | D18: 52-Week Range | G18: =MIN('AMZN daily'!G8:G245) -> 167.32 | H18: =MAX('AMZN daily'!G8:G245) -> 254 | I18: Year Founded | K18: 1994
B19: Enterprise Value (BN) | C19: 2511.5 | D19: Shares Outstanding (M) | H19: ='Actuals FS'!D68 -> 10721 | I19: Inst. Ownership (%) | K19: =Shareholders!D16 -> 0.7522
B20: FY 2024 EPS | C20: =7.08 -> 7.08 | D20: Avg. Volume ('000) | H20: =AVERAGE('AMZN daily'!I8:I1086)/1000 -> 43002.979 | I20: Rating (S&P/Moody's) | K20: AA/A1
B21: FY 2024P/E | C21: =E8/C20 -> 31.94774 | D21: Dividend per share | H21: ='Actuals FS'!D145 -> 0 | I21: Unlevered Beta | K21: =WACC!E21 -> 1.354696
B22: FY 2024 P/Sales | C22: =C18/('Actuals FS'!D47/1000) -> 3.7902436 | D22: Dividend Yield (%) | H22: =H21/E8 -> 0 | I22: Levered Beta | K22: =WACC!E22 -> 1.3772792
B24: Price Performance (NYS: AMZN)
B40: Financial Summary
B42: In $ millions | C42: ='FS all'!D10 -> 2020 A | D42: ='FS all'!E10 -> 2021 A | E42: ='FS all'!F10 -> 2022 A | F42: ='FS all'!G10 -> 2023 A | G42: ='FS all'!H10 -> 2024 A | H42: ='FS all'!I10 -> 2025 F | I42: ='FS all'!J10 -> 2026 F | J42: ='FS all'!K10 -> 2027 F | ... L42: ='FS all'!M10 -> 2029 F
B43: Revenues | C43: ='FS all'!D11 -> 386064 | D43: ='FS all'!E11 -> 469822 | E43: ='FS all'!F11 -> 513983 | F43: ='FS all'!G11 -> 574785 | G43: ='FS all'!H11 -> 637959 | H43: ='FS all'!I11 -> 682616.13 | I43: ='FS all'!J11 -> 744051.58 | J43: ='FS all'!K11 -> 811016.22 | ... L43: ='FS all'!M11 -> 981329.63
B44: EBITDA | C44: ='FS all'!D153 -> 42001 | D44: ='FS all'!E153 -> 61197 | E44: ='FS all'!F153 -> 40049 | F44: ='FS all'!G153 -> 68786 | G44: ='FS all'!H153 -> 100372 | H44: ='FS all'!I153 -> 103809.96 | I44: ='FS all'!J153 -> 120800.59 | J44: ='FS all'!K153 -> 136973.97 | ... L44: ='FS all'!M153 -> 172734.73
B45: Net Income | C45: ='FS all'!D30 -> 21331 | D45: ='FS all'!E30 -> 33364 | E45: ='FS all'!F30 -> -2722 | F45: ='FS all'!G30 -> 30425 | G45: ='FS all'!H30 -> 59248 | H45: ='FS all'!I30 -> 66748.877 | I45: ='FS all'!J30 -> 84364.915 | J45: ='FS all'!K30 -> 100964.18 | ... L45: ='FS all'!M30 -> 139417.22
B46: Total Assets | C46: ='FS all'!D47 -> 321195 | D46: ='FS all'!E47 -> 420549 | E46: ='FS all'!F47 -> 462675 | F46: ='FS all'!G47 -> 527854 | G46: ='FS all'!H47 -> 624894 | H46: ='FS all'!I47 -> 737028.24 | I46: ='FS all'!J47 -> 873770.46 | J46: ='FS all'!K47 -> 1027375.5 | ... L46: ='FS all'!M47 -> 1405539.8
B47: Total Debt | C47: ='FS all'!D55 -> 31816 | D47: ='FS all'!E55 -> 48744 | E47: ='FS all'!F55 -> 67150 | F47: ='FS all'!G55 -> 58314 | G47: ='FS all'!H55 -> 52623 | H47: ='FS all'!I55 -> 57214 | I47: ='FS all'!J55 -> 61805 | J47: ='FS all'!K55 -> 64100.5 | ... L47: ='FS all'!M55 -> 65822.125
B48: Equity | C48: ='FS all'!D67 -> 93404 | D48: ='FS all'!E67 -> 138245 | E48: ='FS all'!F67 -> 146043 | F48: ='FS all'!G67 -> 201875 | G48: ='FS all'!H67 -> 285970 | H48: ='FS all'!I67 -> 374263.03 | I48: ='FS all'!J67 -> 480525.78 | J48: ='FS all'!K67 -> 603747.28 | ... L48: ='FS all'!M67 -> 908851.28
B50: Key Financial Indicators
B52: EBITDA Margin (%) | C52: ='FS all'!D154 -> 0.10879284 | D52: ='FS all'!E154 -> 0.13025571 | E52: ='FS all'!F154 -> 0.077918919 | F52: ='FS all'!G154 -> 0.11967257 | G52: ='FS all'!H154 -> 0.15733299 | H52: ='FS all'!I154 -> 0.15207662 | I52: ='FS all'!J154 -> 0.16235512 | J52: ='FS all'!K154 -> 0.16889178 | ... L52: ='FS all'!M154 -> 0.17602111
B53: Operating Margin (%) | C53: ='FS all'!D119 -> 0.059314 | D53: ='FS all'!E119 -> 0.052954098 | E53: ='FS all'!F119 -> 0.023829582 | F53: ='FS all'!G119 -> 0.064114408 | G53: ='FS all'!H119 -> 0.10751945 | H53: ='FS all'!I119 -> 0.12336577 | I53: ='FS all'!J119 -> 0.14312706 | J53: ='FS all'!K119 -> 0.15719767 | ... L53: ='FS all'!M119 -> 0.17953858
B54: Debt to Equity (x) | C54: =('FS all'!D55/'FS all'!D67) -> 0.34062781 | D54: =('FS all'!E55/'FS all'!E67) -> 0.35259141 | E54: =('FS all'!F55/'FS all'!F67) -> 0.45979609 | F54: =('FS all'!G55/'FS all'!G67) -> 0.28886192 | G54: =('FS all'!H55/'FS all'!H67) -> 0.18401581 | H54: =('FS all'!I55/'FS all'!I67) -> 0.1528711 | I54: =('FS all'!J55/'FS all'!J67) -> 0.12861953 | J54: =('FS all'!K55/'FS all'!K67) -> 0.10617108 | ... L54: =('FS all'!M55/'FS all'!M67) -> 0.072423427
B55: ROE (%) | C55: ='FS all'!D137 -> 0.22837352 | D55: ='FS all'!E137 -> 0.24133965 | E55: ='FS all'!F137 -> -0.018638346 | F55: ='FS all'!G137 -> 0.15071207 | G55: ='FS all'!H137 -> 0.20718257 | H55: ='FS all'!I137 -> 0.1930318 | I55: ='FS all'!J137 -> 0.19047206 | J55: ='FS all'!K137 -> 0.18074065 | ... L55: ='FS all'!M137 -> 0.16516639
B56: ROA (%) | C56: ='FS all'!D120 -> 0.06641137 | D56: ='FS all'!E120 -> 0.079334394 | E56: ='FS all'!F120 -> -0.0058831793 | F56: ='FS all'!G120 -> 0.057639044 | G56: ='FS all'!H120 -> 0.09481288 | H56: ='FS all'!I120 -> 0.098021568 | I56: ='FS all'!J120 -> 0.10474917 | J56: ='FS all'!K120 -> 0.10621402 | ... L56: ='FS all'!M120 -> 0.10680002
B57: ROIC (%) | C57: ='FS all'!D123 -> 0.10810323 | D57: ='FS all'!E123 -> 0.088053842 | E57: ='FS all'!F123 -> 0.03622841 | F57: ='FS all'!G123 -> 0.087275703 | G57: ='FS all'!H123 -> 0.12983255 | H57: ='FS all'!I123 -> 0.17278183 | I57: ='FS all'!J123 -> 0.17278603 | J57: ='FS all'!K123 -> 0.1664498 | ... L57: ='FS all'!M123 -> 0.15583335
B58: EPS | C58: ='FS all'!D140 -> 41.82549 | D58: ='FS all'!E140 -> 64.784466 | E58: ='FS all'!F140 -> -0.26715085 | F58: ='FS all'!G140 -> 2.8998284 | G58: ='FS all'!H140 -> 5.5263502 | H58: ='FS all'!I140 -> 6.1254358 | I58: ='FS all'!J140 -> 7.6169874 | J58: ='FS all'!K140 -> 8.9684418 | ... L58: ='FS all'!M140 -> 11.987338
B59: Dividend Per Share | C59: ='FS all'!D142 -> 0 | D59: ='FS all'!E142 -> 0 | E59: ='FS all'!F142 -> 0 | F59: ='FS all'!G142 -> 0 | G59: ='FS all'!H142 -> 0 | H59: ='FS all'!I142 -> 0 | I59: ='FS all'!J142 -> 0 | J59: ='FS all'!K142 -> 0 | ... L59: ='FS all'!M142 -> 0

Sheet Summary
F3: Valuation Summary
F4: Figures in USD millions, unless told otherwise
C8: Recommendation | E8: BUY
C10: Current Price | E10: =DCF!E14 -> 226.19
C11: Target Price | E11: =DCF!I49 -> 292.99442
C12: Expected Return (%) | E12: =E11/E10-1 -> 0.29534647
C14: Shares Outstanding (M) | E14: =DCF!E15 -> 10721
C15: Market Capitalization (B) | E15: =(E10*E14)/1000 -> 2424.983
C16: 52-Week High | E16: ='Tear Sheet'!H18 -> 254
C17: 52-Week Low | E17: ='Tear Sheet'!G18 -> 167.32
C18: Earnings Per Share | E18: ='Tear Sheet'!C20 -> 7.08
C19: Price / Earnings | E19: ='Tear Sheet'!C21 -> 31.94774
C22: CAT Valuation summary from different methods
F24: Price per Share | K24: Equity Value | P24: Enterprise Value
D25: Valuation Method | F25: Low | G25: Median | H25: Mean | I25: High | K25: Low | L25: Median | M25: Mean | N25: High | P25: Low | Q25: Median | R25: Mean | S25: High
C26: 1 | D26: 52 Week Market High/Low | F26: =MIN('AMZN daily'!H3079:H3330) -> 24.1 | G26: =MEDIAN('AMZN daily'!H3079:H3330) -> 35.89 | H26: =AVERAGE('AMZN daily'!H3079:H3330) -> 34.730119 | I26: =MAX('AMZN daily'!H3079:H3330) -> 42.22 | K26: =F26*DCF!$E$15 -> 258376.1 | L26: =G26*DCF!$E$15 -> 384776.69 | M26: =H26*DCF!$E$15 -> 372341.61 | N26: =I26*DCF!$E$15 -> 452640.62 | P26: =K26+SUM(DCF!$E$44:$E$46) -> 857114.1 | Q26: =L26+SUM(DCF!$E$44:$E$46) -> 983514.69 | R26: =M26+SUM(DCF!$E$44:$E$46) -> 971079.61 | S26: =N26+SUM(DCF!$E$44:$E$46) -> 1051378.6
C27: =C26+1 -> 2 | D27: Base Discounted Cash Flow | F27: =DCF!$E$64 -> 184.16499 | G27: =DCF!$I$63 -> 292.99442 | H27: =DCF!$I$64 -> 318.23482 | I27: =DCF!$E$63 -> 628.85346 | K27: =F27*DCF!$E$15 -> 1974432.9 | L27: =G27*DCF!$E$15 -> 3141193.2 | M27: =H27*DCF!$E$15 -> 3411795.5 | N27: =I27*DCF!$E$15 -> 6741938 | P27: =K27+SUM(DCF!$E$44:$E$46) -> 2573170.9 | Q27: =L27+SUM(DCF!$E$44:$E$46) -> 3739931.2 | R27: =M27+SUM(DCF!$E$44:$E$46) -> 4010533.5 | S27: =N27+SUM(DCF!$E$44:$E$46) -> 7340676
C28: =C27+1 -> 3 | D28: Bull Discounted Cash Flow | F28: 163.15539 | G28: 291.61809 | H28: 333.37732 | I28: 823.84708 | K28: =F28*DCF!$E$15 -> 1749188.9 | L28: =G28*DCF!$E$15 -> 3126437.5 | M28: =H28*DCF!$E$15 -> 3574138.3 | N28: =I28*DCF!$E$15 -> 8832464.6 | P28: =K28+SUM(DCF!$E$44:$E$46) -> 2347926.9 | Q28: =L28+SUM(DCF!$E$44:$E$46) -> 3725175.5 | R28: =M28+SUM(DCF!$E$44:$E$46) -> 4172876.3 | S28: =N28+SUM(DCF!$E$44:$E$46) -> 9431202.6
C29: =C28+1 -> 4 | D29: Bear Discounted Cash Flow | F29: 116.74016 | G29: 212.05019 | H29: 242.89204 | I29: 605.52322 | K29: =F29*DCF!$E$15 -> 1251571.3 | L29: =G29*DCF!$E$15 -> 2273390.1 | M29: =H29*DCF!$E$15 -> 2604045.5 | N29: =I29*DCF!$E$15 -> 6491814.5 | P29: =K29+SUM(DCF!$E$44:$E$46) -> 1850309.3 | Q29: =L29+SUM(DCF!$E$44:$E$46) -> 2872128.1 | R29: =M29+SUM(DCF!$E$44:$E$46) -> 3202783.5 | S29: =N29+SUM(DCF!$E$44:$E$46) -> 7090552.5
C30: =C29+1 -> 5 | D30: EV/Sales | F30: {=TRANSPOSE(Multiples!R49:R52)} -> -44.41795 | G30: 483.26296 | H30: 331.15663 | I30: 656.07723 | K30: =F30*DCF!$E$15 -> -476204.84 | L30: =G30*DCF!$E$15 -> 5181062.1 | M30: =H30*DCF!$E$15 -> 3550330.3 | N30: =I30*DCF!$E$15 -> 7033804 | P30: =K30+SUM(DCF!$E$44:$E$46) -> 122533.16 | Q30: =L30+SUM(DCF!$E$44:$E$46) -> 5779800.1 | R30: =M30+SUM(DCF!$E$44:$E$46) -> 4149068.3 | S30: =N30+SUM(DCF!$E$44:$E$46) -> 7632542
C31: =C30+1 -> 6 | D31: EV/EBIT | F31: {=TRANSPOSE(Multiples!S49:S52)} -> -47.928597 | G31: 128.68395 | H31: 101.11661 | I31: 174.88787 | K31: =F31*DCF!$E$15 -> -513842.49 | L31: =G31*DCF!$E$15 -> 1379620.6 | M31: =H31*DCF!$E$15 -> 1084071.2 | N31: =I31*DCF!$E$15 -> 1874972.9 | P31: =K31+SUM(DCF!$E$44:$E$46) -> 84895.509 | Q31: =L31+SUM(DCF!$E$44:$E$46) -> 1978358.6 | R31: =M31+SUM(DCF!$E$44:$E$46) -> 1682809.2 | S31: =N31+SUM(DCF!$E$44:$E$46) -> 2473710.9
C32: =C31+1 -> 7 | D32: EV/EBITDA | F32: {=TRANSPOSE(Multiples!T49:T52)} -> -48.150495 | G32: 79.130389 | H32: 66.155933 | I32: 131.51332 | K32: =F32*DCF!$E$15 -> -516221.45 | L32: =G32*DCF!$E$15 -> 848356.9 | M32: =H32*DCF!$E$15 -> 709257.75 | N32: =I32*DCF!$E$15 -> 1409954.3 | P32: =K32+SUM(DCF!$E$44:$E$46) -> 82516.548 | Q32: =L32+SUM(DCF!$E$44:$E$46) -> 1447094.9 | R32: =M32+SUM(DCF!$E$44:$E$46) -> 1307995.8 | S32: =N32+SUM(DCF!$E$44:$E$46) -> 2008692.3
C33: =C32+1 -> 8 | D33: P/E | F33: {=TRANSPOSE(Multiples!U49:U52)} -> 16.772007 | G33: 190.68812 | H33: 116.41484 | I33: 261.38465 | K33: =F33*DCF!$E$15 -> 179812.69 | L33: =G33*DCF!$E$15 -> 2044367.3 | M33: =H33*DCF!$E$15 -> 1248083.5 | N33: =I33*DCF!$E$15 -> 2802304.8 | P33: =K33+SUM(DCF!$E$44:$E$46) -> 778550.69 | Q33: =L33+SUM(DCF!$E$44:$E$46) -> 2643105.3 | R33: =M33+SUM(DCF!$E$44:$E$46) -> 1846821.5 | S33: =N33+SUM(DCF!$E$44:$E$46) -> 3401042.8
C34: Low | F34: =MIN(F26:F33) -> -48.150495 | G34: =MIN(G26:G33) -> 35.89 | H34: =MIN(H26:H33) -> 34.730119 | I34: =MIN(I26:I33) -> 42.22 | K34: =MIN(K26:K33) -> -516221.45 | L34: =MIN(L26:L33) -> 384776.69 | M34: =MIN(M26:M33) -> 372341.61 | N34: =MIN(N26:N33) -> 452640.62 | P34: =MIN(P26:P33) -> 82516.548 | Q34: =MIN(Q26:Q33) -> 983514.69 | R34: =MIN(R26:R33) -> 971079.61 | S34: =MIN(S26:S33) -> 1051378.6
C35: Median | F35: =MEDIAN(F26:F33) -> 20.436004 | G35: =MEDIAN(G26:G33) -> 201.36915 | H35: =MEDIAN(H26:H33) -> 179.65344 | I35: =MEDIAN(I26:I33) -> 433.45393 | K35: =MEDIAN(K26:K33) -> 219094.39 | L35: =MEDIAN(L26:L33) -> 2158878.7 | M35: =MEDIAN(M26:M33) -> 1926064.5 | N35: =MEDIAN(N26:N33) -> 4647059.6 | P35: =MEDIAN(P26:P33) -> 817832.39 | Q35: =MEDIAN(Q26:Q33) -> 2757616.7 | R35: =MEDIAN(R26:R33) -> 2524802.5 | S35: =MEDIAN(S26:S33) -> 5245797.6
C36: Mean | F36: =AVERAGE(F26:F33) -> 45.554439 | G36: =AVERAGE(G26:G33) -> 214.28976 | H36: =AVERAGE(H26:H33) -> 193.00979 | I36: =AVERAGE(I26:I33) -> 415.53835 | K36: =AVERAGE(K26:K33) -> 488389.14 | L36: =AVERAGE(L26:L33) -> 2297400.5 | M36: =AVERAGE(M26:M33) -> 2069258 | N36: =AVERAGE(N26:N33) -> 4454986.7 | P36: =AVERAGE(P26:P33) -> 1087127.1 | Q36: =AVERAGE(Q26:Q33) -> 2896138.5 | R36: =AVERAGE(R26:R33) -> 2667996 | S36: =AVERAGE(S26:S33) -> 5053724.7
C37: High | F37: =MAX(F26:F33) -> 184.16499 | G37: =MAX(G26:G33) -> 483.26296 | H37: =MAX(H26:H33) -> 333.37732 | I37: =MAX(I26:I33) -> 823.84708 | K37: =MAX(K26:K33) -> 1974432.9 | L37: =MAX(L26:L33) -> 5181062.1 | M37: =MAX(M26:M33) -> 3574138.3 | N37: =MAX(N26:N33) -> 8832464.6 | P37: =MAX(P26:P33) -> 2573170.9 | Q37: =MAX(Q26:Q33) -> 5779800.1 | R37: =MAX(R26:R33) -> 4172876.3 | S37: =MAX(S26:S33) -> 9431202.6
E40: Football Field Scenario Analysis
E41: Bear Case | F41: =F29 -> 116.74016 | G41: =G29-F29 -> 95.310024 | H41: =G41+F41 -> 212.05019
E42: Bull Case | F42: =F28 -> 163.15539 | G42: =G28-F28 -> 128.4627 | H42: =G42+F42 -> 291.61809
E43: Base Case | F43: =F27 -> 184.16499 | G43: =G27-F27 -> 108.82943 | H43: =G43+F43 -> 292.99442

Sheet Actuals FS
D3: Historic Financial Statements
D4: Figures in USD millions, unless told otherwise
C8: As Reported Comprehensive Financial Statements
C10: 1. Balance sheet (B/S), as of year end | D10: 2024 | E10: =D10-1 -> 2023 | F10: =E10-1 -> 2022 | G10: =F10-1 -> 2021 | H10: =G10-1 -> 2020 | J10: NOTES:
C11: ASSETS
C12: Cash and cash equivalents | D12: 78779 | E12: 73387 | F12: 53888 | G12: 36220 | H12: 42122
C13: Marketable securities | D13: 22423 | E13: 13393 | F13: 16138 | G13: 59829 | H13: 42274
C14: Inventories | D14: 34214 | E14: 33318 | F14: 34405 | G14: 32640 | H14: 23795 | J14: Source: Company Information - Amazon Investor Relations
C15: Accounts receivable, net and other | D15: 55451 | E15: 52253 | F15: 42360 | G15: 32891 | H15: 24542
C16: Total current assets | D16: =SUM(D12:D15) -> 190867 | E16: =SUM(E12:E15) -> 172351 | F16: =SUM(F12:F15) -> 146791 | G16: =SUM(G12:G15) -> 161580 | H16: =SUM(H12:H15) -> 132733
C17: Property and equipment, net | D17: 252665 | E17: 204177 | F17: 186715 | G17: 160281 | H17: 113114
C18: Operating leases | D18: 76141 | E18: 72513 | F18: 66123 | G18: 56082 | H18: 37553
C19: Goodwill | D19: 23074 | E19: 22789 | F19: 20288 | G19: 15371 | H19: 15017
C20: Other assets | D20: 82147 | E20: 56024 | F20: 42758 | G20: 27235 | H20: 22778
C21: Total assets | D21: =SUM(D16,D17:D20) -> 624894 | E21: =SUM(E16,E17:E20) -> 527854 | F21: =SUM(F16,F17:F20) -> 462675 | G21: =SUM(G16,G17:G20) -> 420549 | H21: =SUM(H16,H17:H20) -> 321195
C23: LIABILITIES
C24: Accounts payable | D24: 94363 | E24: 84981 | F24: 79600 | G24: 78664 | H24: 72539
C25: Accrued expenses and other | D25: 66965 | E25: 64709 | F25: 62566 | G25: 51775 | H25: 44138
C26: Unearned revenue | D26: 18103 | E26: 15227 | F26: 13227 | G26: 11827 | H26: 9708
C27: Total current liabilities | D27: =SUM(D24:D26) -> 179431 | E27: =SUM(E24:E26) -> 164917 | F27: =SUM(F24:F26) -> 155393 | G27: =SUM(G24:G26) -> 142266 | H27: =SUM(H24:H26) -> 126385
C28: Long-term lease liabilities | D28: 78277 | E28: 77297 | F28: 72968 | G28: 67651 | H28: 52573
C29: Long-term debt | D29: 52623 | E29: 58314 | F29: 67150 | G29: 48744 | H29: 31816
C30: Other long-term liabilities | D30: 28593 | E30: 25451 | F30: 21121 | G30: 23643 | H30: 17017
C31: Commitments and contingencies (Note 7) | D31: 0 | E31: 0 | F31: 0 | G31: 0 | H31: 0
C32: Total liabilities | D32: =SUM(D27,D28:D31) -> 338924 | E32: =SUM(E27,E28:E31) -> 325979 | F32: =SUM(F27,F28:F31) -> 316632 | G32: =SUM(G27,G28:G31) -> 282304 | H32: =SUM(H27,H28:H31) -> 227791
C34: SHAREHOLDERS EQUITY
C35: Preferred stock ($0.01 par value; 500 shares authorized) | D35: 0 | E35: 0 | F35: 0 | G35: 0 | H35: 0
C36: Common stock ($0.01 par value; 100,000 shares authorized) | D36: 111 | E36: 109 | F36: 108 | G36: 106 | H36: 5
C37: Treasury stock, at cost | D37: -7837 | E37: -7837 | F37: -7837 | G37: -1837 | H37: -1837
C38: Additional paid-in capital | D38: 120864 | E38: 99025 | F38: 75066 | G38: 55437 | H38: 42865
C39: Accumulated other comprehensive income (loss) | D39: -34 | E39: -3040 | F39: -4487 | G39: -1376 | H39: -180
C40: Retained earnings | D40: 172866 | E40: 113618 | F40: 83193 | G40: 85915 | H40: 52551
C41: Total shareholders' equity | D41: =SUM(D35:D40) -> 285970 | E41: =SUM(E35:E40) -> 201875 | F41: =SUM(F35:F40) -> 146043 | G41: =SUM(G35:G40) -> 138245 | H41: =SUM(H35:H40) -> 93404
C42: Total liabilities & shareholders' equity | D42: =D41+D32 -> 624894 | E42: =E41+E32 -> 527854 | F42: =F41+F32 -> 462675 | G42: =G41+G32 -> 420549 | H42: =H41+H32 -> 321195
C44: 2. Income Statement for the year ended | D44: =D10 -> 2024 | E44: =E10 -> 2023 | F44: =F10 -> 2022 | G44: =G10 -> 2021 | H44: =H10 -> 2020
C45: Net product sales | D45: 272311 | E45: 255887 | F45: 242901 | G45: 241787 | H45: 215915
C46: Net service sales | D46: 365648 | E46: 318898 | F46: 271082 | G46: 228035 | H46: 170149
C47: Total net sales | D47: =SUM(D45:D46) -> 637959 | E47: =SUM(E45:E46) -> 574785 | F47: =SUM(F45:F46) -> 513983 | G47: =SUM(G45:G46) -> 469822 | H47: =SUM(H45:H46) -> 386064
C48: Cost of sales | D48: 326288 | E48: 304739 | F48: 288831 | G48: 272344 | H48: 233307
C49: Fulfillment | D49: 98505 | E49: 90619 | F49: 84299 | G49: 75111 | H49: 58517
C50: Technology and infrastructure | D50: 88544 | E50: 85622 | F50: 73213 | G50: 56052 | H50: 42740
C51: Sales and marketing | D51: 43907 | E51: 44370 | F51: 42238 | G51: 32551 | H51: 22008
C52: General and administrative | D52: 11359 | E52: 11816 | F52: 11891 | G52: 8823 | H52: 6668
C53: Other operating expense (income), net | D53: 763 | E53: 767 | F53: 1263 | G53: 62 | H53: -75
C54: Total operating costs | D54: =SUM(D48:D53) -> 569366 | E54: =SUM(E48:E53) -> 537933 | F54: =SUM(F48:F53) -> 501735 | G54: =SUM(G48:G53) -> 444943 | H54: =SUM(H48:H53) -> 363165
C55: Operating profit
C56: Operating income | D56: 68593 | E56: 36852 | F56: 12248 | G56: 24879 | H56: 22899
C57: Interest income | D57: 4677 | E57: 2949 | F57: 989 | G57: 448 | H57: 555
C58: Interest expense | D58: -2406 | E58: -3182 | F58: -2367 | G58: -1809 | H58: -1647
C59: Other income (expense), net | D59: -2250 | E59: 938 | F59: -16806 | G59: 14633 | H59: 2371
C60: Total non-operating income (expense) | D60: 21 | E60: 705 | F60: -18184 | G60: 13272 | H60: 1279
C61: Income (loss) before income taxes | D61: 68614 | E61: 37557 | F61: -5936 | G61: 38151 | H61: 24178
C62: Benefit (provision) for income taxes | D62: -9265 | E62: -7120 | F62: 3217 | G62: -4791 | H62: -2863
C63: Equity-method investment activity, net of tax | D63: -101 | E63: -12 | F63: -3 | G63: 4 | H63: 16
C64: Net income (loss) | D64: =SUM(D61:D63) -> 59248 | E64: =SUM(E61:E63) -> 30425 | F64: =SUM(F61:F63) -> -2722 | G64: =SUM(G61:G63) -> 33364 | H64: =SUM(H61:H63) -> 21331
C65: Basic earnings per share | D65: 5.66 | E65: 2.95 | F65: -0.27 | G65: 65.96 | H65: 42.64
C66: Diluted earnings per share | D66: 5.53 | E66: 2.9 | F66: -0.27 | G66: 64.81 | H66: 41.83
C67: Weighted average shares outstanding - basic | D67: 10473 | E67: 10304 | F67: 10189 | G67: 506 | H67: 500
C68: Weighted average shares outstanding - diluted | D68: 10721 | E68: 10492 | F68: 10189 | G68: 515 | H68: 510
C70: 3. Statement of Cash Flows, for the year ended | D70: =D44 -> 2024 | E70: =E44 -> 2023 | F70: =F44 -> 2022 | G70: =G44 -> 2021 | H70: =H44 -> 2020
C71: CASH, CASH EQUIVALENTS, AND RESTRICTED CASH, BEGINNING OF PERIOD | D71: 73890 | E71: 54253 | F71: 36477 | G71: 42377 | H71: 36410
C72: OPERATING ACTIVITIES:
C73: Net income (loss) | D73: 59248 | E73: 30425 | F73: -2722 | G73: 33364 | H73: 21331
C74: Adjustments to reconcile net income (loss) to net cash from operating activities:
C75: Depreciation and amortization of property and equipment and capitalized content costs, operating lease assets, and other | D75: 52795 | E75: 48663 | F75: 41921 | G75: 34433 | H75: 25180
C76: Stock-based compensation | D76: 22011 | E76: 24023 | F76: 19621 | G76: 12757 | H76: 9208
C77: Non-operating expense (income), net | D77: 2012 | E77: -748 | F77: 16966 | G77: -14306 | H77: -2582
C78: Deferred income taxes | D78: -4648 | E78: -5876 | F78: -8148 | G78: -310 | H78: -554
C79: Changes in operating assets and liabilities:
C80: Inventories | D80: -1884 | E80: 1449 | F80: -2592 | G80: -9487 | H80: -2849
C81: Accounts receivable, net and other | D81: -3249 | E81: -8348 | F81: -8622 | G81: -18163 | H81: -8169
C82: Other assets | D82: -14483 | E82: -12265 | F82: -13275 | G82: 0 | H82: 0
C83: Accounts payable | D83: 2972 | E83: 5473 | F83: 2945 | G83: 3602 | H83: 17480
C84: Accrued expenses and other | D84: -2904 | E84: -2428 | F84: -1558 | G84: 2123 | H84: 5754
C85: Unearned revenue | D85: 4007 | E85: 4578 | F85: 2216 | G85: 2314 | H85: 1265
C86: Net cash provided by (used in) operating activities | D86: =SUM(D73:D85) -> 115877 | E86: =SUM(E73:E85) -> 84946 | F86: =SUM(F73:F85) -> 46752 | G86: =SUM(G73:G85) -> 46327 | H86: =SUM(H73:H85) -> 66064
C87: Purchases of property and equipment | D87: -82999 | E87: -52729 | F87: -63645 | G87: -61053 | H87: -40140
C88: Proceeds from property and equipment sales and incentives | D88: 5341 | E88: 4596 | F88: 5324 | G88: 5657 | H88: 5096
C89: Acquisitions, net of cash acquired, non-marketable investments, and other | D89: -7082 | E89: -5839 | F89: -8316 | G89: -1985 | H89: -2325
C90: Sales and maturities of marketable securities | D90: 16403 | E90: 5627 | F90: 31601 | G90: 59384 | H90: 50237
C91: Purchases of marketable securities | D91: -26005 | E91: -1488 | F91: -2565 | G91: -60157 | H91: -72479
C92: Net cash flows from investing activities | D92: =SUM(D87:D91) -> -94342 | E92: =SUM(E87:E91) -> -49833 | F92: =SUM(F87:F91) -> -37601 | G92: =SUM(G87:G91) -> -58154 | H92: =SUM(H87:H91) -> -59611
C93: Common stock repurchased | D93: 0 | E93: 0 | F93: -6000 | G93: 0 | H93: 0
C94: Proceeds from short-term debt, and other | D94: 5142 | E94: 18129 | F94: 41553 | G94: 7956 | H94: 6796
C95: Repayments of short-term debt, and other | D95: -5060 | E95: -25677 | F95: -37554 | G95: -7753 | H95: -6177
C96: Proceeds from long-term debt | D96: 0 | E96: 0 | F96: 21166 | G96: 19003 | H96: 10525
C97: Repayments of long-term debt | D97: -9182 | E97: -3676 | F97: -1258 | G97: -1590 | H97: -1553
C98: Principal repayments of finance leases | D98: -2043 | E98: -4384 | F98: -7941 | G98: -11163 | H98: -10642
C99: Principal repayments of financing obligations | D99: -669 | E99: -271 | F99: -248 | G99: -162 | H99: -53
C100: Net cash flows from financing activities | D100: =SUM(D93:D99) -> -11812 | E100: =SUM(E93:E99) -> -15879 | F100: =SUM(F93:F99) -> 9718 | G100: =SUM(G93:G99) -> 6291 | H100: =SUM(H93:H99) -> -1104
C101: Foreign currency effect on cash, cash equivalents, and restricted cash | D101: -1301 | E101: 403 | F101: -1093 | G101: -364 | H101: 618
C102: Increase (decrease) in cash, cash equivalents & restricted cash | D102: =SUM(D86,D92,D100,D101) -> 8422 | E102: =SUM(E86,E92,E100,E101) -> 19637 | F102: =SUM(F86,F92,F100,F101) -> 17776 | G102: =SUM(G86,G92,G100,G101) -> -5900 | H102: =SUM(H86,H92,H100,H101) -> 5967
C103: CASH, CASH EQUIVALENTS, AND RESTRICTED CASH, END OF PERIOD | D103: =D71+D86+D92+D100+D101 -> 82312 | E103: =E71+E86+E92+E100+E101 -> 73890 | F103: =F71+F86+F92+F100+F101 -> 54253 | G103: =G71+G86+G92+G100+G101 -> 36477 | H103: =H71+H86+H92+H100+H101 -> 42377
C106: Compariative Analysis with Ratios
D108: =D70 -> 2024 | E108: =E70 -> 2023 | F108: =F70 -> 2022 | G108: =G70 -> 2021 | H108: =H70 -> 2020
C109: Liquidity (Safety)
C110: Current ratio (x) | D110: =D16/D27 -> 1.0637348 | E110: =E16/E27 -> 1.0450772 | F110: =F16/F27 -> 0.94464358 | G110: =G16/G27 -> 1.1357598 | H110: =H16/H27 -> 1.0502275
C111: Quick ratio (x) | D111: =(D12+D13+D15)/D27 -> 0.87305427 | E111: =(E12+E13+E15)/E27 -> 0.84304832 | F111: =(F12+F13+F15)/F27 -> 0.72323721 | G111: =(G12+G13+G15)/G27 -> 0.9063304 | H111: =(H12+H13+H15)/H27 -> 0.86195355
C112: Accounts Receivable Turnover (x) | D112: =D47/D15 -> 11.504914 | E112: =E47/E15 -> 11.000038 | F112: =F47/F15 -> 12.133687 | G112: =G47/G15 -> 14.284211 | H112: =H47/H15 -> 15.730747
C113: Days in Receivable | D113: =365/D112 -> 31.725573 | E113: =365/E112 -> 33.181703 | F113: =365/F112 -> 30.08154 | G113: =365/G112 -> 25.552688 | H113: =365/H112 -> 23.202966
...

Sheet HWMS Model
F2: AMZN Quarterly Sales Forecasting: Holt-Winters Multiplicative Seasonal (HWMS) Model
F3: Figures in USD millions, unless told otherwise
D7: Sensitivity Factors & Forecast Error
D8: Alpha | G8: 0.72757044
D9: Beta | G9: 0.19620896
D10: Gamma | G10: 1
D11: Mean Squared Error (MSE) | G11: =SUMXMY2(E20:E56,I20:I56)/COUNT(E20:E56) -> 19956348
D12: Mean Absolute % Error (MAPE) | G12: {=AVERAGE(ABS(E20:E56-I20:I56)/E20:E56)} -> 0.042656503
D14: Sales Forecasting
D15: Date | E15: Sales | F15: Level | G15: Trend | H15: Seasonal | I15: Forecast
C16: Actual | D16: 42277 | E16: 25358 | H16: =E16/$F$19 -> 0.8408034
D17: 42369 | E17: 35747 | H17: =E17/$F$19 -> 1.1852748
D18: 42460 | E18: 29128 | H18: =E18/$F$19 -> 0.96580651
D19: 42551 | E19: 30404 | F19: =AVERAGE(E16:E19) -> 30159.25 | G19: 0 | H19: =E19/$F$19 -> 1.0081153
D20: 42643 | E20: 32714 | F20: =$G$8*(E20/H16)+(1-$G$8)*(F19+G19) -> 36524.6 | G20: =$G$9*(F20-F19)+(1-$G$9)*G19 -> 1248.9387 | H20: =$G$10*(E20/F20)+(1-$G$10)*H16 -> 0.89567031 | I20: =SUM(F19:G19)*H16 -> 25358
D21: 42735 | E21: 43741 | F21: =$G$8*(E21/H17)+(1-$G$8)*(F20+G20) -> 37140.653 | G21: =$G$9*(F21-F20)+(1-$G$9)*G20 -> 1124.7609 | H21: =$G$10*(E21/F21)+(1-$G$10)*H17 -> 1.1777122 | I21: =SUM(F20:G20)*H17 -> 44772.025
D22: 42825 | E22: 35714 | F22: =$G$8*(E22/H18)+(1-$G$8)*(F21+G21) -> 37329.036 | G22: =$G$9*(F22-F21)+(1-$G$9)*G21 -> 941.03514 | H22: =$G$10*(E22/F22)+(1-$G$10)*H18 -> 0.95673512 | I22: =SUM(F21:G21)*H18 -> 36956.986
D23: 42916 | E23: 37955 | F23: =$G$8*(E23/H19)+(1-$G$8)*(F22+G22) -> 37818.537 | G23: =$G$9*(F23-F22)+(1-$G$9)*G22 -> 852.43996 | H23: =$G$10*(E23/F23)+(1-$G$10)*H19 -> 1.0036084 | I23: =SUM(F22:G22)*H19 -> 38580.643
D24: 43008 | E24: 43744 | F24: =$G$8*(E24/H20)+(1-$G$8)*(F23+G23) -> 46069.22 | G24: =$G$9*(F24-F23)+(1-$G$9)*G23 -> 2304.0417 | H24: =$G$10*(E24/F24)+(1-$G$10)*H20 -> 0.94952768 | I24: =SUM(F23:G23)*H20 -> 34636.445
D25: 43100 | E25: 60453 | F25: =$G$8*(E25/H21)+(1-$G$8)*(F24+G24) -> 50525.136 | G25: =$G$9*(F25-F24)+(1-$G$9)*G24 -> 2726.2586 | H25: =$G$10*(E25/F25)+(1-$G$10)*H21 -> 1.1964936 | I25: =SUM(F24:G24)*H21 -> 56969.78
D26: 43190 | E26: 51042 | F26: =$G$8*(E26/H22)+(1-$G$8)*(F25+G25) -> 53323.275 | G26: =$G$9*(F26-F25)+(1-$G$9)*G25 -> 2740.3621 | H26: =$G$10*(E26/F26)+(1-$G$10)*H22 -> 0.95721803 | I26: =SUM(F25:G25)*H22 -> 50947.479
D27: 43281 | E27: 52886 | F27: =$G$8*(E27/H23)+(1-$G$8)*(F26+G26) -> 53613.337 | G27: =$G$9*(F27-F26)+(1-$G$9)*G26 -> 2259.5914 | H27: =$G$10*(E27/F27)+(1-$G$10)*H23 -> 0.98643365 | I27: =SUM(F26:G26)*H23 -> 56265.936
D28: 43373 | E28: 56576 | F28: =$G$8*(E28/H24)+(1-$G$8)*(F27+G27) -> 58572.491 | G28: =$G$9*(F28-F27)+(1-$G$9)*G27 -> 2789.2697 | H28: =$G$10*(E28/F28)+(1-$G$10)*H24 -> 0.96591419 | I28: =SUM(F27:G27)*H24 -> 53052.892
D29: 43465 | E29: 72383 | F29: =$G$8*(E29/H25)+(1-$G$8)*(F28+G28) -> 60731.813 | G29: =$G$9*(F29-F28)+(1-$G$9)*G28 -> 2665.6684 | H29: =$G$10*(E29/F29)+(1-$G$10)*H25 -> 1.1918465 | I29: =SUM(F28:G28)*H25 -> 73418.952
D30: 43555 | E30: 59700 | F30: =$G$8*(E30/H26)+(1-$G$8)*(F29+G29) -> 62648.633 | G30: =$G$9*(F30-F29)+(1-$G$9)*G29 -> 2518.7376 | H30: =$G$10*(E30/F30)+(1-$G$10)*H26 -> 0.9529338 | I30: =SUM(F29:G29)*H26 -> 60685.212
D31: 43646 | E31: 63404 | F31: =$G$8*(E31/H27)+(1-$G$8)*(F30+G30) -> 64518.829 | G31: =$G$9*(F31-F30)+(1-$G$9)*G30 -> 2391.4879 | H31: =$G$10*(E31/F31)+(1-$G$10)*H27 -> 0.98272088 | I31: =SUM(F30:G30)*H27 -> 64283.287
... D56: 45930 | E56: 180169 | F56: =$G$8*(E56/H52)+(1-$G$8)*(F55+G55) -> 176956.24 | G56: =$G$9*(F56-F55)+(1-$G$9)*G55 -> 4887.8339 | H56: =$G$10*(E56/F56)+(1-$G$10)*H52 -> 1.0181557 | I56: =SUM(F55:G55)*H52 -> 174112.53
C57: Forecast | D57: 46022 | I57: =($F$56+$G$56*(ROW()-ROW($I$56)))*H52 -> 183450.04
D58: 46112 | I58: =($F$56+$G$56*(ROW()-ROW($I$56)))*H53 -> 217630.42
D59: 46203 | I59: =($F$56+$G$56*(ROW()-ROW($I$56)))*H54 -> 184178.6
D60: 46295 | I60: =($F$56+$G$56*(ROW()-ROW($I$56)))*H56 -> 200075.3
D61: FY 2025 | I61: =SUM(I57:I60) -> 785334.36
D63: 2023 | E63: =E77 -> 1128.9975
D64: 2029 | E64: =E76 -> 1026.3613
D65: 2028 | E65: =E75 -> 933.05575
D66: 2027 | E66: =E74 -> 856.01445
D67: 26 Q3 | E67: =I60/1000 -> 200.0753
D68: 26 Q2 | E68: =I59/1000 -> 184.1786
D69: 26 Q1 | E69: =I58/1000 -> 217.63042
D70: 25 Q4 | E70: =I57/1000 -> 183.45004
D74: 2024 | E74: {=TRANSPOSE(Revenue!J33:M33)} -> 856.01445
D75: 2025 | E75: 933.05575
D76: 2026 | E76: 1026.3613
D77: 2027 | E77: 1128.9975

Sheet Revenue
D2: Revenue Breakdown & Projections
D3: Figures in USD millions, unless told otherwise
C30: Scenario Forecasted Revenues | O30: NOTES & SOURCES:
C32: In $ billions | D32: 2020 | E32: =D32+1 -> 2021 | F32: =E32+1 -> 2022 | G32: =F32+1 -> 2023 | H32: =G32+1 -> 2024 | I32: =H32+1 -> 2025 | J32: =I32+1 -> 2026 | K32: =J32+1 -> 2027 | L32: =K32+1 -> 2028 | M32: =L32+1 -> 2029 | O32: 5yr CAGR
C33: Base Case Revenues | D33: =(D52)/1000 -> 386.064 | E33: =(E52)/1000 -> 469.822 | F33: =(F52)/1000 -> 513.983 | G33: =(G52)/1000 -> 574.785 | H33: =(H52)/1000 -> 637.959 | I33: ='HWMS Model'!I61/1000 -> 785.33436 | J33: =I33*(1+J34) -> 856.01445 | K33: =J33*(1+K34) -> 933.05575 | L33: =K33*(1+L34) -> 1026.3613 | M33: =L33*(1+M34) -> 1128.9975 | O33: =RATE(5,,H33,-M33) -> 0.12093399
C34: Growth Rate (%) | E34: =E33/D33-1 -> 0.21695367 | F34: =F33/E33-1 -> 0.093995173 | G34: =G33/F33-1 -> 0.11829574 | H34: =H33/G33-1 -> 0.10990892 | I34: =I33/H33-1 -> 0.23101071 | J34: =Scenarios!F18 -> 0.09 | K34: =Scenarios!G18 -> 0.09 | L34: =Scenarios!H18 -> 0.1 | M34: =Scenarios!I18 -> 0.1
C35: Bull Case Revenues | D35: =D33 -> 386.064 | E35: =E33 -> 469.822 | F35: =F33 -> 513.983 | G35: =G33 -> 574.785 | H35: =H33 -> 637.959 | I35: =I33*(1+Scenarios!E19) -> 871.72114 | J35: =I35*(1+J36) -> 993.7621 | K35: =J35*(1+K36) -> 1132.8888 | L35: =K35*(1+L36) -> 1280.1643 | M35: =L35*(1+M36) -> 1446.5857 | O35: =RATE(5,,H35,-M35) -> 0.17790504
C36: Growth Rate (%) | E36: =E35/D35-1 -> 0.21695367 | F36: =F35/E35-1 -> 0.093995173 | G36: =G35/F35-1 -> 0.11829574 | H36: =H35/G35-1 -> 0.10990892 | I36: =I35/H35-1 -> 0.36642188 | J36: =Scenarios!F19 -> 0.14 | K36: =Scenarios!G19 -> 0.14 | L36: =Scenarios!H19 -> 0.13 | M36: =Scenarios!I19 -> 0.13
C37: Bear Case Revenues | D37: =D35 -> 386.064 | E37: =E35 -> 469.822 | F37: =F35 -> 513.983 | G37: =G35 -> 574.785 | H37: =H35 -> 637.959 | I37: =I33*(1+Scenarios!E20) -> 824.60108 | J37: =I37*(1+J38) -> 874.07714 | K37: =J37*(1+K38) -> 926.52177 | L37: =K37*(1+L38) -> 991.37829 | M37: =L37*(1+M38) -> 1060.7748 | O37: =RATE(5,,H37,-M37) -> 0.10704706
C38: Growth Rate (%) | E38: =E37/D37-1 -> 0.21695367 | F38: =F37/E37-1 -> 0.093995173 | G38: =G37/F37-1 -> 0.11829574 | H38: =H37/G37-1 -> 0.10990892 | I38: =I37/H37-1 -> 0.29256124 | J38: =Scenarios!F20 -> 0.06 | K38: =Scenarios!G20 -> 0.06 | L38: =Scenarios!H20 -> 0.07 | M38: =Scenarios!I20 -> 0.07
C40: AWS Remaining Performance Obligations (RPO)
C42: In $ billions | D42: 2020 | E42: =D42+1 -> 2021 | F42: =E42+1 -> 2022 | G42: =F42+1 -> 2023 | H42: =G42+1 -> 2024 | J42: 18 - 22 CAGR | L42: 19 - 22 CAGR
C43: AWS RPO (Backlog) | D43: 50000 | E43: 80000 | F43: 110400 | G43: 155700 | H43: 177000 | J43: =RATE(5,,D43,-H43) -> 0.28765836 | L43: =RATE(4,,E43,-H43) -> 0.21960956 | O43: Source: Company Information
C44: Growth Rate (%) | F44: =F43/E43-1 -> 0.38 | G44: =G43/F43-1 -> 0.41032609 | H44: =H43/G43-1 -> 0.13680154
E45: =E43/D43-1 -> 0.6
C46: Revenues by Business Segment, Forecasted with Industry Expectations
D48: 2020 | E48: =D48+1 -> 2021 | F48: =E48+1 -> 2022 | G48: =F48+1 -> 2023 | H48: =G48+1 -> 2024 | I48: =H48+1 -> 2025 | J48: =I48+1 -> 2026 | K48: =J48+1 -> 2027 | L48: =K48+1 -> 2028 | M48: =L48+1 -> 2029
C49: North America | D49: 236282 | E49: 279833 | F49: 315880 | G49: 352828 | H49: 387497 | I49: =H49*(1+I65) -> 395467.07 | J49: =I49*(1+J65) -> 403221.32 | K49: =J49*(1+K65) -> 410739.68 | L49: =K49*(1+L65) -> 418002.27 | M49: =L49*(1+M65) -> 425393.27 | O49: Following US government infrastructure spending, adjusted to gradual increase in market share
C50: International | D50: 104412 | E50: 127787 | F50: 118007 | G50: 131200 | H50: 142906 | I50: =H50*(1+I67) -> 150480.02 | J50: =I50*(1+J67) -> 158154.5 | K50: =J50*(1+K67) -> 166062.22 | L50: =K50*(1+L67) -> 174697.46 | M50: =L50*(1+M67) -> 183607.03 | O50: Following demand for critical minerals
C51: AWS | D51: 45370 | E51: 62202 | F51: 80096 | G51: 90757 | H51: 107556 | I51: =H51*(1+I69) -> 116707.61 | J51: =I51*(1+J69) -> 127124.13 | K51: =J51*(1+K69) -> 135993.26 | L51: =K51*(1+L69) -> 146066.83 | M51: =L51*(1+M69) -> 155622.61 | O51: Following demand for engine turbine manufacturing in the US, adjusted to gradual increase in market share
C52: Total Revenues | D52: =SUM(D49:D51) -> 386064 | E52: =SUM(E49:E51) -> 469822 | F52: =SUM(F49:F51) -> 513983 | G52: =SUM(G49:G51) -> 574785 | H52: =SUM(H49:H51) -> 637959 | I52: =SUM(I49:I51) -> 662654.69 | J52: =SUM(J49:J51) -> 688499.96 | K52: =SUM(K49:K51) -> 712795.16 | ... M52: =SUM(M49:M51) -> 764622.91
C53: Growth Rate (%) | E53: =E52/D52-1 -> 0.21695367 | F53: =F52/E52-1 -> 0.093995173 | G53: =G52/F52-1 -> 0.11829574 | H53: =H52/G52-1 -> 0.10990892 | I53: =I52/H52-1 -> 0.038710469 | J53: =J52/I52-1 -> 0.039002611 | K53: =K52/J52-1 -> 0.035287158 | L53: =L52/K52-1 -> 0.036435991 | M53: =M52/L52-1 -> 0.034999347
C55: As % of Total | D55: 2020 | E55: =D55+1 -> 2021 | F55: =E55+1 -> 2022 | G55: =F55+1 -> 2023 | H55: =G55+1 -> 2024 | I55: =H55+1 -> 2025 | J55: =I55+1 -> 2026 | K55: =J55+1 -> 2027 | L55: =K55+1 -> 2028 | M55: =L55+1 -> 2029
C56: North America | D56: =D49/(D$52) -> 0.61202806 | E56: =E49/(E$52) -> 0.59561494 | F56: =F49/(F$52) -> 0.61457286 | G56: =G49/(G$52) -> 0.61384344 | H56: =H49/(H$52) -> 0.6074011 | I56: =I49/(I$52) -> 0.59679207 | J56: =J49/(J$52) -> 0.58565192 | K56: =K49/(K$52) -> 0.57623803 | ... M56: =M49/(M$52) -> 0.55634387
C57: International | D57: =D50/(D$52) -> 0.27045257 | E57: =E50/(E$52) -> 0.27199024 | F57: =F50/(F$52) -> 0.2295932 | G57: =G50/(G$52) -> 0.22825926 | H57: =H50/(H$52) -> 0.22400499 | I57: =I50/(I$52) -> 0.22708663 | J57: =J50/(J$52) -> 0.2297088 | K57: =K50/(K$52) -> 0.23297328 | ... M57: =M50/(M$52) -> 0.24012756
C58: AWS | D58: =D51/(D$52) -> 0.11751938 | E58: =E51/(E$52) -> 0.13239482 | F58: =F51/(F$52) -> 0.15583395 | G58: =G51/(G$52) -> 0.1578973 | H58: =H51/(H$52) -> 0.16859391 | I58: =I51/(I$52) -> 0.1761213 | J58: =J51/(J$52) -> 0.18463928 | K58: =K51/(K$52) -> 0.1907887 | ... M58: =M51/(M$52) -> 0.20352857
C59: Total Revenues | D59: =SUM(D56:D58) -> 1 | E59: =SUM(E56:E58) -> 1 | F59: =SUM(F56:F58) -> 1 | G59: =SUM(G56:G58) -> 1 | H59: =SUM(H56:H58) -> 1 | I59: =SUM(I56:I58) -> 1 | J59: =SUM(J56:J58) -> 1 | K59: =SUM(K56:K58) -> 1 | ... M59: =SUM(M56:M58) -> 1
C61: Economic Indicators
D63: 2020 | E63: =D63+1 -> 2021 | F63: =E63+1 -> 2022 | G63: =F63+1 -> 2023 | H63: =G63+1 -> 2024 | I63: =H63+1 -> 2025 | J63: =I63+1 -> 2026 | K63: =J63+1 -> 2027 | L63: =K63+1 -> 2028 | M63: =L63+1 -> 2029
C64: Real PCE (NA Driver) | D64: 13597 | E64: 14792 | F64: 15237 | G64: 15628 | H64: 16089 | I64: =H64*(1+2.1%) -> 16426.869 | J64: =I64*(1+2%) -> 16755.406 | K64: =J64*(1+1.9%) -> 17073.759 | L64: =K64*(1+1.8%) -> 17381.087 | M64: =L64*(1+1.8%) -> 17693.946 | O64: The Congressional Budget Office (CBO) and Federal Reserve consensus forecast US real GDP and consumption to settle at a long-run trend of 1.8% for the 2027–2031 period.
C65: PCE Growth Rate | E65: =1-D64/E64 -> 0.080786912 | F65: =1-E64/F64 -> 0.029205224 | G65: =1-F64/G64 -> 0.025019196 | H65: =1-G64/H64 -> 0.028653117 | I65: =1-H64/I64 -> 0.020568071 | J65: =1-I64/J64 -> 0.019607843 | K65: =1-J64/K64 -> 0.018645731 | L65: =1-K64/L64 -> 0.017681729 | M65: =1-L64/M64 -> 0.017681729 | O65: Source: CBO/BEA
C66: Global GDP (Int Driver) | D66: 85200 | E66: 96500 | F66: 100500 | G66: 104800 | H66: 111300 | I66: =H66*(1+5.3%) -> 117198.9 | J66: =I66*(1+5.1%) -> 123176.04 | K66: =J66*(1+5%) -> 129334.85 | L66: =K66*(1+5.2%) -> 136060.26 | M66: =L66*(1+5.1%) -> 142999.33 | O66: The global economy saw a sharp nominal increase in 2021 as activities resumed and inflation rose. From 2024 onwards, growth is expected to stabilize around 5-6% annually, driven by a real GDP growth of approximately 3.2% and moderating inflation. By 2028, the global economy is projected to surpass $136 trillion, reflecting continued expansion in emerging markets and steady growth in advanced economies like the U.S. and China.
C67: Growth in GDP | E67: =E66/D66-1 -> 0.13262911 | F67: =F66/E66-1 -> 0.041450777 | G67: =G66/F66-1 -> 0.04278607 | H67: =H66/G66-1 -> 0.062022901 | I67: =I66/H66-1 -> 0.053 | J67: =J66/I66-1 -> 0.051 | K67: =K66/J66-1 -> 0.05 | L67: =L66/K66-1 -> 0.052 | M67: =M66/L66-1 -> 0.051 | O67: Source: CBO/IMF
C68: Global IT Spending (AWS Driver) | D68: 3695 | E68: 4241 | F68: 4533 | G68: 4693 | H68: 5069 | I68: =H68*(1+9.3%) -> 5540.417 | J68: =I68*(1+9.8%) -> 6083.3779 | K68: =J68*(1+7.5%) -> 6539.6312 | L68: =K68*(1+8%) -> 7062.8017 | M68: =L68*(1+7%) -> 7557.1978 | O68: Global IT spending is forecast to accelerate primarily due to a surge in investment for data center systems and servers to support Generative AI infrastructure, alongside continued double-digit growth in software and IT services as enterprises integrate these technologies.
C69: Growth in IT Spending | E69: =1-D68/E68 -> 0.12874322 | F69: =1-E68/F68 -> 0.064416501 | G69: =1-F68/G68 -> 0.03409333 | H69: =1-G68/H68 -> 0.074176366 | I69: =1-H68/I68 -> 0.085086917 | J69: =1-I68/J68 -> 0.089253188 | K69: =1-J68/K68 -> 0.069767442 | L69: =1-K68/L68 -> 0.074074074 | M69: =1-L68/M68 -> 0.065420561 | O69: Source: Gartner
C71: Revenues by Geographic Presence, Forecasted with Regional GDP Expectations
D73: 2020 | E73: =D73+1 -> 2021 | F73: =E73+1 -> 2022 | G73: =F73+1 -> 2023 | H73: =G73+1 -> 2024 | I73: =H73+1 -> 2025 | J73: =I73+1 -> 2026 | K73: =J73+1 -> 2027 | L73: =K73+1 -> 2028 | M73: =L73+1 -> 2029
C74: United States | D74: 263520 | E74: 314006 | F74: 356113 | G74: 395637 | H74: 438015 | I74: =H74*(1+I93) -> 447651.33 | J74: =I74*(1+J93) -> 457052.01 | K74: =J74*(1+K93) -> 465736 | L74: =K74*(1+L93) -> 474119.24 | M74: =L74*(1+M93) -> 482653.39
C75: Germany | D75: 29565 | E75: 31645 | F75: 33598 | G75: 37588 | H75: 40856 | I75: =H75*(1+I94) -> 41182.848 | J75: =I75*(1+J94) -> 41677.042 | K75: =J75*(1+K94) -> 42260.521 | L75: =K75*(1+L94) -> 42809.908 | M75: =L75*(1+M94) -> 43366.436
C76: United Kingdom | D76: 26483 | E76: 27907 | F76: 30074 | G76: 33591 | H76: 37855 | I76: =H76*(1+I95) -> 38422.825 | J76: =I76*(1+J95) -> 38922.322 | K76: =J76*(1+K95) -> 39467.234 | L76: =K76*(1+L95) -> 40059.243 | M76: =L76*(1+M95) -> 40660.131
C77: Japan | D77: 20461 | E77: 23071 | F77: 24396 | G77: 26002 | H77: 27401 | I77: =H77*(1+I96) -> 27702.411 | J77: =I77*(1+J96) -> 27868.625 | K77: =J77*(1+K96) -> 28035.837 | L77: =K77*(1+L96) -> 28176.016 | M77: =L77*(1+M96) -> 28316.896
C78: Rest Of World | D78: 46035 | E78: 73193 | F78: 69802 | G78: 81967 | H78: 93832 | I78: =H78*(1+I97) -> 96834.624 | J78: =I78*(1+J97) -> 99836.497 | K78: =J78*(1+K97) -> 102831.59 | L78: =K78*(1+L97) -> 106019.37 | M78: =L78*(1+M97) -> 109305.97
C79: Total Revenues | D79: =SUM(D74:D78) -> 386064 | E79: =SUM(E74:E78) -> 469822 | F79: =SUM(F74:F78) -> 513983 | G79: =SUM(G74:G78) -> 574785 | H79: =SUM(H74:H78) -> 637959 | I79: =SUM(I74:I78) -> 651794.04 | J79: =SUM(J74:J78) -> 665356.49 | K79: =SUM(K74:K78) -> 678331.18 | ... M79: =SUM(M74:M78) -> 704302.83
C80: Growth Rate (%) | E80: =E79/D79-1 -> 0.21695367 | F80: =F79/E79-1 -> 0.093995173 | G80: =G79/F79-1 -> 0.11829574 | H80: =H79/G79-1 -> 0.10990892 | I80: =I79/H79-1 -> 0.021686406 | J80: =J79/I79-1 -> 0.020807887 | K80: =K79/J79-1 -> 0.019500352 | L80: =L79/K79-1 -> 0.018947385 | M80: =M79/L79-1 -> 0.018980544
C82: As % of Total | D82: 2020 | E82: =D82+1 -> 2021 | F82: =E82+1 -> 2022 | G82: =F82+1 -> 2023 | H82: =G82+1 -> 2024 | I82: =H82+1 -> 2025 | J82: =I82+1 -> 2026 | K82: =J82+1 -> 2027 | L82: =K82+1 -> 2028 | M82: =L82+1 -> 2029
C83: United States | D83: =D74/D$52 -> 0.68258113 | E83: =E74/E$52 -> 0.66835099 | F83: =F74/F$52 -> 0.69284976 | G83: =G74/G$52 -> 0.68832172 | H83: =H74/H$52 -> 0.68658801 | I83: =I74/I$79 -> 0.68679875 | J83: =J74/J$79 -> 0.686928 | K83: =K74/K$79 -> 0.68659087 | L83: =L74/L$79 -> 0.6859525 | M83: =M74/M$79 -> 0.68529242
C84: Germany | D84: =D75/D$52 -> 0.076580567 | E84: =E75/E$52 -> 0.067355296 | F84: =F75/F$52 -> 0.065367921 | G84: =G75/G$52 -> 0.065394887 | H84: =H75/H$52 -> 0.064041733 | I84: =I75/I$79 -> 0.063183837 | J84: =J75/J$79 -> 0.062638664 | K84: =K75/K$79 -> 0.06230072 | L84: =L75/L$79 -> 0.061937083 | M84: =M75/M$79 -> 0.061573566
C85: United Kingdom | D85: =D76/D$52 -> 0.068597435 | E85: =E76/E$52 -> 0.059399092 | F85: =F76/F$52 -> 0.058511663 | G85: =G76/G$52 -> 0.058440982 | H85: =H76/H$52 -> 0.059337669 | I85: =I76/I$79 -> 0.058949335 | J85: =J76/J$79 -> 0.058498447 | K85: =K76/K$79 -> 0.05818284 | L85: =L76/L$79 -> 0.05795744 | M85: =M76/M$79 -> 0.057731035
C86: Japan | D86: =D77/D79 -> 0.052998985 | E86: =E77/E79 -> 0.049105832 | F86: =F77/F79 -> 0.047464605 | G86: =G77/G79 -> 0.045237785 | H86: =H77/H79 -> 0.042951036 | I86: =I77/I79 -> 0.042501786 | J86: =J77/J79 -> 0.041885254 | K86: =K77/K79 -> 0.041330604 | ... M86: =M77/M79 -> 0.04020557
C87: Rest Of World | D87: =D78/D$52 -> 0.11924189 | E87: =E78/E$52 -> 0.15578879 | F87: =F78/F$52 -> 0.13580605 | G87: =G78/G$52 -> 0.14260463 | H87: =H78/H$52 -> 0.14708155 | I87: =I78/I$52 -> 0.14613135 | J87: =J78/J$52 -> 0.14500582 | K87: =K78/K$52 -> 0.14426528 | ... M87: =M78/M$52 -> 0.14295409
C88: Total Revenues | D88: =SUM(D83:D87) -> 1 | E88: =SUM(E83:E87) -> 1 | F88: =SUM(F83:F87) -> 1 | G88: =SUM(G83:G87) -> 1 | H88: =SUM(H83:H87) -> 1 | I88: =SUM(I83:I87) -> 0.99756506 | J88: =SUM(J83:J87) -> 0.99495618 | K88: =SUM(K83:K87) -> 0.99267031 | ... M88: =SUM(M83:M87) -> 0.98775668
C90: Economic Indicators
D92: 2020 | E92: =D92+1 -> 2021 | F92: =E92+1 -> 2022 | G92: =F92+1 -> 2023 | H92: =G92+1 -> 2024 | I92: =H92+1 -> 2025 | J92: =I92+1 -> 2026 | K92: =J92+1 -> 2027 | L92: =K92+1 -> 2028 | M92: =L92+1 -> 2029
C93: US GDP Growth (%) | D93: -0.022 | E93: 0.058 | F93: 0.019 | G93: 0.029 | H93: 0.028 | I93: 0.022 | J93: 0.021 | K93: 0.019 | L93: 0.018 | M93: 0.018 | O93: Source: IMF
C94: Germany GDP Growth (%) | D94: -0.038 | E94: 0.032 | F94: 0.018 | G94: -0.003 | H94: 0 | I94: 0.008 | J94: 0.012 | K94: 0.014 | L94: 0.013 | M94: 0.013 | O94: Source: IMF
C95: UK GDP Growth (%) | D95: -0.104 | E95: 0.087 | F95: 0.043 | G95: 0.003 | H95: 0.011 | I95: 0.015 | J95: 0.013 | K95: 0.014 | L95: 0.015 | M95: 0.015 | O95: Source: IMF
C96: Japan GDP Growth (%) | D96: -0.042 | E96: 0.026 | F96: 0.009 | G96: 0.017 | H96: 0.003 | I96: 0.011 | J96: 0.006 | K96: 0.006 | L96: 0.005 | M96: 0.005 | O96: Source: IMF
C97: Rest of World GDP (%) | D97: -0.031 | E97: 0.063 | F97: 0.035 | G97: 0.032 | H97: 0.032 | I97: 0.032 | J97: 0.031 | K97: 0.03 | L97: 0.031 | M97: 0.031 | O97: Source: IMF

Sheet Scenarios
C3: Scenario Assumptions
C4: Figures in USD millions, unless told otherwise
C8: Case Scenario | D8: 1
C9: Base Case | D9: 1
C10: Bull | D10: 2
C11: Bear | D11: 3
C13: Scenario Assumption Table | K13: NOTE: Base case assumptions are carried forward in the bear and bull cases, unless told otherwise
D15: 5yr Avg. | E15: 2025 | F15: 2026 | G15: 2027 | H15: 2028 | I15: 2029 | K15: Main Rationale
C17: Sales Growth (%) | D17: =AVERAGE('Actuals FS'!D149:G149) -> 0.13478838 | E17: =CHOOSE($D$8,E18,E19,E20) -> 0.07 | F17: =CHOOSE($D$8,F18,F19,F20) -> 0.09 | G17: =CHOOSE($D$8,G18,G19,G20) -> 0.09 | H17: =CHOOSE($D$8,H18,H19,H20) -> 0.1 | I17: =CHOOSE($D$8,I18,I19,I20) -> 0.1
C18: Base Case | E18: 0.07 | F18: 0.09 | G18: 0.09 | H18: 0.1 | I18: 0.1 | K18: The most recent company guidance is for Q1 2025 Net Sales to be between 5% and 9% growth. We adopt the midpoint of the range (7.0%) for 2025, then project a steady increase toward 10.0% by 2028-2029, assuming successful realization of investments.
C19: Bull | E19: =E18+4% -> 0.11 | F19: 0.14 | G19: 0.14 | H19: 0.13 | I19: 0.13 | K19: This scenario reflects high-end analyst expectations based on the AWS re-acceleration (which was the highest-growth segment at 19% in 2024). It assumes the AI infrastructure investments and the strong advertising segment drive growth well above the immediate guidance.
C20: Bear | E20: 0.05 | F20: 0.06 | G20: 0.06 | H20: 0.07 | I20: 0.07 | K20: This uses the low end of the Q1 2025 guidance (5%) and anticipates slower-than-expected recovery in the International segment (which grew 9% in 2024) and poor performance in the highly competitive North America segment.
C21: Cost of Sales (% of sales) | D21: =AVERAGE('Actuals FS'!D150:H150) -> 0.48001736 | E21: =CHOOSE($D$8,E22,E23,E24) -> 0.51 | F21: =CHOOSE($D$8,F22,F23,F24) -> 0.505 | G21: =CHOOSE($D$8,G22,G23,G24) -> 0.5 | H21: =CHOOSE($D$8,H22,H23,H24) -> 0.495 | I21: =CHOOSE($D$8,I22,I23,I24) -> 0.49
C22: Base Case | E22: 0.51 | F22: 0.505 | G22: 0.5 | H22: 0.495 | I22: 0.49 | K22: Starts at 51.0% (aligning with the 2024 actuals) and improves to 49.0%, assuming efficiencies take time to materialize.
C23: Bull | E23: 0.505 | F23: 0.49 | G23: 0.48 | H23: 0.47 | I23: 0.46 | K23: Drops aggressively to 46.0% (surpassing your 48% historical average) due to rapid growth in high-margin AWS/Advertising revenue which dilutes the cost of retail goods.
C24: Bear | E24: 0.515 | F24: 0.52 | G24: 0.525 | H24: 0.53 | I24: 0.535 | K24: Rises to 53.5%, reflecting risks of inventory markdowns and inflation cited in the 10-K.
C25: Fulfillment Expense (% of sales) | D25: =AVERAGE('Actuals FS'!D161:H161) -> 0.15750389 | E25: =CHOOSE($D$8,E26,E27,E28) -> 0.154 | F25: =CHOOSE($D$8,F26,F27,F28) -> 0.152 | G25: =CHOOSE($D$8,G26,G27,G28) -> 0.15 | H25: =CHOOSE($D$8,H26,H27,H28) -> 0.148 | I25: =CHOOSE($D$8,I26,I27,I28) -> 0.146
C26: Base Case | E26: 0.154 | F26: 0.152 | G26: 0.15 | H26: 0.148 | I26: 0.146 | K26: Slight improvement from 2024 (15.4%) to 14.6%. Rationale: Continued realization of "regionalization" efficiencies in the logistics network, which reduces miles driven and cost per package.
C27: Bull | E27: 0.15 | F27: 0.145 | G27: 0.14 | H27: 0.135 | I27: 0.13 | K27: Aggressive drop to 13.0%. Rationale: Robotics and automation in fulfillment centers significantly lower labor intensity, addressing the "constrained labor market" risk by reducing reliance on temporary staffing.
C28: Bear | E28: 0.16 | F28: 0.165 | G28: 0.165 | H28: 0.17 | I28: 0.17 | K28: Increases to 17.0%. Rationale: Labor shortages force wage hikes, and "variability in demand" leads to underutilized capacity in the massive logistics footprint, driving up fixed costs per unit.
C29: Tech & Infra (% of sales) | D29: =AVERAGE('Actuals FS'!D154:H154) -> 0.13204208 | E29: =CHOOSE($D$8,E30,E31,E32) -> -0.145 | F29: =CHOOSE($D$8,F30,F31,F32) -> -0.145 | G29: =CHOOSE($D$8,G30,G31,G32) -> -0.14 | H29: =CHOOSE($D$8,H30,H31,H32) -> -0.135 | I29: =CHOOSE($D$8,I30,I31,I32) -> -0.13
C30: Base Case | E30: -0.145 | F30: -0.145 | G30: -0.14 | H30: -0.135 | I30: -0.13 | K30: Assumes the ratio initially worsens to -14.5% due to expected increases in AI infrastructure spending, then improves as those investments mature and revenue leverage kicks in.
C31: Bull | E31: -0.135 | F31: -0.13 | G31: -0.125 | H31: -0.12 | I31: -0.115 | K31: Models a rapid improvement to -11.5% as high-margin AWS revenue grows faster than the fixed costs of the new data centers.
C32: Bear | E32: -0.15 | F32: -0.155 | G32: -0.16 | H32: -0.16 | I32: -0.16 | K32: Reflects a deterioration to -16.0% driven by "service disruptions" or low utilization of the expanded infrastructure, causing costs to outpace sales growth.
C33: S&M + G&A (% of sales) | D33: =AVERAGE('Actuals FS'!D153:H153) -> 0.37995287 | E33: =CHOOSE($D$8,E34,E35,E36) -> 0.087 | F33: =CHOOSE($D$8,F34,F35,F36) -> 0.086 | G33: =CHOOSE($D$8,G34,G35,G36) -> 0.085 | H33: =CHOOSE($D$8,H34,H35,H36) -> 0.084 | I33: =CHOOSE($D$8,I34,I35,I36) -> 0.083
C34: Base Case | E34: 0.087 | F34: =E34-0.1% -> 0.086 | G34: =F34-0.1% -> 0.085 | H34: =G34-0.1% -> 0.084 | I34: =H34-0.1% -> 0.083 | K34: Assumes a gradual improvement from the 2024 level as the company continues to realize efficiencies in payroll and maintains a lean corporate structure to let revenue grow faster than overhead.
C35: Bull | E35: 0.085 | F35: =E35-0.5% -> 0.08 | G35: =F35-0.5% -> 0.075 | H35: =G35-0.5% -> 0.07 | I35: =H35-0.5% -> 0.065 | K35: Models significant operating leverage where rapid growth in high-margin AWS and advertising revenue requires far less incremental marketing spend per dollar earned compared to retail.
C36: Bear | E36: 0.09 | F36: =E36+0.5% -> 0.095 | G36: =F36 -> 0.095 | H36: =G36+0.5% -> 0.1 | I36: =H36 -> 0.1 | K36: Reflects rising costs due to "intense competition" for advertising traffic driving up marketing rates and "constrained labor markets" forcing higher wages for corporate staff.
C37: Effective Tax Rate (%) | D37: =AVERAGE('Actuals FS'!D159:H159) -> -0.22211001 | E37: =CHOOSE($D$8,E38,E39,E40) -> -0.15 | F37: =CHOOSE($D$8,F38,F39,F40) -> -0.16 | G37: =CHOOSE($D$8,G38,G39,G40) -> -0.17 | H37: =CHOOSE($D$8,H38,H39,H40) -> -0.17 | I37: =CHOOSE($D$8,I38,I39,I40) -> -0.17
C38: Base Case | E38: -0.15 | F38: =E38-1% -> -0.16 | G38: =F38-1% -> -0.17 | H38: =G38 -> -0.17 | I38: =H38 -> -0.17 | K38: Assumes the rate normalizes from the 2024 low (-13.5%) to -17.0% as new global minimum tax rules (Pillar Two) take effect and U.S. deductions phase out.
C39: Bull | E39: -0.12 | F39: =E39-0.5% -> -0.125 | G39: =F39-0.5% -> -0.13 | H39: =G39-0.5% -> -0.135 | I39: =H39-0.5% -> -0.14 | K39: Models a lower effective rate (-12.0% to -14.0%) driven by the successful maximization of R&D tax credits and "Foreign-Derived Intangible Income" deductions.
C40: Bear | E40: -0.18 | F40: =E40-1% -> -0.19 | G40: =F40-1% -> -0.2 | H40: =G40-1% -> -0.21 | I40: =H40 -> -0.21 | K40: Reflects a surge in tax expense to -21.0% due to adverse outcomes in ongoing "tax controversies" (such as the Indian tax authority dispute) and stricter international enforcement.
C41: Implied EBITDA Margin (%) | D41: =AVERAGE('Actuals FS'!D157:H157) -> 0.11879461 | E41: =1-SUM(E21,E25,E29,E37,E17,E33) -> 0.474 | F41: =1-SUM(F21,F25,F29,F37,F17,F33) -> 0.472 | G41: =1-SUM(G21,G25,G29,G37,G17,G33) -> 0.485 | H41: =1-SUM(H21,H25,H29,H37,H17,H33) -> 0.478 | I41: =1-SUM(I21,I25,I29,I37,I17,I33) -> 0.481
C43: Days in Receivables | D43: =AVERAGE('Actuals FS'!D113:H113) -> 28.748894 | E43: =CHOOSE($D$8,E44,E45,E46) -> 29 | F43: =CHOOSE($D$8,F44,F45,F46) -> 29 | G43: =CHOOSE($D$8,G44,G45,G46) -> 29 | H43: =CHOOSE($D$8,H44,H45,H46) -> 29 | I43: =CHOOSE($D$8,I44,I45,I46) -> 29
C44: Base Case | E44: 29 | F44: 29 | G44: 29 | H44: 29 | I44: 29 | K44: Maintains stability at 29 days, reflecting the high proportion of consumer sales settled instantly via credit card which keeps the collection cycle short.
C45: Bull | E45: 28 | F45: =E45 -> 28 | G45: =F45-0.5 -> 27.5 | H45: =G45 -> 27.5 | I45: =H45-0.5 -> 27 | K45: Drops to 27.0 days as the revenue mix shifts toward high-velocity digital services (AWS and Advertising) which settle faster than physical retail invoicing.
C46: Bear | E46: 30 | F46: =E46+1 -> 31 | G46: =F46+1 -> 32 | H46: =G46 -> 32 | I46: =H46+1 -> 33 | K46: Increases to 33.0 days due to "global economic conditions" causing slower payments from enterprise AWS customers and extended credit terms to stimulate retail sales.
C47: Days in Inventory | D47: =AVERAGE('Actuals FS'!D116:H116) -> 40.525789 | E47: =CHOOSE($D$8,E48,E49,E50) -> 40 | F47: =CHOOSE($D$8,F48,F49,F50) -> 39 | G47: =CHOOSE($D$8,G48,G49,G50) -> 38 | H47: =CHOOSE($D$8,H48,H49,H50) -> 37 | I47: =CHOOSE($D$8,I48,I49,I50) -> 36
C48: Base Case | E48: 40 | F48: =E48-1 -> 39 | G48: =F48-1 -> 38 | H48: =G48-1 -> 37 | I48: =H48-1 -> 36 | K48: Assumes a gradual improvement from 40.5 to 36 days as "fulfillment network efficiencies" and regionalization initiatives allow for faster turnover of stock.
C49: Bull | E49: 38 | F49: =E49-2 -> 36 | G49: =F49-2 -> 34 | H49: =G49-2 -> 32 | I49: =H49-2 -> 30 | K49: Improves significantly to 30.0 days driven by "regionalization" and predictive AI significantly reducing the need for safety stock across the fulfillment network.
C50: Bear | E50: 42 | F50: =E50+2 -> 44 | G50: =F50+2 -> 46 | H50: =G50+2 -> 48 | I50: =H50+2 -> 50 | K50: Worsens to 50.0 days as a result of "overstocking" due to inaccurate demand forecasting, leading to slower turnover and potential write-offs.
C51: Days in Payables | D51: =AVERAGE('Actuals FS'!D119:H119) -> 105.36946 | E51: =CHOOSE($D$8,E52,E53,E54) -> 105.36946 | F51: =CHOOSE($D$8,F52,F53,F54) -> 105.36946 | G51: =CHOOSE($D$8,G52,G53,G54) -> 105.36946 | H51: =CHOOSE($D$8,H52,H53,H54) -> 105.36946 | I51: =CHOOSE($D$8,I52,I53,I54) -> 105.36946
C52: Base Case | E52: =D51 -> 105.36946 | F52: =E52 -> 105.36946 | G52: =F52 -> 105.36946 | H52: =G52 -> 105.36946 | I52: =H52 -> 105.36946 | K52: Holds steady at ~105 days, maintaining the company's strong leverage with suppliers to maximize free cash flow float.
C53: Bull | E53: 110 | F53: =E53+2 -> 112 | G53: =F53+3 -> 115 | H53: =G53 -> 115 | I53: =H53 -> 115 | K53: Extends to 115.0 days as Amazon leverages its dominant market position to negotiate even longer payment terms with suppliers, maximizing working capital float.
C54: Bear | E54: 100 | F54: =E54-5 -> 95 | G54: =F54-5 -> 90 | H54: =G54 -> 90 | I54: =H54 -> 90 | K54: Contracts to 90.0 days due to supplier financial stress or regulatory pressure forcing faster payment terms, reducing the company's operating cash flow advantage.
C55: Implied Cash Conversion Cycle | D55: =D43+D47-D51 -> -36.094774 | E55: =E43+E47-E51 -> -36.369457 | F55: =F43+F47-F51 -> -37.369457 | G55: =G43+G47-G51 -> -38.369457 | H55: =H43+H47-H51 -> -39.369457 | I55: =I43+I47-I51 -> -40.369457
C57: Capex (% of sales) | D57: =AVERAGE('Actuals FS'!D160:H160) -> -0.11591728 | E57: =CHOOSE($D$8,E58,E59,E60) -> -0.14 | F57: =CHOOSE($D$8,F58,F59,F60) -> -0.145 | G57: =CHOOSE($D$8,G58,G59,G60) -> -0.145 | H57: =CHOOSE($D$8,H58,H59,H60) -> -0.135 | I57: =CHOOSE($D$8,I58,I59,I60) -> -0.13
C58: Base Case | E58: -0.14 | F58: =E58-0.5% -> -0.145 | G58: =F58 -> -0.145 | H58: =G58+1% -> -0.135 | I58: =H58+0.5% -> -0.13 | K58: Increases from the -12% average to -14.5% in the near term to fund the expected "increase" in cash capital expenditures for AWS/AI infrastructure, before normalizing.
C59: Bull | E59: -0.16 | F59: -0.17 | G59: -0.17 | H59: -0.16 | I59: -0.15 | K59: Surges to -17.0% as the company aggressively accelerates investment in "technology infrastructure" to capture dominant market share in generative AI.
C60: Bear | E60: -0.12 | F60: -0.11 | G60: -0.11 | H60: -0.1 | I60: -0.1 | K60: Cuts back to -10.0% as macroeconomic uncertainty forces a shift to cash preservation and a delay in planned capacity expansions.
C63: Economic Indicators Impacting AMZN Operating Performance
E65: =E15 -> 2025 | F65: =F15 -> 2026 | G65: =G15 -> 2027 | H65: =H15 -> 2028 | I65: =I15 -> 2029
C66: Revenue Growth with Regional GDP Expectations | E66: =Revenue!I80 -> 0.021686406 | F66: =Revenue!J80 -> 0.020807887 | G66: =Revenue!K80 -> 0.019500352 | H66: =Revenue!L80 -> 0.018947385 | I66: =Revenue!M80 -> 0.018980544 | K66: Source: IMF
C67: Revenue Growth From Industry | E67: =Revenue!I53 -> 0.038710469 | F67: =Revenue!J53 -> 0.039002611 | G67: =Revenue!K53 -> 0.035287158 | H67: =Revenue!L53 -> 0.036435991 | I67: =Revenue!M53 -> 0.034999347 | K67: Source: IMF
C68: US Inflation (%) | E68: 0.033 | F68: 0.016 | G68: 0.015 | H68: 0.016 | I68: 0.017 | K68: Source: Morningstar
C69: US Monetary Policy (%) | E69: 0.0475 | F69: 0.02 | G69: 0.02 | H69: 0.0175 | I69: 0.0175 | K69: Source: Morningstar
F73: Indicators Impacting AMZN Operating Performance

Sheet Multiples
C3: Relative Multiples Valuation Model Based on Selected Industry Peers
C4: Figures in USD millions, unless told otherwise
C8: AMZN Intrinsic Value Based on Selected Comparable Companies
E10: EV/Sales | F10: EV/EBIT | G10: EV/EBITDA | H10: P/E
C11: Selected Multiple | E11: =R39 -> 9.0598301 | F11: =S39 -> 28.84199 | G11: =T39 -> 21.096831 | H11: =U39 -> 34.505254
C12: Operating Metric | E12: ='Forecasted FS'!E37 -> 637959 | F12: ='Forecasted FS'!E47 -> 68593 | G12: ='Forecasted FS'!E47 -> 68593 | H12: ='Forecasted FS'!E56 -> 59248
C13: Enterprise Value | E13: =E12*E11 -> 5779800.1 | F13: =F12*F11 -> 1978358.6 | G13: =G12*G11 -> 1447094.9 | H13: =H17-SUM(H14:H16) -> 2643105.3
C14: - Debt | E14: =DCF!$I$44 -> -52623 | F14: =DCF!$I$44 -> -52623 | G14: =DCF!$I$44 -> -52623 | H14: =DCF!$I$44 -> -52623
C15: + Cash | E15: =DCF!$I$45 -> 78779 | F15: =DCF!$I$45 -> 78779 | G15: =DCF!$I$45 -> 78779 | H15: =DCF!$I$45 -> 78779
C16: - Minority Interest | E16: =DCF!$I$46 -> -624894 | F16: =DCF!$I$46 -> -624894 | G16: =DCF!$I$46 -> -624894 | H16: =DCF!$I$46 -> -624894
C17: Equity Value | E17: =SUM(E13:E16) -> 5181062.1 | F17: =SUM(F13:F16) -> 1379620.6 | G17: =SUM(G13:G16) -> 848356.9 | H17: =H11*H12 -> 2044367.3
C18: Shares Outstanding | E18: =DCF!$E$15 -> 10721 | F18: =DCF!$E$15 -> 10721 | G18: =DCF!$E$15 -> 10721 | H18: =DCF!$E$15 -> 10721
C20: Implied Price | E20: =E17/E18 -> 483.26296 | F20: =F17/F18 -> 128.68395 | G20: =G17/G18 -> 79.130389 | H20: =H17/H18 -> 190.68812
C22: NOTE: Median value of comparable companies table to eliminate outliers
C24: Relative Valuation Summary
F26: Company Information | I26: Market Data | M26: Financial Data | R26: Valuation
D27: Company Name | F27: Ticker | G27: Country | I27: Price ($/share) | J27: Market Cap | K27: EV | M27: Sales | N27: EBIT | O27: EBITDA | P27: Earnings | R27: EV/Sales | S27: EV/EBIT | T27: EV/EBITDA | U27: P/E
C28: 1 | D28: Microsoft Corporation | F28: =VLOOKUP($D28,'Peer Fin Info'!$D$11:$R$20,2,FALSE) -> MSFT | G28: =VLOOKUP($D28,'Peer Fin Info'!$D$11:$R$20,3,FALSE) -> USA | I28: =VLOOKUP(F28,'Peer Mkt Info'!$E$10:$M$19,9,FALSE) -> 483.47 | J28: =VLOOKUP($D28,'Peer Fin Info'!$D$11:$R$20,14,FALSE) -> 3556616 | K28: =VLOOKUP($D28,'Peer Fin Info'!$D$11:$R$20,15,FALSE) -> 3515167 | M28: =VLOOKUP($D28,'Peer Fin Info'!$D$11:$R$20,5,FALSE) -> 293812 | N28: =VLOOKUP($D28,'Peer Fin Info'!$D$11:$R$20,6,FALSE) -> 127218 | O28: =VLOOKUP($D28,'Peer Fin Info'!$D$11:$R$20,7,FALSE) -> 167049 | P28: =VLOOKUP($D28,'Peer Fin Info'!$D$11:$R$20,8,FALSE) -> 104912 | R28: =$K28/M28 -> 11.964001 | S28: =$K28/N28 -> 27.631051 | T28: =$K28/O28 -> 21.04273 | U28: =J28/P28 -> 33.900946
C29: =C28+1 -> 2 | D29: Alphabet Inc. | F29: =VLOOKUP($D29,'Peer Fin Info'!$D$11:$R$20,2,FALSE) -> GOOGL | G29: =VLOOKUP($D29,'Peer Fin Info'!$D$11:$R$20,3,FALSE) -> USA | I29: =VLOOKUP(F29,'Peer Mkt Info'!$E$10:$M$19,9,FALSE) -> 312.43 | J29: =VLOOKUP($D29,'Peer Fin Info'!$D$11:$R$20,14,FALSE) -> 3732202 | K29: =VLOOKUP($D29,'Peer Fin Info'!$D$11:$R$20,15,FALSE) -> 3667419 | M29: =VLOOKUP($D29,'Peer Fin Info'!$D$11:$R$20,5,FALSE) -> 385476 | N29: =VLOOKUP($D29,'Peer Fin Info'!$D$11:$R$20,6,FALSE) -> 148227 | O29: =VLOOKUP($D29,'Peer Fin Info'!$D$11:$R$20,7,FALSE) -> 167528 | P29: =VLOOKUP($D29,'Peer Fin Info'!$D$11:$R$20,8,FALSE) -> 124251 | R29: =$K29/M29 -> 9.5140009 | S29: =$K29/N29 -> 24.741909 | T29: =$K29/O29 -> 21.891379 | U29: =J29/P29 -> 30.037601
C30: =C29+1 -> 3 | D30: Meta Platforms, Inc. | F30: =VLOOKUP($D30,'Peer Fin Info'!$D$11:$R$20,2,FALSE) -> META | G30: =VLOOKUP($D30,'Peer Fin Info'!$D$11:$R$20,3,FALSE) -> USA | I30: =VLOOKUP(F30,'Peer Mkt Info'!$E$10:$M$19,9,FALSE) -> 652.71 | J30: =VLOOKUP($D30,'Peer Fin Info'!$D$11:$R$20,14,FALSE) -> 1623799 | K30: =VLOOKUP($D30,'Peer Fin Info'!$D$11:$R$20,15,FALSE) -> 1630411 | M30: =VLOOKUP($D30,'Peer Fin Info'!$D$11:$R$20,5,FALSE) -> 189458 | N30: =VLOOKUP($D30,'Peer Fin Info'!$D$11:$R$20,6,FALSE) -> 82861 | O30: =VLOOKUP($D30,'Peer Fin Info'!$D$11:$R$20,7,FALSE) -> 100526 | P30: =VLOOKUP($D30,'Peer Fin Info'!$D$11:$R$20,8,FALSE) -> 58528 | R30: =$K30/M30 -> 8.6056593 | S30: =$K30/N30 -> 19.676458 | T30: =$K30/O30 -> 16.218799 | U30: =J30/P30 -> 27.743969
C31: =C30+1 -> 4 | D31: Oracle Corporation | F31: =VLOOKUP($D31,'Peer Fin Info'!$D$11:$R$20,2,FALSE) -> ORCL | G31: =VLOOKUP($D31,'Peer Fin Info'!$D$11:$R$20,3,FALSE) -> USA | I31: =VLOOKUP(F31,'Peer Mkt Info'!$E$10:$M$19,9,FALSE) -> 198.85 | J31: =VLOOKUP($D31,'Peer Fin Info'!$D$11:$R$20,14,FALSE) -> 541565 | K31: =VLOOKUP($D31,'Peer Fin Info'!$D$11:$R$20,15,FALSE) -> 646185 | M31: =VLOOKUP($D31,'Peer Fin Info'!$D$11:$R$20,5,FALSE) -> 61016 | N31: =VLOOKUP($D31,'Peer Fin Info'!$D$11:$R$20,6,FALSE) -> 20629 | O31: =VLOOKUP($D31,'Peer Fin Info'!$D$11:$R$20,7,FALSE) -> 22757 | P31: =VLOOKUP($D31,'Peer Fin Info'!$D$11:$R$20,8,FALSE) -> 15425 | R31: =$K31/M31 -> 10.590419 | S31: =$K31/N31 -> 31.324107 | T31: =$K31/O31 -> 28.394999 | U31: =J31/P31 -> 35.109562
C32: =C31+1 -> 5 | D32: Walmart Inc. | F32: =VLOOKUP($D32,'Peer Fin Info'!$D$11:$R$20,2,FALSE) -> WMT | G32: =VLOOKUP($D32,'Peer Fin Info'!$D$11:$R$20,3,FALSE) -> USA | I32: =VLOOKUP(F32,'Peer Mkt Info'!$E$10:$M$19,9,FALSE) -> 115.52 | J32: =VLOOKUP($D32,'Peer Fin Info'!$D$11:$R$20,14,FALSE) -> 930118 | K32: =VLOOKUP($D32,'Peer Fin Info'!$D$11:$R$20,15,FALSE) -> 987960 | M32: =VLOOKUP($D32,'Peer Fin Info'!$D$11:$R$20,5,FALSE) -> 703061 | N32: =VLOOKUP($D32,'Peer Fin Info'!$D$11:$R$20,6,FALSE) -> 32874 | O32: =VLOOKUP($D32,'Peer Fin Info'!$D$11:$R$20,7,FALSE) -> 46710 | P32: =VLOOKUP($D32,'Peer Fin Info'!$D$11:$R$20,8,FALSE) -> 23303 | R32: =$K32/M32 -> 1.4052266 | S32: =$K32/N32 -> 30.052929 | T32: =$K32/O32 -> 21.150931 | U32: =J32/P32 -> 39.914088
C33: =C32+1 -> 6 | D33: Costco Wholesale | F33: =VLOOKUP($D33,'Peer Fin Info'!$D$11:$R$20,2,FALSE) -> COST | G33: =VLOOKUP($D33,'Peer Fin Info'!$D$11:$R$20,3,FALSE) -> USA | I33: =VLOOKUP(F33,'Peer Mkt Info'!$E$10:$M$19,9,FALSE) -> 888.48 | J33: =VLOOKUP($D33,'Peer Fin Info'!$D$11:$R$20,14,FALSE) -> 392667 | K33: =VLOOKUP($D33,'Peer Fin Info'!$D$11:$R$20,15,FALSE) -> 385556 | M33: =VLOOKUP($D33,'Peer Fin Info'!$D$11:$R$20,5,FALSE) -> 208391 | N33: =VLOOKUP($D33,'Peer Fin Info'!$D$11:$R$20,6,FALSE) -> 10691 | O33: =VLOOKUP($D33,'Peer Fin Info'!$D$11:$R$20,7,FALSE) -> 13166 | P33: =VLOOKUP($D33,'Peer Fin Info'!$D$11:$R$20,8,FALSE) -> 8302 | R33: =$K33/M33 -> 1.8501567 | S33: =$K33/N33 -> 36.063605 | T33: =$K33/O33 -> 29.284217 | U33: =J33/P33 -> 47.29788
C34: =C33+1 -> 7 | D34: Target Corporation | F34: =VLOOKUP($D34,'Peer Fin Info'!$D$11:$R$20,2,FALSE) -> TGT | G34: =VLOOKUP($D34,'Peer Fin Info'!$D$11:$R$20,3,FALSE) -> USA | I34: =VLOOKUP(F34,'Peer Mkt Info'!$E$10:$M$19,9,FALSE) -> 96.97 | J34: =VLOOKUP($D34,'Peer Fin Info'!$D$11:$R$20,14,FALSE) -> 43909 | K34: =VLOOKUP($D34,'Peer Fin Info'!$D$11:$R$20,15,FALSE) -> 60128 | M34: =VLOOKUP($D34,'Peer Fin Info'!$D$11:$R$20,5,FALSE) -> 105242 | N34: =VLOOKUP($D34,'Peer Fin Info'!$D$11:$R$20,6,FALSE) -> 5301 | O34: =VLOOKUP($D34,'Peer Fin Info'!$D$11:$R$20,7,FALSE) -> 8398 | P34: =VLOOKUP($D34,'Peer Fin Info'!$D$11:$R$20,8,FALSE) -> 3763 | R34: =$K34/M34 -> 0.57133084 | S34: =$K34/N34 -> 11.342766 | T34: =$K34/O34 -> 7.1598 | U34: =J34/P34 -> 11.668615
C35: =C34+1 -> 8 | D35: Alibaba Group | F35: =VLOOKUP($D35,'Peer Fin Info'!$D$11:$R$20,2,FALSE) -> BABA | G35: =VLOOKUP($D35,'Peer Fin Info'!$D$11:$R$20,3,FALSE) -> China | I35: =VLOOKUP(F35,'Peer Mkt Info'!$E$10:$M$19,9,FALSE) -> 156.9 | J35: =VLOOKUP($D35,'Peer Fin Info'!$D$11:$R$20,14,FALSE) -> 374369 | K35: =VLOOKUP($D35,'Peer Fin Info'!$D$11:$R$20,15,FALSE) -> 194386 | M35: =VLOOKUP($D35,'Peer Fin Info'!$D$11:$R$20,5,FALSE) -> 1012055 | N35: =VLOOKUP($D35,'Peer Fin Info'!$D$11:$R$20,6,FALSE) -> 157058 | O35: =VLOOKUP($D35,'Peer Fin Info'!$D$11:$R$20,7,FALSE) -> 161586 | P35: =VLOOKUP($D35,'Peer Fin Info'!$D$11:$R$20,8,FALSE) -> 123354 | R35: =$K35/M35 -> 0.19207059 | S35: =$K35/N35 -> 1.2376702 | T35: =$K35/O35 -> 1.2029879 | U35: =J35/P35 -> 3.0349158
C36: =C35+1 -> 9 | D36: Apple Inc. | F36: =VLOOKUP($D36,'Peer Fin Info'!$D$11:$R$20,2,FALSE) -> AAPL | G36: =VLOOKUP($D36,'Peer Fin Info'!$D$11:$R$20,3,FALSE) -> USA | I36: =VLOOKUP(F36,'Peer Mkt Info'!$E$10:$M$19,9,FALSE) -> 278.03 | J36: =VLOOKUP($D36,'Peer Fin Info'!$D$11:$R$20,14,FALSE) -> 4108269 | K36: =VLOOKUP($D36,'Peer Fin Info'!$D$11:$R$20,15,FALSE) -> 4152229 | M36: =VLOOKUP($D36,'Peer Fin Info'!$D$11:$R$20,5,FALSE) -> 416161 | N36: =VLOOKUP($D36,'Peer Fin Info'!$D$11:$R$20,6,FALSE) -> 132729 | O36: =VLOOKUP($D36,'Peer Fin Info'!$D$11:$R$20,7,FALSE) -> 144427 | P36: =VLOOKUP($D36,'Peer Fin Info'!$D$11:$R$20,8,FALSE) -> 112010 | R36: =$K36/M36 -> 9.9774582 | S36: =$K36/N36 -> 31.28351 | T36: =$K36/O36 -> 28.749673 | U36: =J36/P36 -> 36.677698
C37: =C36+1 -> 10 | D37: Netflix, Inc. | F37: =VLOOKUP($D37,'Peer Fin Info'!$D$11:$R$20,2,FALSE) -> NFLX | G37: =VLOOKUP($D37,'Peer Fin Info'!$D$11:$R$20,3,FALSE) -> USA | I37: =VLOOKUP(F37,'Peer Mkt Info'!$E$10:$M$19,9,FALSE) -> 94.09 | J37: =VLOOKUP($D37,'Peer Fin Info'!$D$11:$R$20,14,FALSE) -> 399119 | K37: =VLOOKUP($D37,'Peer Fin Info'!$D$11:$R$20,15,FALSE) -> 404294.73 | M37: =VLOOKUP($D37,'Peer Fin Info'!$D$11:$R$20,5,FALSE) -> 39000.966 | N37: =VLOOKUP($D37,'Peer Fin Info'!$D$11:$R$20,6,FALSE) -> 12642.706 | O37: =VLOOKUP($D37,'Peer Fin Info'!$D$11:$R$20,7,FALSE) -> 25926.506 | P37: =VLOOKUP($D37,'Peer Fin Info'!$D$11:$R$20,8,FALSE) -> 8615.615 | R37: =$K37/M37 -> 10.366275 | S37: =$K37/N37 -> 31.978497 | T37: =$K37/O37 -> 15.593877 | U37: =J37/P37 -> 46.325074
C38: Low | R38: =MIN(R28:R37) -> 0.19207059 | S38: =MIN(S28:S37) -> 1.2376702 | T38: =MIN(T28:T37) -> 1.2029879 | U38: =MIN(U28:U37) -> 3.0349158
C39: Median | R39: =MEDIAN(R28:R37) -> 9.0598301 | S39: =MEDIAN(S28:S37) -> 28.84199 | T39: =MEDIAN(T28:T37) -> 21.096831 | U39: =MEDIAN(U28:U37) -> 34.505254
C40: Mean | R40: =AVERAGE(R28:R37) -> 6.5036598 | S40: =AVERAGE(S28:S37) -> 24.53325 | T40: =AVERAGE(T28:T37) -> 19.068939 | U40: =AVERAGE(U28:U37) -> 31.171035
C41: High | R41: =MAX(R28:R37) -> 11.964001 | S41: =MAX(S28:S37) -> 36.063605 | T41: =MAX(T28:T37) -> 29.284217 | U41: =MAX(U28:U37) -> 47.29788
D43: Amazon Inc. | F43: AMZN | G43: USA | I43: =DCF!E14 -> 226.19 | J43: =DCF!E43 -> 2424983 | K43: =DCF!E47 -> 3023721 | M43: =DCF!E27 -> 637959 | N43: =DCF!E31 -> 68593 | O43: =DCF!E29 -> 121388 | P43: ='Forecasted FS'!E56 -> 59248 | R43: =$K43/M43 -> 4.7396792 | S43: =$K43/N43 -> 44.082064 | T43: =$K43/O43 -> 24.909554 | U43: =J43/P43 -> 40.929365
C45: NOTE: Selection of peers is based on size and similarity of product offering and business risk to AMZN
C46: Source: PitchBook, Yahoo Finance
C47: https://my.pitchbook.com/dashboard | R47: AMZN Relative Valuation
C48: https://finance.yahoo.com/?guccounter=1 | R48: EV/Sales | S48: EV/EBIT | T48: EV/EBITDA | U48: P/E
P49: Low | R49: =(R38*E12+SUM(E14:E16))/E18 -> -44.41795 | S49: =(S38*F12+SUM(F14:F16))/F18 -> -47.928597 | T49: =(T38*G12+SUM(G14:G16))/G18 -> -48.150495 | U49: =(U38*H12)/H18 -> 16.772007
P50: Median | R50: =(R39*E12+SUM(E14:E16))/E18 -> 483.26296 | S50: =(S39*F12+SUM(F14:F16))/F18 -> 128.68395 | T50: =(T39*G12+SUM(G14:G16))/G18 -> 79.130389 | U50: =(U39*H12)/H18 -> 190.68812
P51: Mean | R51: =(R40*E12+SUM(E14:E16))/E18 -> 331.15663 | S51: =(S40*F12+SUM(F14:F16))/F18 -> 101.11661 | T51: =(T40*G12+SUM(G14:G16))/G18 -> 66.155933 | U51: =(U40*H12+SUM(H14:H16))/H18 -> 116.41484
P52: High | R52: =(R41*E12+SUM(E14:E16))/E18 -> 656.07723 | S52: =(S41*F12+SUM(F14:F16))/F18 -> 174.88787 | T52: =(T41*G12+SUM(G14:G16))/G18 -> 131.51332 | U52: =(U41*H12)/H18 -> 261.38465
R55: Low | S55: Median | T55: High
P56: {=TRANSPOSE(R27:U27)} -> EV/Sales | R56: {=TRANSPOSE(R49:U49)} -> -44.41795 | S56: {=TRANSPOSE(R50:U50)} -> 483.26296 | T56: {=TRANSPOSE(R52:U52)} -> 656.07723
P57: EV/EBIT | R57: -47.928597 | S57: 128.68395 | T57: 174.88787
P58: EV/EBITDA | R58: -48.150495 | S58: 79.130389 | T58: 131.51332
P59: P/E | R59: 16.772007 | S59: 190.68812 | T59: 261.38465
R62: Low | S62: Median | T62: High
P63: =P56 -> EV/Sales | R63: =R56 -> -44.41795 | S63: =S56-R56 -> 527.6809 | T63: =T56-S63-R63 -> 172.81427
P64: =P57 -> EV/EBIT | R64: =R57 -> -47.928597 | S64: =S57-R57 -> 176.61255 | T64: =T57-S64-R64 -> 46.20392
P65: =P58 -> EV/EBITDA | R65: =R58 -> -48.150495 | S65: =S58-R58 -> 127.28088 | T65: =T58-S65-R65 -> 52.38293
P66: =P59 -> P/E | R66: =R59 -> 16.772007 | S66: =S59-R59 -> 173.91611 | T66: =T59-S66-R66 -> 70.696531

Sheet Reg. Beta
C3: Beta Buildup Based on Regression Method
C4: In USD, unless told otherwise
C8: Date | D8: S&P 500 | E8: AMZN | F8: S&P Returns (%) | G8: AMZN Returns (%) | I8: NOTE:
C9: 44197 | D9: 3714.24 | E9: 160.31 | I9: Equity Beta construction is based on 5 year monthly returns of AMZN and S&P 500
C10: 44228 | D10: 3811.15 | E10: 154.65 | F10: =D10/D9-1 -> 0.026091475 | G10: =E10/E9-1 -> -0.035306593 | I10: Prices are based on adjusted at closing
C11: 44256 | D11: 3972.89 | E11: 154.7 | F11: =D11/D10-1 -> 0.042438634 | G11: =E11/E10-1 -> 0.0003233107
C12: 44287 | D12: 4181.17 | E12: 173.37 | F12: =D12/D11-1 -> 0.052425313 | G12: =E12/E11-1 -> 0.1206852 | I12: Beta Calculations
C13: 44317 | D13: 4204.11 | E13: 161.15 | F13: =D13/D12-1 -> 0.0054865026 | G13: =E13/E12-1 -> -0.07048509 | I13: AMZN Standard Deviation | J13: =_xlfn.STDEV.S(G10:G68) -> 0.090178662
C14: 44348 | D14: 4297.5 | E14: 172.01 | F14: =D14/D13-1 -> 0.022213976 | G14: =E14/E13-1 -> 0.06739063 | I14: S&P 500 Standard Deviation | J14: =_xlfn.STDEV.S(F10:F68) -> 0.043812395
C15: 44378 | D15: 4395.26 | E15: 166.38 | F15: =D15/D14-1 -> 0.022748109 | G15: =E15/E14-1 -> -0.032730655 | I15: Correlation Coefficient | J15: =CORREL(F10:F68,G10:G68) -> 0.66913721
C16: 44409 | D16: 4522.68 | E16: 173.54 | F16: =D16/D15-1 -> 0.028990321 | G16: =E16/E15-1 -> 0.043034019 | I16: Equity Beta | J16: =J15*J13/J14 -> 1.3772792 | K16: =SLOPE(G10:G68,F10:F68) -> 1.3772792
C17: 44440 | D17: 4307.54 | E17: 164.25 | F17: =D17/D16-1 -> -0.04756914 | G17: =E17/E16-1 -> -0.053532327
C18: 44470 | D18: 4605.38 | E18: 168.62 | F18: =D18/D17-1 -> 0.069143873 | G18: =E18/E17-1 -> 0.026605784 | I18: Source: Yahoo Finance
C19: 44501 | D19: 4567 | E19: 175.35 | F19: =D19/D18-1 -> -0.0083337314 | G19: =E19/E18-1 -> 0.039912229 | I19: https://finance.yahoo.com/quote/AMZN/history/?filter=history&frequency=1mo&period1=1607455486&period2=1765221833
C20: 44531 | D20: 4766.18 | E20: 166.72 | F20: =D20/D19-1 -> 0.043612875 | G20: =E20/E19-1 -> -0.049215854 | I20: https://finance.yahoo.com/quote/%5EGSPC/history/?period1=1609459200&period2=1767225600&interval=1mo&filter=history&frequency=1mo&includeAdjustedClose=true
C21: 44562 | D21: 4515.55 | E21: 149.57 | F21: =D21/D20-1 -> -0.052585089 | G21: =E21/E20-1 -> -0.10286708
C22: 44593 | D22: 4373.94 | E22: 153.56 | F22: =D22/D21-1 -> -0.031360521 | G22: =E22/E21-1 -> 0.026676473
C23: 44621 | D23: 4530.41 | E23: 163 | F23: =D23/D22-1 -> 0.035773239 | G23: =E23/E22-1 -> 0.061474342
C24: 44652 | D24: 4131.93 | E24: 124.28 | F24: =D24/D23-1 -> -0.087956719 | G24: =E24/E23-1 -> -0.23754601
C25: 44682 | D25: 4132.15 | E25: 120.21 | F25: =D25/D24-1 -> 5.3243884e-05 | G25: =E25/E24-1 -> -0.032748632
C26: 44713 | D26: 3785.38 | E26: 106.21 | F26: =D26/D25-1 -> -0.083919993 | G26: =E26/E25-1 -> -0.11646286
C27: 44743 | D27: 4130.29 | E27: 134.95 | F27: =D27/D26-1 -> 0.091116348 | G27: =E27/E26-1 -> 0.27059599
C28: 44774 | D28: 3955 | E28: 126.77 | F28: =D28/D27-1 -> -0.042440119 | G28: =E28/E27-1 -> -0.060615043
C29: 44805 | D29: 3585.62 | E29: 113 | F29: =D29/D28-1 -> -0.093395702 | G29: =E29/E28-1 -> -0.10862191
C30: 44835 | D30: 3871.98 | E30: 102.44 | F30: =D30/D29-1 -> 0.079863455 | G30: =E30/E29-1 -> -0.093451327
C31: 44866 | D31: 4080.11 | E31: 96.54 | F31: =D31/D30-1 -> 0.05375286 | G31: =E31/E30-1 -> -0.05759469
C32: 44896 | D32: 3839.5 | E32: 84 | F32: =D32/D31-1 -> -0.058971449 | G32: =E32/E31-1 -> -0.12989434
... C68: 45992 | D68: 6870.4 | E68: 229.53 | F68: =D68/D67-1 -> 0.0031113622 | G68: =E68/E67-1 -> -0.015821971

Sheet Forecasted FS
C3: Forecasted Financial Statements
C4: Figures in USD millions, unless told otherwise
C8: Scenario | D8: =IF(Scenarios!D8=Scenarios!D9,Scenarios!C9,IF(Scenarios!D8=Scenarios!D10,Scenarios!C10,Scenarios!C11)) -> Base Case
C10: Forecasting Assumptions
E12: 2024 Actual | F12: 2025 | G12: 2026 | H12: 2027 | I12: 2028 | J12: 2029 | L12: NOTES:
C13: Comprehensive Income Statement items:
C14: Sales Forecasted | E14: =E37 -> 637959 | F14: =E14*(1+F15) -> 682616.13 | G14: =F14*(1+G15) -> 744051.58 | H14: =G14*(1+H15) -> 811016.22 | I14: =H14*(1+I15) -> 892117.85 | J14: =I14*(1+J15) -> 981329.63 | L14: First year based on HWMS model
C15: Sales Growth Forecasted | E15: ='Actuals FS'!D149 -> 0.10990892 | F15: =Scenarios!E17 -> 0.07 | G15: =Scenarios!F17 -> 0.09 | H15: =Scenarios!G17 -> 0.09 | I15: =Scenarios!H17 -> 0.1 | J15: =Scenarios!I17 -> 0.1 | L15: Following scenario assumptions. First year is an adjustment to the base revenue forecasted with HWMS model
C16: Cost of Sales (% of sales) | E16: =D38 -> -0.51145607 | F16: =-Scenarios!E21 -> -0.51 | G16: =-Scenarios!F21 -> -0.505 | H16: =-Scenarios!G21 -> -0.5 | I16: =-Scenarios!H21 -> -0.495 | J16: =-Scenarios!I21 -> -0.49 | L16: Following scenario assumptions
C17: Fulfillment (% of sales) | E17: =D41 -> 0.15440647 | F17: =Scenarios!E25 -> 0.154 | G17: =Scenarios!F25 -> 0.152 | H17: =Scenarios!G25 -> 0.15 | I17: =Scenarios!H25 -> 0.148 | J17: =Scenarios!I25 -> 0.146 | L17: Following scenario assumptions
C18: Technology and infrastructure Exp (% of sales) | E18: =D42 -> 0.13879262 | F18: =Scenarios!E29 -> -0.145 | G18: =Scenarios!F29 -> -0.145 | H18: =Scenarios!G29 -> -0.14 | I18: =Scenarios!H29 -> -0.135 | J18: =Scenarios!I29 -> -0.13 | L18: Following scenario assumptions
C19: Sales and Marketing & General and Administrative (% of sales) | E19: =D43+D44 -> 0.086629392 | F19: =Scenarios!E33 -> 0.087 | G19: =Scenarios!F33 -> 0.086 | H19: =Scenarios!G33 -> 0.085 | I19: =Scenarios!H33 -> 0.084 | J19: =Scenarios!I33 -> 0.083 | L19: Following scenario assumptions
C20: Interest Income (% of Cash & Securities) | E20: =D49 -> 0.0073311921 | F20: =E20*(1+12%) -> 0.0082109352 | G20: =F20*(1+12%) -> 0.0091962474 | H20: =G20*(1+12%) -> 0.010299797 | I20: =H20*(1+12%) -> 0.011535773 | J20: =I20*(1+12%) -> 0.012920065
C21: Interest expense (% of sales) | E21: =D50 -> -0.0037714022 | F21: =Scenarios!E37 -> -0.15 | G21: =Scenarios!F37 -> -0.16 | H21: =Scenarios!G37 -> -0.17 | I21: =Scenarios!H37 -> -0.17 | J21: =Scenarios!I37 -> -0.17 | L21: Result of D&A schedule
C22: Other Operating Expense (Income) | E22: =D45 -> 0.0011960016 | F22: =E22*(1+1%) -> 0.0012079616 | G22: =F22*(1+1%) -> 0.0012200413 | H22: =G22*(1+1%) -> 0.0012322417 | I22: =H22*(1+1%) -> 0.0012445641 | J22: =I22*(1+1%) -> 0.0012570097
C23: Tax rate (% of income before tax) | E23: 0.21 | F23: 0.21 | G23: 0.21 | H23: 0.21 | I23: 0.21 | J23: 0.21 | L23: US Corporate Tax Rate (Source: PwC)
C24: Shares growth rate (%YOY) | E24: =D57 -> 0.016416415 | F24: =E24 -> 0.016416415 | G24: =F24 -> 0.016416415 | H24: =G24 -> 0.016416415 | I24: =H24 -> 0.016416415 | J24: =I24 -> 0.016416415 | L24: In order to increase dividend per share by high single digits as expected by management, gradual increase of 1% starting at 4% in 2023
L25: Slow down to accommodate dividend payment and deliver $10bln out of the $15bln share repurchase program authorized by CAT
C27: Balance Sheet accounts:
C28: Days in Receivables | E28: ='Actuals FS'!D113 -> 31.725573 | F28: =E28*(1+0.5%) -> 31.884201 | G28: =F28*(1+0.5%) -> 32.043622 | H28: =G28*(1+0.5%) -> 32.20384 | I28: =H28*(1+0.5%) -> 32.364859 | J28: =I28*(1+0.5%) -> 32.526684 | L28: Result of Capex growth and depreciation schedule
C29: Days in Inventory | E29: =E143 -> 38.273274 | F29: =E29*(1-0.5%) -> 38.081908 | G29: =F29*(1-0.5%) -> 37.891498 | H29: =G29*(1-0.5%) -> 37.702041 | I29: =H29*(1-0.5%) -> 37.51353 | J29: =I29*(1-0.5%) -> 37.325963 | L29: Result of amortization schedule
C30: Days in Payables | E30: =E146 -> 105.55857 | F30: =E30*(1-0.5%) -> 105.03078 | G30: =F30*(1-0.5%) -> 104.50562 | H30: =G30*(1-0.5%) -> 103.9831 | I30: =H30*(1-0.5%) -> 103.46318 | J30: =I30*(1-0.5%) -> 102.94586 | L30: Following scenario assumptions
C31: Capex (% of sales) | E31: ='Actuals FS'!D160 -> -0.13010084 | F31: =E31*(1-1.2%) -> -0.12853963 | G31: =F31*(1-1.2%) -> -0.12699715 | H31: =G31*(1-1.2%) -> -0.12547319 | I31: =H31*(1-1.2%) -> -0.12396751 | J31: =I31*(1-1.2%) -> -0.1224799 | L31: Following scenario assumptions
C32: P/E Multiple | E32: ='Actuals FS'!D142/'Actuals FS'!D143 -> 41.432409 | F32: =E32*(1-5%) -> 39.360789 | G32: =F32*(1-5%) -> 37.392749 | H32: =G32*(1-5%) -> 35.523112 | I32: =H32*(1-5%) -> 33.746956 | J32: =I32*(1-5%) -> 32.059608
C34: Forecasted Financial Statements
C36: 1. Income Statement for the year ended | D36: % of sales | E36: 2024 Actual | F36: 2025 | G36: 2026 | H36: 2027 | I36: 2028 | J36: 2029
C37: Total net sales | D37: =E37/$E$37 -> 1 | E37: ='Actuals FS'!D47 -> 637959 | F37: =F14 -> 682616.13 | G37: =F37*(1+G15) -> 744051.58 | H37: =G37*(1+H15) -> 811016.22 | I37: =H37*(1+I15) -> 892117.85 | J37: =I37*(1+J15) -> 981329.63 | L37: Following scenario assumptions
C38: Less Cost of sales | D38: =E38/$E$37 -> -0.51145607 | E38: =-('Actuals FS'!D48) -> -326288 | F38: =F16*F37 -> -348134.23 | G38: =G16*G37 -> -375746.05 | H38: =H16*H37 -> -405508.11 | I38: =I16*I37 -> -441598.33 | J38: =J16*J37 -> -480851.52 | L38: Following scenario assumptions
C39: Gross margin | D39: =E39/$E$37 -> 0.48854393 | E39: =E37+E38 -> 311671 | F39: =SUM(F37:F38) -> 334481.9 | G39: =SUM(G37:G38) -> 368305.53 | H39: =SUM(H37:H38) -> 405508.11 | I39: =SUM(I37:I38) -> 450519.51 | J39: =SUM(J37:J38) -> 500478.11
C40: Less Operating expenses:
C41: Fulfillment | D41: =E41/$E$37 -> 0.15440647 | E41: ='Actuals FS'!D49 -> 98505 | F41: =E41*(1+F17) -> 113674.77 | G41: =F41*(1+G17) -> 130953.34 | H41: =G41*(1+H17) -> 150596.34 | I41: =H41*(1+I17) -> 172884.59 | J41: =I41*(1+J17) -> 198125.74
C42: Technology and infrastructure | D42: =E42/$E$37 -> 0.13879262 | E42: ='Actuals FS'!D50 -> 88544 | F42: =E42*(1+F18) -> 75705.12 | G42: =F42*(1+G18) -> 64727.878 | H42: =G42*(1+H18) -> 55665.975 | I42: =H42*(1+I18) -> 48151.068 | J42: =I42*(1+J18) -> 41891.429 | L42: Following scenario assumptions
C43: Sales and Marketing | D43: =E43/$E$37 -> 0.068824172 | E43: ='Actuals FS'!D51 -> 43907 | F43: =E43*(1+F19) -> 47726.909 | G43: =F43*(1+G19) -> 51831.423 | H43: =G43*(1+H19) -> 56237.094 | I43: =H43*(1+I19) -> 60961.01 | J43: =I43*(1+J19) -> 66020.774 | L43: Following scenario assumptions
C44: General and Administrative | D44: =E44/$E$37 -> 0.017805219 | E44: ='Actuals FS'!D52 -> 11359 | F44: =E44*(1+F19) -> 12347.233 | G44: =F44*(1+G19) -> 13409.095 | H44: =G44*(1+H19) -> 14548.868 | I44: =H44*(1+I19) -> 15770.973 | J44: =I44*(1+J19) -> 17079.964
C45: Other Operating Expense (Income), net | D45: =E45/$E$37 -> 0.0011960016 | E45: ='Actuals FS'!D53 -> 763 | F45: =$D$45*F37 -> 816.41 | G45: =$D$45*G37 -> 889.8869 | H45: =$D$45*H37 -> 969.97672 | I45: =$D$45*I37 -> 1066.9744 | J45: =$D$45*J37 -> 1173.6718
C46: Total operating expenses | D46: =E46/$E$37 -> 0.89248055 | E46: ='Actuals FS'!D54 -> 569366 | F46: =SUM(F41:F45)+F39 -> 584752.35 | G46: =SUM(G41:G45)+G39 -> 630117.15 | H46: =SUM(H41:H45)+H39 -> 683526.36 | I46: =SUM(I41:I45)+I39 -> 749354.13 | J46: =SUM(J41:J45)+J39 -> 824769.69
C47: Operating Income | D47: =E47/$E$37 -> 0.10751945 | E47: ='Actuals FS'!D56 -> 68593 | F47: =F39-F41-F42-F43-F44-F45 -> 84211.462 | G47: =G39-G41-G42-G43-G44-G45 -> 106493.92 | H47: =H39-H41-H42-H43-H44-H45 -> 127489.86 | I47: =I39-I41-I42-I43-I44-I45 -> 151684.89 | J47: =J39-J41-J42-J43-J44-J45 -> 176186.53
C48: Non-Operating Items:
C49: Interest Income | D49: =E49/$E$37 -> 0.0073311921 | E49: ='Actuals FS'!D57 -> 4677 | F49: =$E$49*(1+F20) -> 4715.4025 | G49: =$E$49*(1+G20) -> 4720.0108 | H49: =$E$49*(1+H20) -> 4725.1722 | I49: =$E$49*(1+I20) -> 4730.9528 | J49: =$E$49*(1+J20) -> 4737.4271
C50: Interst Expense | D50: =E50/$E$37 -> -0.0037714022 | E50: ='Actuals FS'!D58 -> -2406 | F50: =$E$50*(1+F21) -> -2045.1 | G50: =$E$50*(1+G21) -> -2021.04 | H50: =$E$50*(1+H21) -> -1996.98 | I50: =$E$50*(1+I21) -> -1996.98 | J50: =$E$50*(1+J21) -> -1996.98
C51: Other Income (Expense, net) | D51: =E51/$E$37 -> -0.0035268724 | E51: ='Actuals FS'!D59 -> -2250 | F51: =$E$51*(1+F22) -> -2252.7179 | G51: =$E$51*(1+G22) -> -2252.7451 | H51: =$E$51*(1+H22) -> -2252.7725 | I51: =$E$51*(1+I22) -> -2252.8003 | J51: =$E$51*(1+J22) -> -2252.8283 | L51: For simplicity purposes, assuming current % of sales
C52: Income Before Income Taxes | D52: =E52/$E$37 -> 0.10755237 | E52: ='Actuals FS'!D61 -> 68614 | F52: =SUM(F47:F51) -> 84629.046 | G52: =SUM(G47:G51) -> 106940.14 | H52: =SUM(H47:H51) -> 127965.28 | I52: =SUM(I47:I51) -> 152166.07 | J52: =SUM(J47:J51) -> 176674.15 | L52: Following scenario assumptions
C53: Less Provision for Income tax | D53: =E53/$E$37 -> -0.014522877 | E53: ='Actuals FS'!D62 -> -9265 | F53: =-F52*F23 -> -17772.1 | G53: =-G52*G23 -> -22457.43 | H53: =-H52*H23 -> -26872.709 | I53: =-I52*I23 -> -31954.874 | J53: =-J52*J23 -> -37101.571 | L53: Assuming US corporate Tax Rate of 21% (Source: PwC)
C54: Net Income of consolidated companies | D54: =E54/$E$37 -> 0.093029489 | E54: =E52+E53 -> 59349 | F54: =F52+F53 -> 66856.947 | G54: =G52+G53 -> 84482.711 | H54: =H52+H53 -> 101092.57 | I54: =I52+I53 -> 120211.19 | J54: =J52+J53 -> 139572.58
C55: Equity-method investment activity, net of tax | D55: =E55/$E$37 -> -0.00015831738 | E55: ='Actuals FS'!D63 -> -101 | F55: =$D$55*F37 -> -108.07 | G55: =$D$55*G37 -> -117.7963 | H55: =$D$55*H37 -> -128.39797 | I55: =$D$55*I37 -> -141.23776 | J55: =$D$55*J37 -> -155.36154 | L55: For simplicity purposes, assuming current % of sales
C56: Net Income | D56: =E56/$E$37 -> 0.092871172 | E56: ='Actuals FS'!D64 -> 59248 | F56: =SUM(F54:F55) -> 66748.877 | G56: =SUM(G54:G55) -> 84364.915 | H56: =SUM(H54:H55) -> 100964.18 | I56: =SUM(I54:I55) -> 120069.95 | J56: =SUM(J54:J55) -> 139417.22
C57: Weighted average shares outstanding - basic | D57: =E57/$E$37 -> 0.016416415 | E57: 10473 | F57: =E57*(1+F24) -> 10644.929 | G57: =F57*(1+G24) -> 10819.681 | H57: =G57*(1+H24) -> 10997.301 | I57: =H57*(1+I24) -> 11177.837 | J57: =I57*(1+J24) -> 11361.337 | L57: Source: Page 37 (Diluted). Forecast ~1-2% growth for stock-based comp dilution
C58: Weighted average shares outstanding - diluted | D58: =E58/$E$37 -> 0.016805155 | E58: 10721 | F58: =E58*(1+F24) -> 10897 | G58: =F58*(1+G24) -> 11075.89 | H58: =G58*(1+H24) -> 11257.716 | I58: =H58*(1+I24) -> 11442.528 | J58: =I58*(1+J24) -> 11630.373
C60: 2. Balance sheet (B/S), as of year end | D60: % of sales | E60: 2024 Actual | F60: 2025 | G60: 2026 | H60: 2027 | I60: 2028 | J60: 2029
C61: Current assets:
C62: Cash and cash equivalents | D62: =E62/$E$37 -> 0.12348599 | E62: ='Actuals FS'!D12 -> 78779 | F62: =IF((SUM(F63:F65)+F72)>(F85+F93), E62, (F85+F93)-(SUM(F63:F65)+F72)) -> 152610.2 | G62: =IF((SUM(G63:G65)+G72)>(G85+G93), F62, (G85+G93)-(SUM(G63:G65)+G72)) -> 248470.26 | H62: =IF((SUM(H63:H65)+H72)>(H85+H93), G62, (H85+H93)-(SUM(H63:H65)+H72)) -> 357625.51 | I62: =IF((SUM(I63:I65)+I72)>(I85+I93), H62, (I85+I93)-(SUM(I63:I65)+I72)) -> 485458.26 | J62: =IF((SUM(J63:J65)+J72)>(J85+J93), I62, (J85+J93)-(SUM(J63:J65)+J72)) -> 629419.85 | L62: Cash generation throughout time
C63: Marketable securities | D63: =E63/$E$37 -> 0.035148027 | E63: ='Actuals FS'!D13 -> 22423 | F63: =E63 -> 22423 | G63: =F63 -> 22423 | H63: =G63 -> 22423 | I63: =H63 -> 22423 | J63: =I63 -> 22423 | L63: Following scenario assumptions
C64: Inventories | D64: =E64/$E$37 -> 0.053630406 | E64: ='Actuals FS'!D14 -> 34214 | F64: =(F29/365)*-F38 -> 36322.234 | G64: =(G29/365)*-G38 -> 39007.07 | H64: =(H29/365)*-H38 -> 41886.256 | I64: =(I29/365)*-I38 -> 45386.062 | J64: =(J29/365)*-J38 -> 49173.276 | L64: Following scenario assumptions
C65: Accounts receivable, net and other | D65: =E65/$E$37 -> 0.086919379 | E65: ='Actuals FS'!D15 -> 55451 | F65: =E65 -> 55451 | G65: =F65 -> 55451 | H65: =G65 -> 55451 | I65: =H65 -> 55451 | J65: =I65 -> 55451 | L65: For simplicity purposes, assuming no changes
C66: Total current assets | D66: =E66/$E$37 -> 0.2991838 | E66: =SUM(E62:E65) -> 190867 | F66: =SUM(F62:F65) -> 266806.43 | G66: =SUM(G62:G65) -> 365351.33 | H66: =SUM(H62:H65) -> 477385.76 | I66: =SUM(I62:I65) -> 608718.32 | J66: =SUM(J62:J65) -> 756467.12
C67: Non-current assets:
C68: Property and equipment, net | D68: =E68/$E$37 -> 0.3960521 | E68: ='Actuals FS'!D17 -> 252665 | F68: =E68+ABS(F114)-ABS(F102) -> 283529.94 | G68: =F68+ABS(F114)-ABS(F102) -> 314394.89 | H68: =G68+ABS(G114)-ABS(G102) -> 347973.18 | I68: =H68+ABS(H114)-ABS(H102) -> 384854.48 | J68: =I68+ABS(I114)-ABS(I102) -> 426729.09 | L68: Result of Capex growth and depreciation schedule
C69: Operating leases | D69: =E69/$E$37 -> 0.11935093 | E69: ='Actuals FS'!D18 -> 76141 | F69: =$D$69*F37 -> 81470.87 | G69: =$D$69*G37 -> 88803.248 | H69: =$D$69*H37 -> 96795.541 | I69: =$D$69*I37 -> 106475.09 | J69: =$D$69*J37 -> 117122.6 | L69: For simplicity purposes, assuming current % of sales
C70: Goodwill | D70: =E70/$E$37 -> 0.036168469 | E70: ='Actuals FS'!D19 -> 23074 | F70: =E70 -> 23074 | G70: =F70 -> 23074 | H70: =G70 -> 23074 | I70: =H70 -> 23074 | J70: =I70 -> 23074 | L70: Result of amortization schedule
C71: Other assets | D71: =E71/$E$37 -> 0.12876533 | E71: ='Actuals FS'!D20 -> 82147 | F71: =E71 -> 82147 | G71: =F71 -> 82147 | H71: =G71 -> 82147 | I71: =H71 -> 82147 | J71: =I71 -> 82147 | L71: For simplicity purposes, assuming no changes
C72: Total non-current assets | D72: =E72/$E$37 -> 0.68033682 | E72: =SUM(E68:E71) -> 434027 | F72: =SUM(F68:F71) -> 470221.81 | G72: =SUM(G68:G71) -> 508419.14 | H72: =SUM(H68:H71) -> 549989.72 | I72: =SUM(I68:I71) -> 596550.58 | J72: =SUM(J68:J71) -> 649072.69
C73: Total assets | D73: =E73/$E$37 -> 0.97952063 | E73: =E72+E66 -> 624894 | F73: =F72+F66 -> 737028.24 | G73: =G72+G66 -> 873770.46 | H73: =H72+H66 -> 1027375.5 | I73: =I72+I66 -> 1205268.9 | J73: =J72+J66 -> 1405539.8
C74: Current liabilities:
C75: Accounts payable | D75: =E75/$E$37 -> 0.14791389 | E75: ='Actuals FS'!D24 -> 94363 | F75: =-(F38/365)*F30 -> 100177.56 | G75: =-(G38/365)*G30 -> 107582.4 | H75: =-(H38/365)*H30 -> 115523.26 | I75: =-(I38/365)*I30 -> 125175.8 | J75: =-(J38/365)*J30 -> 135621.03 | L75: Following scenario assumptions
C76: Accrued expenses and other | D76: =E76/$E$37 -> 0.10496756 | E76: ='Actuals FS'!D25 -> 66965 | F76: =$D$76*F37 -> 71652.55 | G76: =$D$76*G37 -> 78101.28 | H76: =$D$76*H37 -> 85130.395 | I76: =$D$76*I37 -> 93643.434 | J76: =$D$76*J37 -> 103007.78 | L76: For simplicity purposes, assuming no changes
C77: Unearned revenue | D77: =E77/$E$37 -> 0.028376432 | E77: ='Actuals FS'!D26 -> 18103 | F77: =$D$77*F37 -> 19370.21 | G77: =$D$77*G37 -> 21113.529 | H77: =$D$77*H37 -> 23013.747 | I77: =$D$77*I37 -> 25315.121 | J77: =$D$77*J37 -> 27846.633 | L77: Additional financing needs for any shortfall in working capital
C78: Total current liabilities | D78: =E78/$E$37 -> 0.28125789 | E78: =SUM(E75:E77) -> 179431 | F78: =SUM(F75:F77) -> 191200.32 | G78: =SUM(G75:G77) -> 206797.21 | H78: =SUM(H75:H77) -> 223667.4 | I78: =SUM(I75:I77) -> 244134.36 | J78: =SUM(J75:J77) -> 266475.44
C79: Non-current liabilities:
C80: Long-term lease liabilities | D80: =E80/$E$37 -> 0.12269911 | E80: ='Actuals FS'!D28 -> 78277 | F80: =$D$80*F37 -> 83756.39 | G80: =$D$80*G37 -> 91294.465 | H80: =$D$80*H37 -> 99510.967 | I80: =$D$80*I37 -> 109462.06 | J80: =$D$80*J37 -> 120408.27
C81: Long-term debt | D81: =E81/$E$37 -> 0.082486492 | E81: ='Actuals FS'!D29 -> 52623 | F81: =(E81-F122)-F124 -> 57214 | G81: =(F81-F122)-F124 -> 61805 | H81: =(G81-G122)-G124 -> 64100.5 | I81: =(H81-H122)-H124 -> 65248.25 | J81: =(I81-I122)-I124 -> 65822.125
C82: Other long-term liabilities | D82: =E82/$E$37 -> 0.044819495 | E82: ='Actuals FS'!D30 -> 28593 | F82: =$D$82*F37 -> 30594.51 | G82: =$D$82*G37 -> 33348.016 | H82: =$D$82*H37 -> 36349.337 | I82: =$D$82*I37 -> 39984.271 | J82: =$D$82*J37 -> 43982.698 | L82: Assuming current % of sales to support the investments in capital expenditure and other assets
C83: Commitments and contingencies (Note 7) | D83: =E83/$E$37 -> 0 | E83: ='Actuals FS'!D31 -> 0 | F83: =E83 -> 0 | G83: =F83 -> 0 | H83: =G83 -> 0 | I83: =H83 -> 0 | J83: =I83 -> 0 | L83: For simplicity purposes, assuming no changes
C84: Total non-current liabilities | D84: =E84/$E$37 -> 0.25000509 | E84: =SUM(E80:E83) -> 159493 | F84: =SUM(F80:F83) -> 171564.9 | G84: =SUM(G80:G83) -> 186447.48 | H84: =SUM(H80:H83) -> 199960.8 | I84: =SUM(I80:I83) -> 214694.58 | J84: =SUM(J80:J83) -> 230213.09
C85: Total liabilities | D85: =E85/$E$37 -> 0.53126298 | E85: =E78+E84 -> 338924 | F85: =F78+F84 -> 362765.22 | G85: =G78+G84 -> 393244.69 | H85: =H78+H84 -> 423628.2 | I85: =I78+I84 -> 458828.94 | J85: =J78+J84 -> 496688.53
C86: Shareholder's Equity:
C87: Preferred stock ($0.01 par value; 500 shares authorized) | D87: =E87/$E$37 -> 0 | E87: ='Actuals FS'!D35 -> 0 | F87: =E87 -> 0 | G87: =F87 -> 0 | H87: =G87 -> 0 | I87: =H87 -> 0 | J87: =I87 -> 0
C88: Common stock ($0.01 par value; 100,000 shares authorized) | D88: =E88/$E$37 -> 0.00017399237 | E88: ='Actuals FS'!D36 -> 111 | F88: =E88*(1+2%) -> 113.22 | G88: =F88*(1+2%) -> 115.4844 | H88: =G88*(1+2%) -> 117.79409 | I88: =H88*(1+2%) -> 120.14997 | J88: =I88*(1+2%) -> 122.55297
C89: Treasury stock, at cost | D89: =E89/$E$37 -> -0.012284489 | E89: ='Actuals FS'!D37 -> -7837 | F89: =E89 -> -7837 | G89: =F89 -> -7837 | H89: =G89 -> -7837 | I89: =H89 -> -7837 | J89: =I89 -> -7837 | L89: Assuming no share issuance
C90: Additional paid-in capital | D90: =E90/$E$37 -> 0.18945418 | E90: ='Actuals FS'!D38 -> 120864 | F90: =E90+F56+F57+F58 -> 209154.81 | G90: =F90+G56+G57+G58 -> 315415.29 | H90: =G90+H56+H57+H58 -> 438634.48 | I90: =H90+I56+I57+I58 -> 581324.8 | J90: =I90+J56+J57+J58 -> 743733.73 | L90: Growth based on net income, less dividends and share repurchased
C91: Accumulated other comprehensive income (loss) | D91: =E91/$E$37 -> -5.3294961e-05 | E91: ='Actuals FS'!D39 -> -34 | F91: =E91 -> -34 | G91: =F91 -> -34 | H91: =G91 -> -34 | I91: =H91 -> -34 | J91: =I91 -> -34 | L91: For simplicity purposes, assuming no changes
C92: Retained earnings | D92: =E92/$E$37 -> 0.27096726 | E92: ='Actuals FS'!D40 -> 172866 | F92: =E92 -> 172866 | G92: =F92 -> 172866 | H92: =G92 -> 172866 | I92: =H92 -> 172866 | J92: =I92 -> 172866 | L92: For simplicity purposes, assuming no changes
C93: Total shareholders' equity | D93: =E93/$E$37 -> 0.44825765 | E93: =SUM(E87:E92) -> 285970 | F93: =SUM(F87:F92) -> 374263.03 | G93: =SUM(G87:G92) -> 480525.78 | H93: =SUM(H87:H92) -> 603747.28 | I93: =SUM(I87:I92) -> 746439.95 | J93: =SUM(J87:J92) -> 908851.28
C94: Total liabilities and shareholders' equity | D94: =E94/$E$37 -> 0.97952063 | E94: =E93+E85 -> 624894 | F94: =F93+F85 -> 737028.24 | G94: =G93+G85 -> 873770.46 | H94: =H93+H85 -> 1027375.5 | I94: =I93+I85 -> 1205268.9 | J94: =J93+J85 -> 1405539.8
C95: Check | E95: =E94-E73 -> 0 | F95: =F94-F73 -> 0 | G95: =G94-G73 -> 0 | H95: =H94-H73 -> 0 | I95: =I94-I73 -> 0 | J95: =J94-J73 -> 0
C97: 3. Statement of Cash Flows, for the year ended | E97: 2024 Actual | F97: 2025 | G97: 2026 | H97: 2027 | I97: 2028 | J97: 2029
C98: CASH, CASH EQUIVALENTS, AND RESTRICTED CASH, BEGINNING OF PERIOD | E98: ='Actuals FS'!D71 -> 73890 | F98: =E130 -> 82312 | G98: =F130 -> 138129.18 | H98: =G130 -> 196687.75 | I98: =H130 -> 268056.14 | J98: =I130 -> 351675.93
C99: OPERATING ACTIVITIES:
C100: Net income (loss) | E100: ='Actuals FS'!D73 -> 59248 | F100: =F56 -> 66748.877 | G100: =G56 -> 84364.915 | H100: =H56 -> 100964.18 | I100: =I56 -> 120069.95 | J100: =J56 -> 139417.22
C101: Adjustments to reconcile net income (loss) to net cash from operating activities:
C102: Depreciation and amortization of property and equipment and capitalized content costs, operating lease assets, and other | E102: ='Actuals FS'!D75 -> 52795 | F102: =E102*(1+$E$102/F37) -> 56878.279 | G102: =F102*(1+$E$102/G37) -> 60914.14 | H102: =G102*(1+$E$102/H37) -> 64879.488 | I102: =H102*(1+$E$102/I37) -> 68719.018 | J102: =I102*(1+$E$102/J37) -> 72416.063
C103: Stock-based compensation | E103: ='Actuals FS'!D76 -> 22011 | F103: =E103*(1+$E$103/F37) -> 22720.746 | G103: =F103*(1+$E$103/G37) -> 23392.885 | H103: =G103*(1+$E$103/H37) -> 24027.769 | I103: =H103*(1+$E$103/I37) -> 24620.6 | J103: =I103*(1+$E$103/J37) -> 25172.834
C104: Non-operating expense (income), net | E104: ='Actuals FS'!D77 -> 2012 | F104: 0 | G104: 0 | H104: 0 | I104: 0 | J104: 0 | L104: It is impossible to reliably predict the future stock price movements of public companies Amazon invests in. Therefore, the standard "neutral" modeling assumption is to assume no further gains or losses.
C105: Deferred income taxes | E105: ='Actuals FS'!D78 -> -4648 | F105: =F53*50% -> -8886.0499 | G105: =G53*50% -> -11228.715 | H105: =H53*50% -> -13436.355 | I105: =I53*50% -> -15977.437 | J105: =J53*50% -> -18550.786
C106: Changes in operating assets and liabilities:
C107: Inventories | E107: ='Actuals FS'!D80 -> -1884 | F107: =E64-F64 -> -2108.234 | G107: =F64-G64 -> -2684.8363 | H107: =G64-H64 -> -2879.1852 | I107: =H64-I64 -> -3499.8061 | J107: =I64-J64 -> -3787.2147
C108: Accounts receivable, net and other | E108: ='Actuals FS'!D81 -> -3249 | F108: =E65-F65 -> 0 | G108: =F65-G65 -> 0 | H108: =G65-H65 -> 0 | I108: =H65-I65 -> 0 | J108: =I65-J65 -> 0
C109: Other assets | E109: ='Actuals FS'!D82 -> -14483 | F109: =E71-F71 -> 0 | G109: =F71-G71 -> 0 | H109: =G71-H71 -> 0 | I109: =H71-I71 -> 0 | J109: =I71-J71 -> 0
C110: Accounts payable | E110: ='Actuals FS'!D83 -> 2972 | F110: =-(E75-F75) -> 5814.558 | G110: =-(F75-G75) -> 7404.8403 | H110: =-(G75-H75) -> 7940.8592 | I110: =-(H75-I75) -> 9652.5458 | J110: =-(I75-J75) -> 10445.225
C111: Accrued expenses and other | E111: ='Actuals FS'!D84 -> -2904 | F111: =-(E76-F76) -> 4687.55 | G111: =F76-G76 -> -6448.7295 | H111: =G76-H76 -> -7029.1152 | I111: =H76-I76 -> -8513.0395 | J111: =I76-J76 -> -9364.3434
C112: Unearned revenue | E112: ='Actuals FS'!D85 -> 4007 | F112: =-(E77-F77) -> 1267.21 | G112: =F77-G77 -> -1743.3189 | H112: =G77-H77 -> -1900.2176 | I112: =H77-I77 -> -2301.3747 | J112: =I77-J77 -> -2531.5121
...

Sheet WACC
B3: Weighted Average Cost of Capital
B4: Figures in USD millions, unless told otherwise
C8: Weighted Average Cost of Capital Calculations | I8: NOTES:
C10: Beta Methodology | E10: Regression | F10: Comps | I10: Selection of WACC based on the regression methodology of Beta as it represents the individual risk of CAT
C11: Capital Structure
C12: Debt / Total Capitalization | E12: =E35/E37 -> 0.020665509 | F12: =E35/E37 -> 0.020665509 | I12: Market value of debt using current median price of outstanding bonds
C13: Equity / Total Capitalization | E13: =E36/E37 -> 0.97933449 | F13: =E36/E37 -> 0.97933449 | I13: Current market capitalization
C14: Debt / Equity | E14: =E12/E13 -> 0.021101584 | F14: =F12/F13 -> 0.021101584
C16: Cost of Equity Breakdown
C17: Risk Free-Rate | E17: ='10yr TBill'!D2551/100 -> 0.0405 | F17: =E17 -> 0.0405 | I17: Current YTM of US 10yr T-Bill
C18: Expected Market Return | E18: ='10 Year Bond Average'!G9 -> 0.14052675 | F18: =E18 -> 0.14052675 | I18: Historic 10yr S&P return (Source: S&P)
C19: Benchmark Risk Free-Rate | E19: ='10yr TBill'!G8/100 -> 0.026371914 | F19: =E19 -> 0.026371914 | I19: Historic 10yr average YTM of 10yr US T-Bill (Source: US Department of The Treasury)
C20: Market Risk Premium | E20: 0.05 | F20: 0.05
C21: Unlevered Beta | E21: =E22/(1+(1-E26)*E14) -> 1.354696 | F21: =H86 -> 0.86865496 | I21: Using the Hamada Equation
C22: Levered Beta | E22: ='Reg. Beta'!J16 -> 1.3772792 | F22: =F21*(1+(1-F26)*F14) -> 0.88313565 | I22: Using the Hamada Equation
C23: Cost of Equity | E23: =E17+E20*E22 -> 0.10936396 | F23: =F17+F20*F22 -> 0.084656783 | I23: Using the Capital Asset Pricing Model
C25: Cost of Debt | E25: =F50 -> 0.0455 | F25: =E25 -> 0.0455 | I25: Weighted Average Cost of Debt
C26: Tax Rate | E26: ='Tax Rate'!D8 -> 0.21 | F26: =E26 -> 0.21 | I26: US Corporate Tax Rate (Source: PwC)
C27: After Tax Cost of Debt | E27: =E25*(1-E26) -> 0.035945 | F27: =F25*(1-F26) -> 0.035945
C29: WACC | E29: =(E23*E13)+(E27*E12) -> 0.10784672 | F29: =(F23*F13)+(F27*F12) -> 0.083650129
C31: Capital Structure Breakdown
D33: Date | E33: Value | F33: Weight
C34: Median Current Price | D34: =Bonds!D8 -> 46003 | E34: =Bonds!O46 -> 97.240717
C35: Market Value of Debt | E35: =D48*E34/100 -> 51170.983 | F35: =E35/E37 -> 0.020665509
C36: Market Value of Equity | D36: 45001 | E36: =DCF!E43 -> 2424983 | F36: =E36/E37 -> 0.97933449
C37: Total Capitalization | E37: =E35+E36 -> 2476154 | F37: =E37/E37 -> 1
C39: Source: CAT 10-K, Morningstar, Yahoo Finance
C40: https://investors.caterpillar.com/financials/quarterly-results/default.aspx
C41: https://finra-markets.morningstar.com/BondCenter/Default.jsp
C42: https://finance.yahoo.com/quote/CAT/history?p=CAT
C44: Cost of Debt Breakdown
D46: Value | E46: Weight | F46: Rate
C47: Long-term debt | D47: ='Actuals FS'!D29 -> 52623 | E47: =D47/$D$48 -> 1 | F47: =Bonds!$K$46 -> 0.0455
C48: Total Debt | D48: =SUM(D47:D47) -> 52623 | E48: =D48/$D$48 -> 1
C50: Weighted Average Cost of Debt | F50: =SUMPRODUCT(E47:E47,F47:F47) -> 0.0455
C52: Source: AMZN 10-K
C58: WACC Sensitivity Analysis
E60: Cost of Debt
C61: Stressing (+/- 1%) | D61: D/V | E61: =F61-0.01 -> 0.0255 | F61: =G61-0.01 -> 0.0355 | G61: =E25 -> 0.0455 | H61: =G61+0.01 -> 0.0555 | I61: =H61+0.01 -> 0.0655
C62: - Cost of Debt | D62: =D63-0.01 -> 0.00066550915 | E62: =E$61*(1-$E$26)*$D62+(1-$D62)*($E$17+$E$20*($E$21*(1+(1-$E$26)*($D62/(1-$D62))))) -> 0.10821179 | F62: =F$61*(1-$E$26)*$D62+(1-$D62)*($E$17+$E$20*($E$21*(1+(1-$E$26)*($D62/(1-$D62))))) -> 0.10821705 | G62: =G$61*(1-$E$26)*$D62+(1-$D62)*($E$17+$E$20*($E$21*(1+(1-$E$26)*($D62/(1-$D62))))) -> 0.1082223 | H62: =H$61*(1-$E$26)*$D62+(1-$D62)*($E$17+$E$20*($E$21*(1+(1-$E$26)*($D62/(1-$D62))))) -> 0.10822756 | I62: =I$61*(1-$E$26)*$D62+(1-$D62)*($E$17+$E$20*($E$21*(1+(1-$E$26)*($D62/(1-$D62))))) -> 0.10823282
C63: - Debt to Total Capitalization | D63: =D64-0.01 -> 0.010665509 | E63: =E$61*(1-$E$26)*$D63+(1-$D63)*($E$17+$E$20*($E$21*(1+(1-$E$26)*($D63/(1-$D63))))) -> 0.107866 | F63: =F$61*(1-$E$26)*$D63+(1-$D63)*($E$17+$E$20*($E$21*(1+(1-$E$26)*($D63/(1-$D63))))) -> 0.10795025 | G63: =G$61*(1-$E$26)*$D63+(1-$D63)*($E$17+$E$20*($E$21*(1+(1-$E$26)*($D63/(1-$D63))))) -> 0.10803451 | H63: =H$61*(1-$E$26)*$D63+(1-$D63)*($E$17+$E$20*($E$21*(1+(1-$E$26)*($D63/(1-$D63))))) -> 0.10811877 | I63: =I$61*(1-$E$26)*$D63+(1-$D63)*($E$17+$E$20*($E$21*(1+(1-$E$26)*($D63/(1-$D63))))) -> 0.10820303
D64: =E12 -> 0.020665509 | E64: =E$61*(1-$E$26)*$D64+(1-$D64)*($E$17+$E$20*($E$21*(1+(1-$E$26)*($D64/(1-$D64))))) -> 0.1075202 | F64: =F$61*(1-$E$26)*$D64+(1-$D64)*($E$17+$E$20*($E$21*(1+(1-$E$26)*($D64/(1-$D64))))) -> 0.10768346 | G64: =G$61*(1-$E$26)*$D64+(1-$D64)*($E$17+$E$20*($E$21*(1+(1-$E$26)*($D64/(1-$D64))))) -> 0.10784672 | H64: =H$61*(1-$E$26)*$D64+(1-$D64)*($E$17+$E$20*($E$21*(1+(1-$E$26)*($D64/(1-$D64))))) -> 0.10800998 | I64: =I$61*(1-$E$26)*$D64+(1-$D64)*($E$17+$E$20*($E$21*(1+(1-$E$26)*($D64/(1-$D64))))) -> 0.10817323
D65: =D64+0.01 -> 0.030665509 | E65: =E$61*(1-$E$26)*$D65+(1-$D65)*($E$17+$E$20*($E$21*(1+(1-$E$26)*($D65/(1-$D65))))) -> 0.10717441 | F65: =F$61*(1-$E$26)*$D65+(1-$D65)*($E$17+$E$20*($E$21*(1+(1-$E$26)*($D65/(1-$D65))))) -> 0.10741667 | G65: =G$61*(1-$E$26)*$D65+(1-$D65)*($E$17+$E$20*($E$21*(1+(1-$E$26)*($D65/(1-$D65))))) -> 0.10765892 | H65: =H$61*(1-$E$26)*$D65+(1-$D65)*($E$17+$E$20*($E$21*(1+(1-$E$26)*($D65/(1-$D65))))) -> 0.10790118 | I65: =I$61*(1-$E$26)*$D65+(1-$D65)*($E$17+$E$20*($E$21*(1+(1-$E$26)*($D65/(1-$D65))))) -> 0.10814344
D66: =D65+0.01 -> 0.040665509 | E66: =E$61*(1-$E$26)*$D66+(1-$D66)*($E$17+$E$20*($E$21*(1+(1-$E$26)*($D66/(1-$D66))))) -> 0.10682862 | F66: =F$61*(1-$E$26)*$D66+(1-$D66)*($E$17+$E$20*($E$21*(1+(1-$E$26)*($D66/(1-$D66))))) -> 0.10714987 | G66: =G$61*(1-$E$26)*$D66+(1-$D66)*($E$17+$E$20*($E$21*(1+(1-$E$26)*($D66/(1-$D66))))) -> 0.10747113 | H66: =H$61*(1-$E$26)*$D66+(1-$D66)*($E$17+$E$20*($E$21*(1+(1-$E$26)*($D66/(1-$D66))))) -> 0.10779239 | I66: =I$61*(1-$E$26)*$D66+(1-$D66)*($E$17+$E$20*($E$21*(1+(1-$E$26)*($D66/(1-$D66))))) -> 0.10811365
D68: High | E68: =MAX(E62:I66) -> 0.10823282 | H68: Median | I68: =MEDIAN(E62:I66) -> 0.10795025
D69: Low | E69: =MIN(E62:I66) -> 0.10682862 | H69: Average | I69: =AVERAGE(E62:I66) -> 0.10784672
C71: Beta Buildup Based on Selected Comparable Industry Peers
C73: Company Name | D73: Country | E73: Equity Beta | F73: Tax Rate | G73: D / E | H73: Asset Beta
C74: Microsoft Corporation | D74: =Multiples!G28 -> USA | E74: ='Peer Mkt Info'!H10 -> 1.03 | F74: ='Tax Rate'!D8 -> 0.21 | G74: =VLOOKUP(C74,'Peer Fin Info'!$D$11:$S$20,16,FALSE) -> 0.16678602 | H74: =E74/(1+(1-F74)*G74) -> 0.91008618
C75: Alphabet Inc. | D75: =Multiples!G29 -> USA | E75: ='Peer Mkt Info'!H11 -> 0.93 | F75: ='Tax Rate'!D8 -> 0.21 | G75: =VLOOKUP(C75,'Peer Fin Info'!$D$11:$S$20,16,FALSE) -> 0.087143644 | H75: =E75/(1+(1-F75)*G75) -> 0.87009934
C76: Meta Platforms, Inc. | D76: =Multiples!G30 -> USA | E76: ='Peer Mkt Info'!H12 -> 1.48 | F76: ='Tax Rate'!D8 -> 0.21 | G76: =VLOOKUP(C76,'Peer Fin Info'!$D$11:$S$20,16,FALSE) -> 0.26310637 | H76: =E76/(1+(1-F76)*G76) -> 1.2253136
C77: Oracle Corporation | D77: =Multiples!G31 -> USA | E77: ='Peer Mkt Info'!H13 -> 1.86 | F77: ='Tax Rate'!D8 -> 0.21 | G77: =VLOOKUP(C77,'Peer Fin Info'!$D$11:$S$20,16,FALSE) -> 4.0839873 | H77: =E77/(1+(1-F77)*G77) -> 0.44009607
C78: Walmart Inc. | D78: =Multiples!G32 -> USA | E78: ='Peer Mkt Info'!H14 -> 2.86 | F78: ='Tax Rate'!D8 -> 0.21 | G78: =VLOOKUP(C78,'Peer Fin Info'!$D$11:$S$20,16,FALSE) -> 0.66747308 | H78: =E78/(1+(1-F78)*G78) -> 1.872581
C79: Costco Wholesale | D79: =Multiples!G33 -> USA | E79: ='Peer Mkt Info'!H15 -> 1.12 | F79: ='Tax Rate'!D8 -> 0.21 | G79: =VLOOKUP(C79,'Peer Fin Info'!$D$11:$S$20,16,FALSE) -> 0.28024277 | H79: =E79/(1+(1-F79)*G79) -> 0.91698668
C80: Target Corporation | D80: =Multiples!G34 -> USA | E80: ='Peer Mkt Info'!H16 -> 1.46 | F80: ='Tax Rate'!D8 -> 0.21 | G80: =VLOOKUP(C80,'Peer Fin Info'!$D$11:$S$20,16,FALSE) -> 1.2928843 | H80: =E80/(1+(1-F80)*G80) -> 0.72227933
C81: Alibaba Group | D81: =Multiples!G35 -> China | E81: ='Peer Mkt Info'!H17 -> 0.32 | F81: 0.25 | G81: =VLOOKUP(C81,'Peer Fin Info'!$D$11:$S$20,16,FALSE) -> 0.24568801 | H81: =E81/(1+(1-F81)*G81) -> 0.27020956
C82: Apple Inc. | D82: =Multiples!G36 -> USA | E82: ='Peer Mkt Info'!H18 -> 1.03 | F82: ='Tax Rate'!D8 -> 0.21 | G82: =VLOOKUP(C82,'Peer Fin Info'!$D$11:$S$20,16,FALSE) -> 1.3380305 | H82: =E82/(1+(1-F82)*G82) -> 0.50071849
C83: Netflix, Inc. | D83: =Multiples!G37 -> USA | E83: ='Peer Mkt Info'!H19 -> 1.38 | F83: ='Tax Rate'!D8 -> 0.21 | G83: =VLOOKUP(C83,'Peer Fin Info'!$D$11:$S$20,16,FALSE) -> 0.55725516 | H83: =E83/(1+(1-F83)*G83) -> 0.95817924
C84: Low | E84: =MIN(E74:E83) -> 0.32 | G84: =MIN(G74:G83) -> 0.087143644 | H84: =MIN(H74:H83) -> 0.27020956
C85: Median | E85: =MEDIAN(E74:E83) -> 1.25 | G85: =MEDIAN(G74:G83) -> 0.41874896 | H85: =MEDIAN(H74:H83) -> 0.89009276
C86: Mean | E86: =AVERAGE(E74:E83) -> 1.347 | G86: =AVERAGE(G74:G83) -> 0.89825971 | H86: =AVERAGE(H74:H83) -> 0.86865496
C87: High | E87: =MAX(E74:E83) -> 2.86 | G87: =MAX(G74:G83) -> 4.0839873 | H87: =MAX(H74:H83) -> 1.872581
C89: NOTE: Debt to Equity ratio of comparable companies is based on book value of debt and market value of equity
C90: Source: Pitchbook, Yahoo Finance
C91: https://my.pitchbook.com/dashboard
C92: https://finance.yahoo.com/?guccounter=1
C93: https://taxsummaries.pwc.com/peoples-republic-of-china/corporate/taxes-on-corporate-income#:~:text=A%20non%2DTRE%20with%20an,standard%20tax%20rate%20is%2025%25.

Sheet DCF
C3: Discounted Cash Flows Model
C4: Figures in USD millions, unless told otherwise
C8: General Considerations | I8: .
C10: SCENARIO | E10: =IF(Scenarios!D8=1,Scenarios!C9,IF(Scenarios!D8=2,Scenarios!C10,Scenarios!C11)) -> Base Case
C11: Tax Rate | E11: ='Tax Rate'!D8 -> 0.21
C12: Discount Rate | E12: =WACC!E29 -> 0.10784672
C13: Terminal Growth Rate | E13: 0.03
C14: Current Price (12/12/25) | E14: ='AMZN daily'!G8 -> 226.19
C15: Shares Outstanding | E15: ='Actuals FS'!D68 -> 10721
C16: Asset Beta | E16: =WACC!E21 -> 1.354696
C17: Equity Risk Premium | E17: =WACC!E20 -> 0.05
C18: Risk Free Rate | E18: =WACC!E17 -> 0.0405
C19: Cost of Debt | E19: =WACC!E25 -> 0.0455
C20: Price of Debt | E20: =WACC!E34 -> 97.240717
C22: Valuation Based on Discounted Cash Flows Methodology
E24: Entry | F24: 2025 F | G24: 2026 F | H24: 2027 F | I24: 2028 F | J24: 2029 F | K24: Exit | M24: Terminal Value
C25: Date | E25: 45292 | F25: =DATE(YEAR($E$25)+F26,1,1) -> 45658 | G25: =DATE(YEAR($E$25)+G26,1,1) -> 46023 | H25: =DATE(YEAR($E$25)+H26,1,1) -> 46388 | I25: =DATE(YEAR($E$25)+I26,1,1) -> 46753 | J25: =DATE(YEAR($E$25)+J26,1,1) -> 47119 | K25: =DATE(YEAR($E$25)+K26,1,1) -> 47119 | M25: Perpetual Value | O25: =J38*(1+O26) -> 354944.96
C26: Time Periods | E26: 0 | F26: =E26+1 -> 1 | G26: =F26+1 -> 2 | H26: =G26+1 -> 3 | I26: =H26+1 -> 4 | J26: =I26+1 -> 5 | K26: =J26 -> 5 | M26: Growth Rate | O26: =E13 -> 0.03
C27: Revenues | E27: ='Forecasted FS'!E37 -> 637959 | F27: ='Forecasted FS'!F37 -> 682616.13 | G27: ='Forecasted FS'!G37 -> 744051.58 | H27: ='Forecasted FS'!H37 -> 811016.22 | I27: ='Forecasted FS'!I37 -> 892117.85 | J27: ='Forecasted FS'!J37 -> 981329.63 | M27: Perpetual Value | O27: =O25/(E12-O26) -> 4559536.6
C28: Growth (%) | E28: ='Actuals FS'!D47/'Actuals FS'!E47-1 -> 0.10990892 | F28: =F27/E27-1 -> 0.07 | G28: =G27/F27-1 -> 0.09 | H28: =H27/G27-1 -> 0.09 | I28: =I27/H27-1 -> 0.1 | J28: 0.02
C29: EBITDA | E29: =E31+E35 -> 121388 | F29: =F31+F35 -> 141375.57 | G29: =G31+G35 -> 168388.7 | H29: =H31+H35 -> 194506.82 | I29: =I31+I35 -> 224247.91 | J29: =J31+J35 -> 254754.58 | M29: Rate of Returns
C30: Margin (%) | E30: =E29/E27 -> 0.19027555 | F30: =F29/F27 -> 0.20710845 | G30: =G29/G27 -> 0.22631321 | H30: =H29/H27 -> 0.23983099 | I30: =I29/I27 -> 0.2513658 | J30: =J29/J27 -> 0.25960144 | M30: Target Upside Return (%) | O30: =O39/O37-1 -> 0.29534647
C31: EBIT | E31: ='Forecasted FS'!E47 -> 68593 | F31: ='Forecasted FS'!F47 -> 84211.462 | G31: ='Forecasted FS'!G47 -> 106493.92 | H31: ='Forecasted FS'!H47 -> 127489.86 | I31: ='Forecasted FS'!I47 -> 151684.89 | J31: ='Forecasted FS'!J47 -> 176186.53 | M31: Cost of Equity (%) | O31: =E18+E17*E16 -> 0.1082348
C32: Margin (%) | E32: =E31/E27 -> 0.10751945 | F32: =F31/F27 -> 0.12336577 | G32: =G31/G27 -> 0.14312706 | H32: =H31/H27 -> 0.15719767 | I32: =I31/I27 -> 0.17002787 | J32: =J31/J27 -> 0.17953858 | M32: IRR (%) | O32: =XIRR(E40:K40,E25:K25) -> 0.16202695
C33: - Cash Taxes | D33: =E11 -> 0.21 | E33: =-$D$33*E31 -> -14404.53 | F33: =-$D$33*F31 -> -17684.407 | G33: =-$D$33*G31 -> -22363.722 | H33: =-$D$33*H31 -> -26772.871 | I33: =-$D$33*I31 -> -31853.828 | J33: =-$D$33*J31 -> -36999.171 | M33: ROIC (%) | O33: ='Forecasted FS'!J153 -> 0.15583335
C34: NOPAT | E34: =SUM(E31:E33) -> 54188.578 | F34: =SUM(F31:F33) -> 66527.178 | G34: =SUM(G31:G33) -> 84130.336 | H34: =SUM(H31:H33) -> 100717.15 | I34: =SUM(I31:I33) -> 119831.24 | J34: =SUM(J31:J33) -> 139187.54 | M34: WACC (%) | O34: =E12 -> 0.10784672
C35: + D&A | E35: ='D&A'!E22 -> 52795 | F35: ='D&A'!F22 -> 57164.108 | G35: ='D&A'!G22 -> 61894.787 | H35: ='D&A'!H22 -> 67016.958 | I35: ='D&A'!I22 -> 72563.021 | J35: ='D&A'!J22 -> 78568.053
C36: - Capex | E36: =-'Forecasted FS'!E114 -> 82999 | F36: =-'Forecasted FS'!F114 -> 87743.223 | G36: =-'Forecasted FS'!G114 -> 94492.432 | H36: =-'Forecasted FS'!H114 -> 101760.79 | I36: =-'Forecasted FS'!I114 -> 110593.63 | J36: =-'Forecasted FS'!J114 -> 120193.15 | M36: Market Value vs Intrinsic Value
C37: - Changes in NWC | E37: =-E74 -> 5288 | F37: =-F74 -> 3706.324 | G37: =-G74 -> 4720.004 | H37: =-H74 -> 5061.674 | I37: =-I74 -> 6152.7397 | J37: =-J74 -> 6658.0107 | M37: Market Value | O37: =E49 -> 226.19
C38: Unlevered FCF | E38: =SUM(E34:E37) -> 195270.58 | F38: =SUM(F34:F37) -> 215140.83 | G38: =SUM(G34:G37) -> 245237.56 | H38: =SUM(H34:H37) -> 274556.57 | I38: =SUM(I34:I37) -> 309140.62 | J38: =SUM(J34:J37) -> 344606.75 | M38: Upside | O38: =I49-E49 -> 66.804418
C39: (Entry)/Exit | E39: =-E47 -> -3023721 | K39: =O27 -> 4559536.6 | M39: Intrinsic Value | O39: =I49 -> 292.99442
C40: Transaction CF | E40: =E39 -> -3023721 | F40: =F38 -> 215140.83 | G40: =G38 -> 245237.56 | H40: =H38 -> 274556.57 | I40: =I38 -> 309140.62 | J40: =J38 -> 344606.75 | K40: =K39 -> 4559536.6
C42: Market Value | G42: Intrinsic Value
C43: Market Cap. | E43: =E14*E15 -> 2424983 | G43: Enterprise Value | I43: =NPV(E12,F40:I40,J40+K40) -> 3739931.2
C44: + Debt | E44: ='Actuals FS'!D133 -> 52623 | G44: - Debt | I44: =-E44 -> -52623
C45: - Cash | E45: =-'Forecasted FS'!E62 -> -78779 | G45: + Cash | I45: =-E45 -> 78779
C46: + Minority Interest | E46: ='Actuals FS'!D42 -> 624894 | G46: - Minority Interest | I46: =-E46 -> -624894
C47: Enterprise Value | E47: =SUM(E43:E46) -> 3023721 | G47: Equity Value | I47: =SUM(I43:I46) -> 3141193.2
C49: Equity Value/Share | E49: =E14 -> 226.19 | G49: Equity Value/Share | I49: =I47/E15 -> 292.99442
C51: Sensitivity Analysis
D53: Intrinsic Price | K53: Equity Value | R53: Enterprise Value
C55: Stressing (+/- 1%) | E55: WACC | L55: WACC | S55: WACC
C56: - Cost of Capital | D56: Growth | E56: =F56-0.01 -> 0.087846718 | F56: =G56-0.01 -> 0.097846718 | G56: =E12 -> 0.10784672 | H56: =G56+0.01 -> 0.11784672 | I56: =H56+0.01 -> 0.12784672 | K56: Growth | L56: =M56-0.01 -> 0.087846718 | M56: =N56-0.01 -> 0.097846718 | N56: =G56 -> 0.10784672 | O56: =N56+0.01 -> 0.11784672 | P56: =O56+0.01 -> 0.12784672 | R56: Growth | S56: =T56-0.01 -> 0.087846718 | T56: =U56-0.01 -> 0.097846718 | U56: =N56 -> 0.10784672 | V56: =U56+0.01 -> 0.11784672 | W56: =V56+0.01 -> 0.12784672
C57: - Growth Rate | D57: =D58-1% -> 0.01 | E57: =L57/$E$15 -> 317.24508 | F57: =M57/$E$15 -> 272.49543 | G57: =N57/$E$15 -> 236.96537 | H57: =O57/$E$15 -> 208.08723 | I57: =P57/$E$15 -> 184.16499 | K57: =D57 -> 0.01 | L57: =S57+SUM($I$44:$I$46) -> 3401184.5 | M57: =T57+SUM($I$44:$I$46) -> 2921423.5 | N57: =U57+SUM($I$44:$I$46) -> 2540505.8 | O57: =V57+SUM($I$44:$I$46) -> 2230903.2 | P57: =W57+SUM($I$44:$I$46) -> 1974432.9 | R57: =K57 -> 0.01 | S57: =NPV(S$56,$F$38:$I$38,$J$38+(($J$38*(1+$R57))/(S$56-$R57))) -> 3999922.5 | T57: =NPV(T$56,$F$38:$I$38,$J$38+(($J$38*(1+$R57))/(T$56-$R57))) -> 3520161.5 | U57: =NPV(U$56,$F$38:$I$38,$J$38+(($J$38*(1+$R57))/(U$56-$R57))) -> 3139243.8 | V57: =NPV(V$56,$F$38:$I$38,$J$38+(($J$38*(1+$R57))/(V$56-$R57))) -> 2829641.2 | W57: =NPV(W$56,$F$38:$I$38,$J$38+(($J$38*(1+$R57))/(W$56-$R57))) -> 2573170.9
D58: =D59-1% -> 0.02 | E58: =L58/$E$15 -> 360.70096 | F58: =M58/$E$15 -> 304.8515 | G58: =N58/$E$15 -> 261.79087 | H58: =O58/$E$15 -> 227.59494 | I58: =P58/$E$15 -> 199.79516 | K58: =D58 -> 0.02 | L58: =S58+SUM($I$44:$I$46) -> 3867075 | M58: =T58+SUM($I$44:$I$46) -> 3268312.9 | N58: =U58+SUM($I$44:$I$46) -> 2806659.9 | O58: =V58+SUM($I$44:$I$46) -> 2440045.3 | P58: =W58+SUM($I$44:$I$46) -> 2142003.9 | R58: =K58 -> 0.02 | S58: =NPV(S$56,$F$38:$I$38,$J$38+(($J$38*(1+$R58))/(S$56-$R58))) -> 4465813 | T58: =NPV(T$56,$F$38:$I$38,$J$38+(($J$38*(1+$R58))/(T$56-$R58))) -> 3867050.9 | U58: =NPV(U$56,$F$38:$I$38,$J$38+(($J$38*(1+$R58))/(U$56-$R58))) -> 3405397.9 | V58: =NPV(V$56,$F$38:$I$38,$J$38+(($J$38*(1+$R58))/(V$56-$R58))) -> 3038783.3 | W58: =NPV(W$56,$F$38:$I$38,$J$38+(($J$38*(1+$R58))/(W$56-$R58))) -> 2740741.9
D59: =E13 -> 0.03 | E59: =L59/$E$15 -> 419.18133 | F59: =M59/$E$15 -> 346.74557 | G59: =N59/$E$15 -> 292.99442 | H59: =O59/$E$15 -> 251.54395 | I59: =P59/$E$15 -> 218.62016 | K59: =D59 -> 0.03 | L59: =S59+SUM($I$44:$I$46) -> 4494043 | M59: =T59+SUM($I$44:$I$46) -> 3717459.2 | N59: =U59+SUM($I$44:$I$46) -> 3141193.2 | O59: =V59+SUM($I$44:$I$46) -> 2696802.7 | P59: =W59+SUM($I$44:$I$46) -> 2343826.8 | R59: =K59 -> 0.03 | S59: =NPV(S$56,$F$38:$I$38,$J$38+(($J$38*(1+$R59))/(S$56-$R59))) -> 5092781 | T59: =NPV(T$56,$F$38:$I$38,$J$38+(($J$38*(1+$R59))/(T$56-$R59))) -> 4316197.2 | U59: =NPV(U$56,$F$38:$I$38,$J$38+(($J$38*(1+$R59))/(U$56-$R59))) -> 3739931.2 | V59: =NPV(V$56,$F$38:$I$38,$J$38+(($J$38*(1+$R59))/(V$56-$R59))) -> 3295540.7 | W59: =NPV(W$56,$F$38:$I$38,$J$38+(($J$38*(1+$R59))/(W$56-$R59))) -> 2942564.8
D60: =D59+1% -> 0.04 | E60: =L60/$E$15 -> 502.10658 | F60: =M60/$E$15 -> 403.12414 | G60: =N60/$E$15 -> 333.39621 | H60: =O60/$E$15 -> 281.64583 | I60: =P60/$E$15 -> 241.73104 | K60: =D60 -> 0.04 | L60: =S60+SUM($I$44:$I$46) -> 5383084.6 | M60: =T60+SUM($I$44:$I$46) -> 4321893.9 | N60: =U60+SUM($I$44:$I$46) -> 3574340.8 | O60: =V60+SUM($I$44:$I$46) -> 3019525 | P60: =W60+SUM($I$44:$I$46) -> 2591598.4 | R60: =K60 -> 0.04 | S60: =NPV(S$56,$F$38:$I$38,$J$38+(($J$38*(1+$R60))/(S$56-$R60))) -> 5981822.6 | T60: =NPV(T$56,$F$38:$I$38,$J$38+(($J$38*(1+$R60))/(T$56-$R60))) -> 4920631.9 | U60: =NPV(U$56,$F$38:$I$38,$J$38+(($J$38*(1+$R60))/(U$56-$R60))) -> 4173078.8 | V60: =NPV(V$56,$F$38:$I$38,$J$38+(($J$38*(1+$R60))/(V$56-$R60))) -> 3618263 | W60: =NPV(W$56,$F$38:$I$38,$J$38+(($J$38*(1+$R60))/(W$56-$R60))) -> 3190336.4
D61: =D60+1% -> 0.05 | E61: =L61/$E$15 -> 628.85346 | F61: =M61/$E$15 -> 483.06904 | G61: =N61/$E$15 -> 387.76657 | H61: =O61/$E$15 -> 320.62121 | I61: =P61/$E$15 -> 270.77944 | K61: =D61 -> 0.05 | L61: =S61+SUM($I$44:$I$46) -> 6741938 | M61: =T61+SUM($I$44:$I$46) -> 5178983.2 | N61: =U61+SUM($I$44:$I$46) -> 4157245.4 | O61: =V61+SUM($I$44:$I$46) -> 3437380 | P61: =W61+SUM($I$44:$I$46) -> 2903026.4 | R61: =K61 -> 0.05 | S61: =NPV(S$56,$F$38:$I$38,$J$38+(($J$38*(1+$R61))/(S$56-$R61))) -> 7340676 | T61: =NPV(T$56,$F$38:$I$38,$J$38+(($J$38*(1+$R61))/(T$56-$R61))) -> 5777721.2 | U61: =NPV(U$56,$F$38:$I$38,$J$38+(($J$38*(1+$R61))/(U$56-$R61))) -> 4755983.4 | V61: =NPV(V$56,$F$38:$I$38,$J$38+(($J$38*(1+$R61))/(V$56-$R61))) -> 4036118 | W61: =NPV(W$56,$F$38:$I$38,$J$38+(($J$38*(1+$R61))/(W$56-$R61))) -> 3501764.4
D63: High | E63: =MAX(E57:I61) -> 628.85346 | H63: Median | I63: =MEDIAN(E57:I61) -> 292.99442 | K63: High | L63: =MAX(L57:P61) -> 6741938 | O63: Median | P63: =MEDIAN(L57:P61) -> 3141193.2 | R63: High | S63: =MAX(S57:W61) -> 7340676 | V63: Median | W63: =MEDIAN(S57:W61) -> 3739931.2
D64: Low | E64: =MIN(E57:I61) -> 184.16499 | H64: Average | I64: =AVERAGE(E57:I61) -> 318.23482 | K64: Low | L64: =MIN(L57:P61) -> 1974432.9 | O64: Average | P64: =AVERAGE(L57:P61) -> 3411795.5 | R64: Low | S64: =MIN(S57:W61) -> 2573170.9 | V64: Average | W64: =AVERAGE(S57:W61) -> 4010533.5
C67: Working Capital Summary
E69: 2024 Actual | F69: 2025 F | G69: 2026 F | H69: 2027 F | I69: 2028 F | J69: 2029 F
C70: Accounts Receivable | E70: ='Forecasted FS'!E65 -> 55451 | F70: ='Forecasted FS'!F65 -> 55451 | G70: ='Forecasted FS'!G65 -> 55451 | H70: ='Forecasted FS'!H65 -> 55451 | I70: ='Forecasted FS'!I65 -> 55451 | J70: ='Forecasted FS'!J65 -> 55451
C71: Inventory | E71: ='Forecasted FS'!E64 -> 34214 | F71: ='Forecasted FS'!F64 -> 36322.234 | G71: ='Forecasted FS'!G64 -> 39007.07 | H71: ='Forecasted FS'!H64 -> 41886.256 | I71: ='Forecasted FS'!I64 -> 45386.062 | J71: ='Forecasted FS'!J64 -> 49173.276
C72: Accounts Payable | E72: ='Forecasted FS'!E75 -> 94363 | F72: ='Forecasted FS'!F75 -> 100177.56 | G72: ='Forecasted FS'!G75 -> 107582.4 | H72: ='Forecasted FS'!H75 -> 115523.26 | I72: ='Forecasted FS'!I75 -> 125175.8 | J72: ='Forecasted FS'!J75 -> 135621.03
C73: Working Capital | E73: =E70+E71-E72 -> -4698 | F73: =F70+F71-F72 -> -8404.324 | G73: =G70+G71-G72 -> -13124.328 | H73: =H70+H71-H72 -> -18186.002 | I73: =I70+I71-I72 -> -24338.742 | J73: =J70+J71-J72 -> -30996.752
C74: Changes in W/C | E74: =E73-('Actuals FS'!E14+'Actuals FS'!E15-'Actuals FS'!E24) -> -5288 | F74: =F73-('Forecasted FS'!E64+'Forecasted FS'!E65-'Forecasted FS'!E75) -> -3706.324 | G74: =G73-('Forecasted FS'!F64+'Forecasted FS'!F65-'Forecasted FS'!F75) -> -4720.004 | H74: =H73-('Forecasted FS'!G64+'Forecasted FS'!G65-'Forecasted FS'!G75) -> -5061.674 | I74: =I73-('Forecasted FS'!H64+'Forecasted FS'!H65-'Forecasted FS'!H75) -> -6152.7397 | J74: =J73-('Forecasted FS'!I64+'Forecasted FS'!I65-'Forecasted FS'!I75) -> -6658.0107
C77: Terminal Growth Rate
D79: Revenue Weight | F79: Risk Free Rate
C80: United States | D80: =Revenue!H83 -> 0.68658801 | F80: =E18 -> 0.0405 | G80: US 10Y T-Bill
C81: Germany | D81: =Revenue!H84 -> 0.064041733 | F81: 0.028633 | G81: German 10Y Bund
C82: United Kingdom | D82: =Revenue!H85 -> 0.059337669 | F82: 0.0453 | G82: UK 10-Year Gilt
C83: Japan | D83: =Revenue!H86 -> 0.042951036 | F83: 0.01963 | G83: Japan 10Y Notes
C84: Rest Of World | D84: =Revenue!H87 -> 0.14708155 | F84: 0.052 | G84: Average 10Y Note
C85: Weighted Terminal Growth Rate | F85: =SUMPRODUCT(D80:D84,F80:F84) -> 0.040819887
C86: Premium | F86: 0.005 | G86: Based on expected capitalization of transition to clean energy
C87: Terminal Growth Rate | F87: =F86+F85 -> 0.045819887
C89: Source: World Government Bonds, US Department of The Treasury

Sheet References
B7: References
B8: 1 | C8: https://ir.aboutamazon.com/sec-filings/default.aspx
B9: 2 | C9: https://smartasset.com/taxes/corporate-tax-rate-per-state
B10: 3 | C10: https://markets.businessinsider.com/searchresults?p=1&_type=anleihen&_search=Amazon
B11: 4 | C11: https://www.cnbc.com/quotes/DE10Y-DE
B12: 5 | C12: https://www.cnbc.com/quotes/JP10Y-JP
B13: 6 | C13: https://www.cnbc.com/quotes/UK10Y-GB
B14: 7 | C14: https://my.pitchbook.com/profile/11919-79/company/profile#overview
B15: 8 | C15: https://finance.yahoo.com/quote/AMZN/profile/
B16: 9 | C16: https://finra-markets.morningstar.com/MarketData/EquityOptions/detail.jsp?query=19%3A0P000000B7&sdkVersion=2.63.2
B17: 10 | C17: https://my.pitchbook.com/dashboard
B18: 11 | C18: https://finance.yahoo.com/?guccounter=1
B19: 12 | C19: https://finance.yahoo.com/quote/AMZN/history/?filter=history&frequency=1mo&period1=1607455486&period2=1765221833
... B47: 40 | C47: https://www.bvresources.com/articles/bvwire/kroll-lowers-recommended-us-erp-to-50#:~:text=September%2010%2C%202025,discount%20rates%20as%20of%20Sept.

Sheet Appendix
C3: Additional Information
B7: Appendix
B8: 1 | C8: ='FS all'!C3 -> Financial Statements
B9: =B8+1 -> 2 | C9: =Ratios!C3 -> Financial Ratios Analysis
B10: =B9+1 -> 3 | C10: ='Operating Margin'!C3 -> Operating Margin Target Based on Management Expectations
B11: =B10+1 -> 4 | C11: ='D&A'!C3 -> Depreciation & Amortization Schedule
B12: =B11+1 -> 5 | C12: =Bonds!C3 -> Summary of Corporate Bonds
B13: =B12+1 -> 6 | C13: ='Scenario Summary '!C3 -> Scenario Summary
B14: =B13+1 -> 7 | C14: ='Peer Mkt Info'!C3 -> Industry Peers Market Information
B15: =B14+1 -> 8 | C15: ='Peer Fin Info'!C3 -> Industry Peers Financial Information
B16: =B15+1 -> 9 | C16: ='10 Year Bond Average'!C3 -> 10 year Historic S&P Returns
B17: =B16+1 -> 10 | C17: ='AMZN daily'!C3 -> AMZN Historic Daily Stock Prices from 12/12/205 to date (12/12/2025)
B18: =B17+1 -> 11 | C18: ='10yr TBill'!C3 -> 10 year Historic Yield to Maturity of US 10 year Treasury Bill
B19: =B18+1 -> 12 | C19: ='Tax Rate'!C3 -> Country Corporate Income Tax Rate
B20: =B19+1 -> 13 | C20: =FX!C3 -> Local Currency Exchange Rate to US Dollar
B21: =B20+1 -> 14 | C21: =BoD!C3 -> Board of Directors
B22: =B21+1 -> 15 | C22: ='Exec. Team'!C3 -> Senior Executive Team
B23: =B22+1 -> 16 | C23: =Shareholders!C3 -> Top 5 Institutional Investors & Insider Holders
B24: =B23+1 -> 17 | C24: =Abbreviations!C3 -> Abbreviations

Sheet FS all
C3: Financial Statements
C4: Figures in USD millions, unless told otherwise
C8: Financial Statements
C10: 1. Income Statement for the year ended | D10: 2020 A | E10: 2021 A | F10: 2022 A | G10: 2023 A | H10: 2024 A | I10: 2025 F | J10: 2026 F | K10: 2027 F | L10: 2028 F | M10: 2029 F
C11: Total net sales | D11: ='Actuals FS'!H47 -> 386064 | E11: ='Actuals FS'!G47 -> 469822 | F11: ='Actuals FS'!F47 -> 513983 | G11: ='Actuals FS'!E47 -> 574785 | H11: ='Forecasted FS'!E37 -> 637959 | I11: ='Forecasted FS'!F37 -> 682616.13 | J11: ='Forecasted FS'!G37 -> 744051.58 | K11: ='Forecasted FS'!H37 -> 811016.22 | L11: ='Forecasted FS'!I37 -> 892117.85 | M11: ='Forecasted FS'!J37 -> 981329.63
C12: Less Cost of sales | D12: =-'Actuals FS'!H48 -> -233307 | E12: =-'Actuals FS'!G48 -> -272344 | F12: =-'Actuals FS'!F48 -> -288831 | G12: =-'Actuals FS'!E48 -> -304739 | H12: ='Forecasted FS'!E38 -> -326288 | I12: ='Forecasted FS'!F38 -> -348134.23 | J12: ='Forecasted FS'!G38 -> -375746.05 | K12: ='Forecasted FS'!H38 -> -405508.11 | L12: ='Forecasted FS'!I38 -> -441598.33 | M12: ='Forecasted FS'!J38 -> -480851.52
C13: Gross margin | D13: =SUM(D11:D12) -> 152757 | E13: =SUM(E11:E12) -> 197478 | F13: =SUM(F11:F12) -> 225152 | G13: =SUM(G11:G12) -> 270046 | H13: ='Forecasted FS'!E39 -> 311671 | I13: ='Forecasted FS'!F39 -> 334481.9 | J13: ='Forecasted FS'!G39 -> 368305.53 | K13: ='Forecasted FS'!H39 -> 405508.11 | L13: ='Forecasted FS'!I39 -> 450519.51 | M13: ='Forecasted FS'!J39 -> 500478.11
C14: Less Operating expenses:
C15: Fulfillment | D15: ='Actuals FS'!H49 -> 58517 | E15: ='Actuals FS'!G49 -> 75111 | F15: ='Actuals FS'!F49 -> 84299 | G15: ='Actuals FS'!E49 -> 90619 | H15: ='Forecasted FS'!E41 -> 98505 | I15: ='Forecasted FS'!F41 -> 113674.77 | J15: ='Forecasted FS'!G41 -> 130953.34 | K15: ='Forecasted FS'!H41 -> 150596.34 | L15: ='Forecasted FS'!I41 -> 172884.59 | M15: ='Forecasted FS'!J41 -> 198125.74
C16: Technology and infrastructure | D16: ='Actuals FS'!H50 -> 42740 | E16: ='Actuals FS'!G50 -> 56052 | F16: ='Actuals FS'!F50 -> 73213 | G16: ='Actuals FS'!E50 -> 85622 | H16: ='Forecasted FS'!E42 -> 88544 | I16: ='Forecasted FS'!F42 -> 75705.12 | J16: ='Forecasted FS'!G42 -> 64727.878 | K16: ='Forecasted FS'!H42 -> 55665.975 | L16: ='Forecasted FS'!I42 -> 48151.068 | M16: ='Forecasted FS'!J42 -> 41891.429
C17: Sales and Marketing | D17: ='Actuals FS'!H51 -> 22008 | E17: ='Actuals FS'!G51 -> 32551 | F17: ='Actuals FS'!F51 -> 42238 | G17: ='Actuals FS'!E51 -> 44370 | H17: ='Forecasted FS'!E43 -> 43907 | I17: ='Forecasted FS'!F43 -> 47726.909 | J17: ='Forecasted FS'!G43 -> 51831.423 | K17: ='Forecasted FS'!H43 -> 56237.094 | L17: ='Forecasted FS'!I43 -> 60961.01 | M17: ='Forecasted FS'!J43 -> 66020.774
C18: General and Administrative | D18: ='Actuals FS'!H52 -> 6668 | E18: ='Actuals FS'!G52 -> 8823 | F18: ='Actuals FS'!F52 -> 11891 | G18: ='Actuals FS'!E52 -> 11816 | H18: ='Forecasted FS'!E44 -> 11359 | I18: ='Forecasted FS'!F44 -> 12347.233 | J18: ='Forecasted FS'!G44 -> 13409.095 | K18: ='Forecasted FS'!H44 -> 14548.868 | L18: ='Forecasted FS'!I44 -> 15770.973 | M18: ='Forecasted FS'!J44 -> 17079.964
C19: Other Operating Expense (Income), net | D19: ='Actuals FS'!H53 -> -75 | E19: ='Actuals FS'!G53 -> 62 | F19: ='Actuals FS'!F53 -> 1263 | G19: ='Actuals FS'!E53 -> 767 | H19: ='Forecasted FS'!E45 -> 763 | I19: ='Forecasted FS'!F45 -> 816.41 | J19: ='Forecasted FS'!G45 -> 889.8869 | K19: ='Forecasted FS'!H45 -> 969.97672 | L19: ='Forecasted FS'!I45 -> 1066.9744 | M19: ='Forecasted FS'!J45 -> 1173.6718
C20: Total operating expenses | D20: ='Actuals FS'!H54 -> 363165 | E20: ='Actuals FS'!G54 -> 444943 | F20: ='Actuals FS'!F54 -> 501735 | G20: ='Actuals FS'!E54 -> 537933 | H20: ='Forecasted FS'!E46 -> 569366 | I20: ='Forecasted FS'!F46 -> 584752.35 | J20: ='Forecasted FS'!G46 -> 630117.15 | K20: ='Forecasted FS'!H46 -> 683526.36 | L20: ='Forecasted FS'!I46 -> 749354.13 | M20: ='Forecasted FS'!J46 -> 824769.69
C21: Operating Income | D21: ='Actuals FS'!H56 -> 22899 | E21: ='Actuals FS'!G56 -> 24879 | F21: ='Actuals FS'!F56 -> 12248 | G21: ='Actuals FS'!E56 -> 36852 | H21: ='Forecasted FS'!E47 -> 68593 | I21: ='Forecasted FS'!F47 -> 84211.462 | J21: ='Forecasted FS'!G47 -> 106493.92 | K21: ='Forecasted FS'!H47 -> 127489.86 | L21: ='Forecasted FS'!I47 -> 151684.89 | M21: ='Forecasted FS'!J47 -> 176186.53
C22: Non-Operating Items:
C23: Interest Income | D23: ='Actuals FS'!H57 -> 555 | E23: ='Actuals FS'!G57 -> 448 | F23: ='Actuals FS'!F57 -> 989 | G23: ='Actuals FS'!E57 -> 2949 | H23: ='Forecasted FS'!E49 -> 4677 | I23: ='Forecasted FS'!F49 -> 4715.4025 | J23: ='Forecasted FS'!G49 -> 4720.0108 | K23: ='Forecasted FS'!H49 -> 4725.1722 | L23: ='Forecasted FS'!I49 -> 4730.9528 | M23: ='Forecasted FS'!J49 -> 4737.4271
C24: Interst Expense | D24: ='Actuals FS'!H58 -> -1647 | E24: ='Actuals FS'!G58 -> -1809 | F24: ='Actuals FS'!F58 -> -2367 | G24: ='Actuals FS'!E58 -> -3182 | H24: ='Forecasted FS'!E50 -> -2406 | I24: ='Forecasted FS'!F50 -> -2045.1 | J24: ='Forecasted FS'!G50 -> -2021.04 | K24: ='Forecasted FS'!H50 -> -1996.98 | L24: ='Forecasted FS'!I50 -> -1996.98 | M24: ='Forecasted FS'!J50 -> -1996.98
C25: Other Income (Expense, net) | D25: ='Actuals FS'!H59 -> 2371 | E25: ='Actuals FS'!G59 -> 14633 | F25: ='Actuals FS'!F59 -> -16806 | G25: ='Actuals FS'!E59 -> 938 | H25: ='Forecasted FS'!E51 -> -2250 | I25: ='Forecasted FS'!F51 -> -2252.7179 | J25: ='Forecasted FS'!G51 -> -2252.7451 | K25: ='Forecasted FS'!H51 -> -2252.7725 | L25: ='Forecasted FS'!I51 -> -2252.8003 | M25: ='Forecasted FS'!J51 -> -2252.8283
C26: Income Before Income Taxes | D26: ='Actuals FS'!H61 -> 24178 | E26: ='Actuals FS'!G61 -> 38151 | F26: ='Actuals FS'!F61 -> -5936 | G26: ='Actuals FS'!E61 -> 37557 | H26: ='Forecasted FS'!E52 -> 68614 | I26: ='Forecasted FS'!F52 -> 84629.046 | J26: ='Forecasted FS'!G52 -> 106940.14 | K26: ='Forecasted FS'!H52 -> 127965.28 | L26: ='Forecasted FS'!I52 -> 152166.07 | M26: ='Forecasted FS'!J52 -> 176674.15
C27: Less Provision for Income tax | D27: ='Actuals FS'!H62 -> -2863 | E27: ='Actuals FS'!G62 -> -4791 | F27: ='Actuals FS'!F62 -> 3217 | G27: ='Actuals FS'!E62 -> -7120 | H27: ='Forecasted FS'!E53 -> -9265 | I27: ='Forecasted FS'!F53 -> -17772.1 | J27: ='Forecasted FS'!G53 -> -22457.43 | K27: ='Forecasted FS'!H53 -> -26872.709 | L27: ='Forecasted FS'!I53 -> -31954.874 | M27: ='Forecasted FS'!J53 -> -37101.571
C28: Net Income of consolidated companies | D28: =D26+D27 -> 21315 | E28: =E26+E27 -> 33360 | F28: =F26+F27 -> -2719 | G28: =G26+G27 -> 30437 | H28: ='Forecasted FS'!E54 -> 59349 | I28: ='Forecasted FS'!F54 -> 66856.947 | J28: ='Forecasted FS'!G54 -> 84482.711 | K28: ='Forecasted FS'!H54 -> 101092.57 | L28: ='Forecasted FS'!I54 -> 120211.19 | M28: ='Forecasted FS'!J54 -> 139572.58
C29: Equity-method investment activity, net of tax | D29: ='Actuals FS'!H63 -> 16 | E29: ='Actuals FS'!G63 -> 4 | F29: ='Actuals FS'!F63 -> -3 | G29: ='Actuals FS'!E63 -> -12 | H29: ='Forecasted FS'!E55 -> -101 | I29: ='Forecasted FS'!F55 -> -108.07 | J29: ='Forecasted FS'!G55 -> -117.7963 | K29: ='Forecasted FS'!H55 -> -128.39797 | L29: ='Forecasted FS'!I55 -> -141.23776 | M29: ='Forecasted FS'!J55 -> -155.36154
C30: Net Income | D30: ='Actuals FS'!H64 -> 21331 | E30: ='Actuals FS'!G64 -> 33364 | F30: ='Actuals FS'!F64 -> -2722 | G30: ='Actuals FS'!E64 -> 30425 | H30: ='Forecasted FS'!E56 -> 59248 | I30: ='Forecasted FS'!F56 -> 66748.877 | J30: ='Forecasted FS'!G56 -> 84364.915 | K30: ='Forecasted FS'!H56 -> 100964.18 | L30: ='Forecasted FS'!I56 -> 120069.95 | M30: ='Forecasted FS'!J56 -> 139417.22
C31: Weighted average shares outstanding - basic | D31: ='Actuals FS'!H67 -> 500 | E31: ='Actuals FS'!G67 -> 506 | F31: ='Actuals FS'!F67 -> 10189 | G31: ='Actuals FS'!E67 -> 10304 | H31: ='Forecasted FS'!E57 -> 10473 | I31: ='Forecasted FS'!F57 -> 10644.929 | J31: ='Forecasted FS'!G57 -> 10819.681 | K31: ='Forecasted FS'!H57 -> 10997.301 | L31: ='Forecasted FS'!I57 -> 11177.837 | M31: ='Forecasted FS'!J57 -> 11361.337
C32: Weighted average shares outstanding - diluted | D32: ='Actuals FS'!H68 -> 510 | E32: ='Actuals FS'!G68 -> 515 | F32: ='Actuals FS'!F68 -> 10189 | G32: ='Actuals FS'!E68 -> 10492 | H32: ='Forecasted FS'!E58 -> 10721 | I32: ='Forecasted FS'!F58 -> 10897 | J32: ='Forecasted FS'!G58 -> 11075.89 | K32: ='Forecasted FS'!H58 -> 11257.716 | L32: ='Forecasted FS'!I58 -> 11442.528 | M32: ='Forecasted FS'!J58 -> 11630.373
C34: 2. Balance sheet (B/S), as of year end | D34: =D10 -> 2020 A | E34: =E10 -> 2021 A | F34: =F10 -> 2022 A | G34: =G10 -> 2023 A | H34: =H10 -> 2024 A | I34: =I10 -> 2025 F | J34: =J10 -> 2026 F | K34: =K10 -> 2027 F | ... M34: =M10 -> 2029 F
C35: Current assets:
C36: Cash and cash equivalents | D36: ='Actuals FS'!H12 -> 42122 | E36: ='Actuals FS'!G12 -> 36220 | F36: ='Actuals FS'!F12 -> 53888 | G36: ='Actuals FS'!E12 -> 73387 | H36: ='Forecasted FS'!E62 -> 78779 | I36: ='Forecasted FS'!F62 -> 152610.2 | J36: ='Forecasted FS'!G62 -> 248470.26 | K36: ='Forecasted FS'!H62 -> 357625.51 | L36: ='Forecasted FS'!I62 -> 485458.26 | M36: ='Forecasted FS'!J62 -> 629419.85
C37: Marketable securities | D37: ='Actuals FS'!H13 -> 42274 | E37: ='Actuals FS'!G13 -> 59829 | F37: ='Actuals FS'!F13 -> 16138 | G37: ='Actuals FS'!E13 -> 13393 | H37: ='Forecasted FS'!E63 -> 22423 | I37: ='Forecasted FS'!F63 -> 22423 | J37: ='Forecasted FS'!G63 -> 22423 | K37: ='Forecasted FS'!H63 -> 22423 | L37: ='Forecasted FS'!I63 -> 22423 | M37: ='Forecasted FS'!J63 -> 22423
C38: Inventories | D38: ='Actuals FS'!H14 -> 23795 | E38: ='Actuals FS'!G14 -> 32640 | F38: ='Actuals FS'!F14 -> 34405 | G38: ='Actuals FS'!E14 -> 33318 | H38: ='Forecasted FS'!E64 -> 34214 | I38: ='Forecasted FS'!F64 -> 36322.234 | J38: ='Forecasted FS'!G64 -> 39007.07 | K38: ='Forecasted FS'!H64 -> 41886.256 | L38: ='Forecasted FS'!I64 -> 45386.062 | M38: ='Forecasted FS'!J64 -> 49173.276
C39: Accounts receivable, net and other | D39: ='Actuals FS'!H15 -> 24542 | E39: ='Actuals FS'!G15 -> 32891 | F39: ='Actuals FS'!F15 -> 42360 | G39: ='Actuals FS'!E15 -> 52253 | H39: ='Forecasted FS'!E65 -> 55451 | I39: ='Forecasted FS'!F65 -> 55451 | J39: ='Forecasted FS'!G65 -> 55451 | K39: ='Forecasted FS'!H65 -> 55451 | L39: ='Forecasted FS'!I65 -> 55451 | M39: ='Forecasted FS'!J65 -> 55451
C40: Total current assets | D40: ='Actuals FS'!H16 -> 132733 | E40: ='Actuals FS'!G16 -> 161580 | F40: ='Actuals FS'!F16 -> 146791 | G40: ='Actuals FS'!E16 -> 172351 | H40: ='Forecasted FS'!E66 -> 190867 | I40: ='Forecasted FS'!F66 -> 266806.43 | J40: ='Forecasted FS'!G66 -> 365351.33 | K40: ='Forecasted FS'!H66 -> 477385.76 | L40: ='Forecasted FS'!I66 -> 608718.32 | M40: ='Forecasted FS'!J66 -> 756467.12
C41: Non-current assets:
C42: Property and equipment, net | D42: ='Actuals FS'!H17 -> 113114 | E42: ='Actuals FS'!G17 -> 160281 | F42: ='Actuals FS'!F17 -> 186715 | G42: ='Actuals FS'!E17 -> 204177 | H42: ='Forecasted FS'!E68 -> 252665 | I42: ='Forecasted FS'!F68 -> 283529.94 | J42: ='Forecasted FS'!G68 -> 314394.89 | K42: ='Forecasted FS'!H68 -> 347973.18 | L42: ='Forecasted FS'!I68 -> 384854.48 | M42: ='Forecasted FS'!J68 -> 426729.09
C43: Operating leases | D43: ='Actuals FS'!H18 -> 37553 | E43: ='Actuals FS'!G18 -> 56082 | F43: ='Actuals FS'!F18 -> 66123 | G43: ='Actuals FS'!E18 -> 72513 | H43: ='Forecasted FS'!E69 -> 76141 | I43: ='Forecasted FS'!F69 -> 81470.87 | J43: ='Forecasted FS'!G69 -> 88803.248 | K43: ='Forecasted FS'!H69 -> 96795.541 | L43: ='Forecasted FS'!I69 -> 106475.09 | M43: ='Forecasted FS'!J69 -> 117122.6
C44: Goodwill | D44: ='Actuals FS'!H19 -> 15017 | E44: ='Actuals FS'!G19 -> 15371 | F44: ='Actuals FS'!F19 -> 20288 | G44: ='Actuals FS'!E19 -> 22789 | H44: ='Forecasted FS'!E70 -> 23074 | I44: ='Forecasted FS'!F70 -> 23074 | J44: ='Forecasted FS'!G70 -> 23074 | K44: ='Forecasted FS'!H70 -> 23074 | L44: ='Forecasted FS'!I70 -> 23074 | M44: ='Forecasted FS'!J70 -> 23074
C45: Other assets | D45: ='Actuals FS'!H20 -> 22778 | E45: ='Actuals FS'!G20 -> 27235 | F45: ='Actuals FS'!F20 -> 42758 | G45: ='Actuals FS'!E20 -> 56024 | H45: ='Forecasted FS'!E71 -> 82147 | I45: ='Forecasted FS'!F71 -> 82147 | J45: ='Forecasted FS'!G71 -> 82147 | K45: ='Forecasted FS'!H71 -> 82147 | L45: ='Forecasted FS'!I71 -> 82147 | M45: ='Forecasted FS'!J71 -> 82147
C46: Total non-current assets | D46: =SUM(D42:D45) -> 188462 | E46: =SUM(E42:E45) -> 258969 | F46: =SUM(F42:F45) -> 315884 | G46: =SUM(G42:G45) -> 355503 | H46: ='Forecasted FS'!E72 -> 434027 | I46: ='Forecasted FS'!F72 -> 470221.81 | J46: ='Forecasted FS'!G72 -> 508419.14 | K46: ='Forecasted FS'!H72 -> 549989.72 | L46: ='Forecasted FS'!I72 -> 596550.58 | M46: ='Forecasted FS'!J72 -> 649072.69
C47: Total assets | D47: ='Actuals FS'!H21 -> 321195 | E47: ='Actuals FS'!G21 -> 420549 | F47: ='Actuals FS'!F21 -> 462675 | G47: ='Actuals FS'!E21 -> 527854 | H47: ='Forecasted FS'!E73 -> 624894 | I47: ='Forecasted FS'!F73 -> 737028.24 | J47: ='Forecasted FS'!G73 -> 873770.46 | K47: ='Forecasted FS'!H73 -> 1027375.5 | L47: ='Forecasted FS'!I73 -> 1205268.9 | M47: ='Forecasted FS'!J73 -> 1405539.8
C48: Current liabilities:
C49: Accounts payable | D49: ='Actuals FS'!H24 -> 72539 | E49: ='Actuals FS'!G24 -> 78664 | F49: ='Actuals FS'!F24 -> 79600 | G49: ='Actuals FS'!E24 -> 84981 | H49: ='Forecasted FS'!E75 -> 94363 | I49: ='Forecasted FS'!F75 -> 100177.56 | J49: ='Forecasted FS'!G75 -> 107582.4 | K49: ='Forecasted FS'!H75 -> 115523.26 | L49: ='Forecasted FS'!I75 -> 125175.8 | M49: ='Forecasted FS'!J75 -> 135621.03
C50: Accrued expenses and other | D50: ='Actuals FS'!H25 -> 44138 | E50: ='Actuals FS'!G25 -> 51775 | F50: ='Actuals FS'!F25 -> 62566 | G50: ='Actuals FS'!E25 -> 64709 | H50: ='Forecasted FS'!E76 -> 66965 | I50: ='Forecasted FS'!F76 -> 71652.55 | J50: ='Forecasted FS'!G76 -> 78101.28 | K50: ='Forecasted FS'!H76 -> 85130.395 | L50: ='Forecasted FS'!I76 -> 93643.434 | M50: ='Forecasted FS'!J76 -> 103007.78
C51: Unearned revenue | D51: ='Actuals FS'!H26 -> 9708 | E51: ='Actuals FS'!G26 -> 11827 | F51: ='Actuals FS'!F26 -> 13227 | G51: ='Actuals FS'!E26 -> 15227 | H51: ='Forecasted FS'!E77 -> 18103 | I51: ='Forecasted FS'!F77 -> 19370.21 | J51: ='Forecasted FS'!G77 -> 21113.529 | K51: ='Forecasted FS'!H77 -> 23013.747 | L51: ='Forecasted FS'!I77 -> 25315.121 | M51: ='Forecasted FS'!J77 -> 27846.633
C52: Total current liabilities | D52: ='Actuals FS'!H27 -> 126385 | E52: ='Actuals FS'!G27 -> 142266 | F52: ='Actuals FS'!F27 -> 155393 | G52: ='Actuals FS'!E27 -> 164917 | H52: ='Forecasted FS'!E78 -> 179431 | I52: ='Forecasted FS'!F78 -> 191200.32 | J52: ='Forecasted FS'!G78 -> 206797.21 | K52: ='Forecasted FS'!H78 -> 223667.4 | L52: ='Forecasted FS'!I78 -> 244134.36 | M52: ='Forecasted FS'!J78 -> 266475.44
C53: Non-current liabilities:
C54: Long-term lease liabilities | D54: ='Actuals FS'!H28 -> 52573 | E54: ='Actuals FS'!G28 -> 67651 | F54: ='Actuals FS'!F28 -> 72968 | G54: ='Actuals FS'!E28 -> 77297 | H54: ='Forecasted FS'!E80 -> 78277 | I54: ='Forecasted FS'!F80 -> 83756.39 | J54: ='Forecasted FS'!G80 -> 91294.465 | K54: ='Forecasted FS'!H80 -> 99510.967 | L54: ='Forecasted FS'!I80 -> 109462.06 | M54: ='Forecasted FS'!J80 -> 120408.27
C55: Long-term debt | D55: ='Actuals FS'!H29 -> 31816 | E55: ='Actuals FS'!G29 -> 48744 | F55: ='Actuals FS'!F29 -> 67150 | G55: ='Actuals FS'!E29 -> 58314 | H55: ='Forecasted FS'!E81 -> 52623 | I55: ='Forecasted FS'!F81 -> 57214 | J55: ='Forecasted FS'!G81 -> 61805 | K55: ='Forecasted FS'!H81 -> 64100.5 | L55: ='Forecasted FS'!I81 -> 65248.25 | M55: ='Forecasted FS'!J81 -> 65822.125
C56: Other long-term liabilities | D56: ='Actuals FS'!H30 -> 17017 | E56: ='Actuals FS'!G30 -> 23643 | F56: ='Actuals FS'!F30 -> 21121 | G56: ='Actuals FS'!E30 -> 25451 | H56: ='Forecasted FS'!E82 -> 28593 | I56: ='Forecasted FS'!F82 -> 30594.51 | J56: ='Forecasted FS'!G82 -> 33348.016 | K56: ='Forecasted FS'!H82 -> 36349.337 | L56: ='Forecasted FS'!I82 -> 39984.271 | M56: ='Forecasted FS'!J82 -> 43982.698
C57: Commitments and contingencies (Note 7) | D57: ='Actuals FS'!H31 -> 0 | E57: ='Actuals FS'!G31 -> 0 | F57: ='Actuals FS'!F31 -> 0 | G57: ='Actuals FS'!E31 -> 0 | H57: ='Forecasted FS'!E83 -> 0 | I57: ='Forecasted FS'!F83 -> 0 | J57: ='Forecasted FS'!G83 -> 0 | K57: ='Forecasted FS'!H83 -> 0 | L57: ='Forecasted FS'!I83 -> 0 | M57: ='Forecasted FS'!J83 -> 0
C58: Total non-current liabilities | D58: =SUM(D54:D57) -> 101406 | E58: =SUM(E54:E57) -> 140038 | F58: =SUM(F54:F57) -> 161239 | G58: =SUM(G54:G57) -> 161062 | H58: ='Forecasted FS'!E84 -> 159493 | I58: ='Forecasted FS'!F84 -> 171564.9 | J58: ='Forecasted FS'!G84 -> 186447.48 | K58: ='Forecasted FS'!H84 -> 199960.8 | L58: ='Forecasted FS'!I84 -> 214694.58 | M58: ='Forecasted FS'!J84 -> 230213.09
C59: Total liabilities | D59: ='Actuals FS'!H32 -> 227791 | E59: ='Actuals FS'!G32 -> 282304 | F59: ='Actuals FS'!F32 -> 316632 | G59: ='Actuals FS'!E32 -> 325979 | H59: ='Forecasted FS'!E85 -> 338924 | I59: ='Forecasted FS'!F85 -> 362765.22 | J59: ='Forecasted FS'!G85 -> 393244.69 | K59: ='Forecasted FS'!H85 -> 423628.2 | L59: ='Forecasted FS'!I85 -> 458828.94 | M59: ='Forecasted FS'!J85 -> 496688.53
C60: Shareholder's Equity:
C61: Preferred stock ($0.01 par value; 500 shares authorized) | D61: ='Actuals FS'!H35 -> 0 | E61: ='Actuals FS'!G35 -> 0 | F61: ='Actuals FS'!F35 -> 0 | G61: ='Actuals FS'!E35 -> 0 | H61: ='Forecasted FS'!E87 -> 0 | I61: ='Forecasted FS'!F87 -> 0 | J61: ='Forecasted FS'!G87 -> 0 | K61: ='Forecasted FS'!H87 -> 0 | L61: ='Forecasted FS'!I87 -> 0 | M61: ='Forecasted FS'!J87 -> 0
C62: Common stock ($0.01 par value; 100,000 shares authorized) | D62: ='Actuals FS'!H36 -> 5 | E62: ='Actuals FS'!G36 -> 106 | F62: ='Actuals FS'!F36 -> 108 | G62: ='Actuals FS'!E36 -> 109 | H62: ='Forecasted FS'!E88 -> 111 | I62: ='Forecasted FS'!F88 -> 113.22 | J62: ='Forecasted FS'!G88 -> 115.4844 | K62: ='Forecasted FS'!H88 -> 117.79409 | L62: ='Forecasted FS'!I88 -> 120.14997 | M62: ='Forecasted FS'!J88 -> 122.55297
C63: Treasury stock, at cost | D63: ='Actuals FS'!H37 -> -1837 | E63: ='Actuals FS'!G37 -> -1837 | F63: ='Actuals FS'!F37 -> -7837 | G63: ='Actuals FS'!E37 -> -7837 | H63: ='Forecasted FS'!E89 -> -7837 | I63: ='Forecasted FS'!F89 -> -7837 | J63: ='Forecasted FS'!G89 -> -7837 | K63: ='Forecasted FS'!H89 -> -7837 | L63: ='Forecasted FS'!I89 -> -7837 | M63: ='Forecasted FS'!J89 -> -7837
C64: Additional paid-in capital | D64: ='Actuals FS'!H38 -> 42865 | E64: ='Actuals FS'!G38 -> 55437 | F64: ='Actuals FS'!F38 -> 75066 | G64: ='Actuals FS'!E38 -> 99025 | H64: ='Forecasted FS'!E90 -> 120864 | I64: ='Forecasted FS'!F90 -> 209154.81 | J64: ='Forecasted FS'!G90 -> 315415.29 | K64: ='Forecasted FS'!H90 -> 438634.48 | L64: ='Forecasted FS'!I90 -> 581324.8 | M64: ='Forecasted FS'!J90 -> 743733.73
C65: Accumulated other comprehensive income (loss) | D65: ='Actuals FS'!H39 -> -180 | E65: ='Actuals FS'!G39 -> -1376 | F65: ='Actuals FS'!F39 -> -4487 | G65: ='Actuals FS'!E39 -> -3040 | H65: ='Forecasted FS'!E91 -> -34 | I65: ='Forecasted FS'!F91 -> -34 | J65: ='Forecasted FS'!G91 -> -34 | K65: ='Forecasted FS'!H91 -> -34 | L65: ='Forecasted FS'!I91 -> -34 | M65: ='Forecasted FS'!J91 -> -34
C66: Retained earnings | D66: ='Actuals FS'!H40 -> 52551 | E66: ='Actuals FS'!G40 -> 85915 | F66: ='Actuals FS'!F40 -> 83193 | G66: ='Actuals FS'!E40 -> 113618 | H66: ='Forecasted FS'!E92 -> 172866 | I66: ='Forecasted FS'!F92 -> 172866 | J66: ='Forecasted FS'!G92 -> 172866 | K66: ='Forecasted FS'!H92 -> 172866 | L66: ='Forecasted FS'!I92 -> 172866 | M66: ='Forecasted FS'!J92 -> 172866
C67: Total shareholders' equity | D67: ='Actuals FS'!H41 -> 93404 | E67: ='Actuals FS'!G41 -> 138245 | F67: ='Actuals FS'!F41 -> 146043 | G67: ='Actuals FS'!E41 -> 201875 | H67: ='Forecasted FS'!E93 -> 285970 | I67: ='Forecasted FS'!F93 -> 374263.03 | J67: ='Forecasted FS'!G93 -> 480525.78 | K67: ='Forecasted FS'!H93 -> 603747.28 | L67: ='Forecasted FS'!I93 -> 746439.95 | M67: ='Forecasted FS'!J93 -> 908851.28
C68: Total liabilities and shareholders' equity | D68: ='Actuals FS'!H42 -> 321195 | E68: ='Actuals FS'!G42 -> 420549 | F68: ='Actuals FS'!F42 -> 462675 | G68: ='Actuals FS'!E42 -> 527854 | H68: ='Forecasted FS'!E94 -> 624894 | I68: ='Forecasted FS'!F94 -> 737028.24 | J68: ='Forecasted FS'!G94 -> 873770.46 | K68: ='Forecasted FS'!H94 -> 1027375.5 | L68: ='Forecasted FS'!I94 -> 1205268.9 | M68: ='Forecasted FS'!J94 -> 1405539.8
C70: 3. Statement of Cash Flows, for the year ended | D70: =D34 -> 2020 A | E70: =E34 -> 2021 A | F70: =F34 -> 2022 A | G70: =G34 -> 2023 A | H70: =H34 -> 2024 A | I70: =I34 -> 2025 F | J70: =J34 -> 2026 F | K70: =K34 -> 2027 F | ... M70: =M34 -> 2029 F
C71: CASH, CASH EQUIVALENTS, AND RESTRICTED CASH, BEGINNING OF PERIOD | D71: ='Actuals FS'!H71 -> 36410 | E71: ='Actuals FS'!G71 -> 42377 | F71: ='Actuals FS'!F71 -> 36477 | G71: ='Actuals FS'!E71 -> 54253 | H71: ='Forecasted FS'!E98 -> 73890 | I71: ='Forecasted FS'!F98 -> 82312 | J71: ='Forecasted FS'!G98 -> 138129.18 | K71: ='Forecasted FS'!H98 -> 196687.75 | L71: ='Forecasted FS'!I98 -> 268056.14 | M71: ='Forecasted FS'!J98 -> 351675.93
C72: OPERATING ACTIVITIES:
C73: Net income (loss) | D73: ='Actuals FS'!H73 -> 21331 | E73: ='Actuals FS'!G73 -> 33364 | F73: ='Actuals FS'!F73 -> -2722 | G73: ='Actuals FS'!E73 -> 30425 | H73: ='Forecasted FS'!E100 -> 59248 | I73: ='Forecasted FS'!F100 -> 66748.877 | J73: ='Forecasted FS'!G100 -> 84364.915 | K73: ='Forecasted FS'!H100 -> 100964.18 | L73: ='Forecasted FS'!I100 -> 120069.95 | M73: ='Forecasted FS'!J100 -> 139417.22
C74: Adjustments to reconcile net income (loss) to net cash from operating activities:
C75: Depreciation and amortization of property and equipment and capitalized content costs, operating lease assets, and other | D75: ='Actuals FS'!H75 -> 25180 | E75: ='Actuals FS'!G75 -> 34433 | F75: ='Actuals FS'!F75 -> 41921 | G75: ='Actuals FS'!E75 -> 48663 | H75: ='Forecasted FS'!E102 -> 52795 | I75: ='Forecasted FS'!F102 -> 56878.279 | J75: ='Forecasted FS'!G102 -> 60914.14 | K75: ='Forecasted FS'!H102 -> 64879.488 | L75: ='Forecasted FS'!I102 -> 68719.018 | M75: ='Forecasted FS'!J102 -> 72416.063
C76: Stock-based compensation | D76: ='Actuals FS'!H76 -> 9208 | E76: ='Actuals FS'!G76 -> 12757 | F76: ='Actuals FS'!F76 -> 19621 | G76: ='Actuals FS'!E76 -> 24023 | H76: ='Forecasted FS'!E103 -> 22011 | I76: ='Forecasted FS'!F103 -> 22720.746 | J76: ='Forecasted FS'!G103 -> 23392.885 | K76: ='Forecasted FS'!H103 -> 24027.769 | L76: ='Forecasted FS'!I103 -> 24620.6 | M76: ='Forecasted FS'!J103 -> 25172.834
C77: Non-operating expense (income), net | D77: ='Actuals FS'!H77 -> -2582 | E77: ='Actuals FS'!G77 -> -14306 | F77: ='Actuals FS'!F77 -> 16966 | G77: ='Actuals FS'!E77 -> -748 | H77: ='Forecasted FS'!E104 -> 2012 | I77: ='Forecasted FS'!F104 -> 0 | J77: ='Forecasted FS'!G104 -> 0 | K77: ='Forecasted FS'!H104 -> 0 | L77: ='Forecasted FS'!I104 -> 0 | M77: ='Forecasted FS'!J104 -> 0
C78: Deferred income taxes | D78: ='Actuals FS'!H78 -> -554 | E78: ='Actuals FS'!G78 -> -310 | F78: ='Actuals FS'!F78 -> -8148 | G78: ='Actuals FS'!E78 -> -5876 | H78: ='Forecasted FS'!E105 -> -4648 | I78: ='Forecasted FS'!F105 -> -8886.0499 | J78: ='Forecasted FS'!G105 -> -11228.715 | K78: ='Forecasted FS'!H105 -> -13436.355 | L78: ='Forecasted FS'!I105 -> -15977.437 | M78: ='Forecasted FS'!J105 -> -18550.786
C79: Changes in operating assets and liabilities:
C80: Inventories | D80: ='Actuals FS'!H80 -> -2849 | E80: ='Actuals FS'!G80 -> -9487 | F80: ='Actuals FS'!F80 -> -2592 | G80: ='Actuals FS'!E80 -> 1449 | H80: ='Forecasted FS'!E107 -> -1884 | I80: ='Forecasted FS'!F107 -> -2108.234 | J80: ='Forecasted FS'!G107 -> -2684.8363 | K80: ='Forecasted FS'!H107 -> -2879.1852 | L80: ='Forecasted FS'!I107 -> -3499.8061 | M80: ='Forecasted FS'!J107 -> -3787.2147
C81: Accounts receivable, net and other | D81: ='Actuals FS'!H81 -> -8169 | E81: ='Actuals FS'!G81 -> -18163 | F81: ='Actuals FS'!F81 -> -8622 | G81: ='Actuals FS'!E81 -> -8348 | H81: ='Forecasted FS'!E108 -> -3249 | I81: ='Forecasted FS'!F108 -> 0 | J81: ='Forecasted FS'!G108 -> 0 | K81: ='Forecasted FS'!H108 -> 0 | L81: ='Forecasted FS'!I108 -> 0 | M81: ='Forecasted FS'!J108 -> 0
C82: Other assets | D82: ='Actuals FS'!H82 -> 0 | E82: ='Actuals FS'!G82 -> 0 | F82: ='Actuals FS'!F82 -> -13275 | G82: ='Actuals FS'!E82 -> -12265 | H82: ='Forecasted FS'!E109 -> -14483 | I82: ='Forecasted FS'!F109 -> 0 | J82: ='Forecasted FS'!G109 -> 0 | K82: ='Forecasted FS'!H109 -> 0 | L82: ='Forecasted FS'!I109 -> 0 | M82: ='Forecasted FS'!J109 -> 0
C83: Accounts payable | D83: ='Actuals FS'!H83 -> 17480 | E83: ='Actuals FS'!G83 -> 3602 | F83: ='Actuals FS'!F83 -> 2945 | G83: ='Actuals FS'!E83 -> 5473 | H83: ='Forecasted FS'!E110 -> 2972 | I83: ='Forecasted FS'!F110 -> 5814.558 | J83: ='Forecasted FS'!G110 -> 7404.8403 | K83: ='Forecasted FS'!H110 -> 7940.8592 | L83: ='Forecasted FS'!I110 -> 9652.5458 | M83: ='Forecasted FS'!J110 -> 10445.225
C84: Accrued expenses and other | D84: ='Actuals FS'!H84 -> 5754 | E84: ='Actuals FS'!G84 -> 2123 | F84: ='Actuals FS'!F84 -> -1558 | G84: ='Actuals FS'!E84 -> -2428 | H84: ='Forecasted FS'!E111 -> -2904 | I84: ='Forecasted FS'!F111 -> 4687.55 | J84: ='Forecasted FS'!G111 -> -6448.7295 | K84: ='Forecasted FS'!H111 -> -7029.1152 | L84: ='Forecasted FS'!I111 -> -8513.0395 | M84: ='Forecasted FS'!J111 -> -9364.3434
C85: Unearned revenue | D85: ='Actuals FS'!H85 -> 1265 | E85: ='Actuals FS'!G85 -> 2314 | F85: ='Actuals FS'!F85 -> 2216 | G85: ='Actuals FS'!E85 -> 4578 | H85: ='Forecasted FS'!E112 -> 4007 | I85: ='Forecasted FS'!F112 -> 1267.21 | J85: ='Forecasted FS'!G112 -> -1743.3189 | K85: ='Forecasted FS'!H112 -> -1900.2176 | L85: ='Forecasted FS'!I112 -> -2301.3747 | M85: ='Forecasted FS'!J112 -> -2531.5121
C86: Net cash provided by (used in) operating activities | D86: ='Actuals FS'!H86 -> 66064 | E86: ='Actuals FS'!G86 -> 46327 | F86: ='Actuals FS'!F86 -> 46752 | G86: ='Actuals FS'!E86 -> 84946 | H86: ='Forecasted FS'!E113 -> 115877 | I86: ='Forecasted FS'!F113 -> 147122.94 | J86: ='Forecasted FS'!G113 -> 153971.18 | K86: ='Forecasted FS'!H113 -> 172567.42 | L86: ='Forecasted FS'!I113 -> 192770.46 | M86: ='Forecasted FS'!J113 -> 213217.48
C87: Purchases of property and equipment | D87: ='Actuals FS'!H87 -> -40140 | E87: ='Actuals FS'!G87 -> -61053 | F87: ='Actuals FS'!F87 -> -63645 | G87: ='Actuals FS'!E87 -> -52729 | H87: ='Forecasted FS'!E114 -> -82999 | I87: ='Forecasted FS'!F114 -> -87743.223 | J87: ='Forecasted FS'!G114 -> -94492.432 | K87: ='Forecasted FS'!H114 -> -101760.79 | L87: ='Forecasted FS'!I114 -> -110593.63 | M87: ='Forecasted FS'!J114 -> -120193.15
C88: Proceeds from property and equipment sales and incentives | D88: ='Actuals FS'!H88 -> 5096 | E88: ='Actuals FS'!G88 -> 5657 | F88: ='Actuals FS'!F88 -> 5324 | G88: ='Actuals FS'!E88 -> 4596 | H88: ='Forecasted FS'!E115 -> 5341 | I88: ='Forecasted FS'!F115 -> 5754.0844 | J88: ='Forecasted FS'!G115 -> 6162.3718 | K88: ='Forecasted FS'!H115 -> 6563.5259 | L88: ='Forecasted FS'!I115 -> 6951.9514 | M88: ='Forecasted FS'!J115 -> 7325.9626
C89: Acquisitions, net of cash acquired, non-marketable investments, and other | D89: ='Actuals FS'!H89 -> -2325 | E89: ='Actuals FS'!G89 -> -1985 | F89: ='Actuals FS'!F89 -> -8316 | G89: ='Actuals FS'!E89 -> -5839 | H89: ='Forecasted FS'!E116 -> -7082 | I89: ='Forecasted FS'!F116 -> -2000 | J89: ='Forecasted FS'!G116 -> -2000 | K89: ='Forecasted FS'!H116 -> -2000 | L89: ='Forecasted FS'!I116 -> -2000 | M89: ='Forecasted FS'!J116 -> -2000
C90: Sales and maturities of marketable securities | D90: ='Actuals FS'!H90 -> 50237 | E90: ='Actuals FS'!G90 -> 59384 | F90: ='Actuals FS'!F90 -> 31601 | G90: ='Actuals FS'!E90 -> 5627 | H90: ='Forecasted FS'!E117 -> 16403 | I90: ='Forecasted FS'!F117 -> 0 | J90: ='Forecasted FS'!G117 -> 0 | K90: ='Forecasted FS'!H117 -> 0 | L90: ='Forecasted FS'!I117 -> 0 | M90: ='Forecasted FS'!J117 -> 0
C91: Purchases of marketable securities | D91: ='Actuals FS'!H91 -> -72479 | E91: ='Actuals FS'!G91 -> -60157 | F91: ='Actuals FS'!F91 -> -2565 | G91: ='Actuals FS'!E91 -> -1488 | H91: ='Forecasted FS'!E118 -> -26005 | I91: ='Forecasted FS'!F118 -> 0 | J91: ='Forecasted FS'!G118 -> 0 | K91: ='Forecasted FS'!H118 -> 0 | L91: ='Forecasted FS'!I118 -> 0 | M91: ='Forecasted FS'!J118 -> 0
... C103: CASH, CASH EQUIVALENTS, AND RESTRICTED CASH, END OF PERIOD | D103: ='Actuals FS'!H103 -> 42377 | E103: ='Actuals FS'!G103 -> 36477 | F103: ='Actuals FS'!F103 -> 54253 | G103: ='Actuals FS'!E103 -> 73890 | H103: ='Forecasted FS'!E130 -> 82312 | I103: ='Forecasted FS'!F130 -> 138129.18 | J103: ='Forecasted FS'!G130 -> 196687.75 | K103: ='Forecasted FS'!H130 -> 268056.14 | L103: ='Forecasted FS'!I130 -> 351675.93 | M103: ='Forecasted FS'!J130 -> 446714.96
D105: =D70 -> 2020 A | E105: =E70 -> 2021 A | F105: =F70 -> 2022 A | G105: =G70 -> 2023 A | H105: =H70 -> 2024 A | I105: =I70 -> 2025 F | J105: =J70 -> 2026 F | K105: =K70 -> 2027 F | ... M105: =M70 -> 2029 F
C106: Liquidity (Safety)
C107: Current ratio (x) | D107: ='Actuals FS'!H110 -> 1.0502275 | E107: ='Actuals FS'!G110 -> 1.1357598 | F107: ='Actuals FS'!F110 -> 0.94464358 | G107: ='Actuals FS'!E110 -> 1.0450772 | H107: ='Forecasted FS'!E137 -> 1.0637348 | I107: ='Forecasted FS'!F137 -> 1.3954288 | J107: ='Forecasted FS'!G137 -> 1.7667131 | K107: ='Forecasted FS'!H137 -> 2.1343556 | L107: ='Forecasted FS'!I137 -> 2.4933742 | M107: ='Forecasted FS'!J137 -> 2.8387874
C108: Quick ratio (x) | D108: ='Actuals FS'!H111 -> 0.86195355 | E108: ='Actuals FS'!G111 -> 0.9063304 | F108: ='Actuals FS'!F111 -> 0.72323721 | G108: ='Actuals FS'!E111 -> 0.84304832 | H108: ='Forecasted FS'!E138 -> 0.87305427 | I108: ='Forecasted FS'!F138 -> 1.2054593 | J108: ='Forecasted FS'!G138 -> 1.5780883 | K108: ='Forecasted FS'!H138 -> 1.9470853 | L108: ='Forecasted FS'!I138 -> 2.3074682 | M108: ='Forecasted FS'!J138 -> 2.6542553
C109: Accounts Receivable Turnover (x) | D109: ='Actuals FS'!H112 -> 15.730747 | E109: ='Actuals FS'!G112 -> 14.284211 | F109: ='Actuals FS'!F112 -> 12.133687 | G109: ='Actuals FS'!E112 -> 11.000038 | H109: ='Forecasted FS'!E139 -> 11.504914 | I109: ='Forecasted FS'!F139 -> 12.310258 | J109: ='Forecasted FS'!G139 -> 13.418181 | K109: ='Forecasted FS'!H139 -> 14.625818 | L109: ='Forecasted FS'!I139 -> 16.0884 | M109: ='Forecasted FS'!J139 -> 17.69724
C110: Days in Receivable | D110: ='Actuals FS'!H113 -> 23.202966 | E110: ='Actuals FS'!G113 -> 25.552688 | F110: ='Actuals FS'!F113 -> 30.08154 | G110: ='Actuals FS'!E113 -> 33.181703 | H110: ='Forecasted FS'!E140 -> 31.725573 | I110: ='Forecasted FS'!F140 -> 29.650068 | J110: ='Forecasted FS'!G140 -> 27.201898 | K110: ='Forecasted FS'!H140 -> 24.955869 | L110: ='Forecasted FS'!I140 -> 22.687154 | M110: ='Forecasted FS'!J140 -> 20.624685
C111: Productivity (Efficiency)
C112: Inventory Turnover (x) | D112: ='Actuals FS'!H115 -> 9.804875 | E112: ='Actuals FS'!G115 -> 8.3438725 | F112: ='Actuals FS'!F115 -> 8.3950298 | G112: ='Actuals FS'!E115 -> 9.1463773 | H112: ='Forecasted FS'!E142 -> 9.5366809 | I112: ='Forecasted FS'!F142 -> 9.5846039 | J112: ='Forecasted FS'!G142 -> 9.6327677 | K112: ='Forecasted FS'!H142 -> 9.6811736 | L112: ='Forecasted FS'!I142 -> 9.7298227 | M112: ='Forecasted FS'!J142 -> 9.7787163
C113: Days in Inventory | D113: ='Actuals FS'!H116 -> 37.22638 | E113: ='Actuals FS'!G116 -> 43.744676 | F113: ='Actuals FS'!F116 -> 43.478107 | G113: ='Actuals FS'!E116 -> 39.90651 | H113: ='Forecasted FS'!E143 -> 38.273274 | I113: ='Forecasted FS'!F143 -> 38.081908 | J113: ='Forecasted FS'!G143 -> 37.891498 | K113: ='Forecasted FS'!H143 -> 37.702041 | L113: ='Forecasted FS'!I143 -> 37.51353 | M113: ='Forecasted FS'!J143 -> 37.325963
C114: Total Asset Turnover (x) | D114: ='Actuals FS'!H117 -> 1.2019614 | E114: ='Actuals FS'!G117 -> 1.1171635 | F114: ='Actuals FS'!F117 -> 1.1108943 | G114: ='Actuals FS'!E117 -> 1.0889091 | H114: ='Forecasted FS'!E144 -> 1.0209075 | I114: ='Forecasted FS'!F144 -> 1.0024304 | J114: ='Forecasted FS'!G144 -> 0.92382937 | K114: ='Forecasted FS'!H144 -> 0.85318671 | L114: ='Forecasted FS'!I144 -> 0.79915803 | M114: ='Forecasted FS'!J144 -> 0.7517438
C115: Total Fixed Asset Turnover (x) | D115: ='Actuals FS'!H118 -> 3.4130523 | E115: ='Actuals FS'!G118 -> 2.9312395 | F115: ='Actuals FS'!F118 -> 2.7527676 | G115: ='Actuals FS'!E118 -> 2.815131 | H115: ='Forecasted FS'!E145 -> 2.5249203 | I115: ='Forecasted FS'!F145 -> 2.5461491 | J115: ='Forecasted FS'!G145 -> 2.4887797 | K115: ='Forecasted FS'!H145 -> 2.4488385 | L115: ='Forecasted FS'!I145 -> 2.4347275 | M115: ='Forecasted FS'!J145 -> 2.4183083
C116: Days in Payables | D116: ='Actuals FS'!H119 -> 113.48453 | E116: ='Actuals FS'!G119 -> 105.42681 | F116: ='Actuals FS'!F119 -> 100.5917 | G116: ='Actuals FS'!E119 -> 101.78568 | H116: ='Forecasted FS'!E146 -> 105.55857 | I116: ='Forecasted FS'!F146 -> 105.03078 | J116: ='Forecasted FS'!G146 -> 104.50562 | K116: ='Forecasted FS'!H146 -> 103.9831 | L116: ='Forecasted FS'!I146 -> 103.46318 | M116: ='Forecasted FS'!J146 -> 102.94586
C117: Cash Conversion Cycle | D117: ='Actuals FS'!H120 -> -53.055183 | E117: ='Actuals FS'!G120 -> -36.129449 | F117: ='Actuals FS'!F120 -> -27.032049 | G117: ='Actuals FS'!E120 -> -28.697463 | H117: ='Forecasted FS'!E147 -> -35.559724 | I117: ='Forecasted FS'!F147 -> -37.298802 | J117: ='Forecasted FS'!G147 -> -39.412229 | K117: ='Forecasted FS'!H147 -> -41.325186 | L117: ='Forecasted FS'!I147 -> -43.262496 | M117: ='Forecasted FS'!J147 -> -44.995217
C118: Profitability (Performance)
C119: Operating profit margin (%) | D119: ='Actuals FS'!H122 -> 0.059314 | E119: ='Actuals FS'!G122 -> 0.052954098 | F119: ='Actuals FS'!F122 -> 0.023829582 | G119: ='Actuals FS'!E122 -> 0.064114408 | H119: ='Forecasted FS'!E149 -> 0.10751945 | I119: ='Forecasted FS'!F149 -> 0.12336577 | J119: ='Forecasted FS'!G149 -> 0.14312706 | K119: ='Forecasted FS'!H149 -> 0.15719767 | L119: ='Forecasted FS'!I149 -> 0.17002787 | M119: ='Forecasted FS'!J149 -> 0.17953858
C120: Return on Asset (%) | D120: ='Actuals FS'!H123 -> 0.06641137 | E120: ='Actuals FS'!G123 -> 0.079334394 | F120: ='Actuals FS'!F123 -> -0.0058831793 | G120: ='Actuals FS'!E123 -> 0.057639044 | H120: ='Forecasted FS'!E150 -> 0.09481288 | I120: ='Forecasted FS'!F150 -> 0.098021568 | J120: ='Forecasted FS'!G150 -> 0.10474917 | K120: ='Forecasted FS'!H150 -> 0.10621402 | L120: ='Forecasted FS'!I150 -> 0.10755851 | M120: ='Forecasted FS'!J150 -> 0.10680002
...

Sheet Ratios
C3: Financial Ratios Analysis
C4: Figures in USD millions, unless told otherwise
D8: 2020 | E8: =D8+1 -> 2021 | F8: =E8+1 -> 2022 | G8: =F8+1 -> 2023 | H8: =G8+1 -> 2024 | I8: 2025 F | J8: 2026 F | K8: 2027 F | L8: 2028 F | M8: 2029 F | N8: TREND
B10: 1 | C10: Liquidity (Safety)
B11: a. | C11: Current ratio (x) | D11: ='Actuals FS'!H110 -> 1.0502275 | E11: ='Actuals FS'!G110 -> 1.1357598 | F11: ='Actuals FS'!F110 -> 0.94464358 | G11: ='Actuals FS'!E110 -> 1.0450772 | H11: ='Actuals FS'!D110 -> 1.0637348 | I11: ='Forecasted FS'!F137 -> 1.3954288 | J11: ='Forecasted FS'!G137 -> 1.7667131 | K11: ='Forecasted FS'!H137 -> 2.1343556 | L11: ='Forecasted FS'!I137 -> 2.4933742 | M11: ='Forecasted FS'!J137 -> 2.8387874
B12: b. | C12: Quick ratio (x) | D12: ='Actuals FS'!H111 -> 0.86195355 | E12: ='Actuals FS'!G111 -> 0.9063304 | F12: ='Actuals FS'!F111 -> 0.72323721 | G12: ='Actuals FS'!E111 -> 0.84304832 | H12: ='Actuals FS'!D111 -> 0.87305427 | I12: ='Forecasted FS'!F138 -> 1.2054593 | J12: ='Forecasted FS'!G138 -> 1.5780883 | K12: ='Forecasted FS'!H138 -> 1.9470853 | L12: ='Forecasted FS'!I138 -> 2.3074682 | M12: ='Forecasted FS'!J138 -> 2.6542553
B13: c. | C13: Accounts Receivable Turnover (x) | D13: ='Actuals FS'!H112 -> 15.730747 | E13: ='Actuals FS'!G112 -> 14.284211 | F13: ='Actuals FS'!F112 -> 12.133687 | G13: ='Actuals FS'!E112 -> 11.000038 | H13: ='Actuals FS'!D112 -> 11.504914 | I13: ='Forecasted FS'!F139 -> 12.310258 | J13: ='Forecasted FS'!G139 -> 13.418181 | K13: ='Forecasted FS'!H139 -> 14.625818 | L13: ='Forecasted FS'!I139 -> 16.0884 | M13: ='Forecasted FS'!J139 -> 17.69724
B14: d. | C14: Days in Receivable | D14: ='Actuals FS'!H113 -> 23.202966 | E14: ='Actuals FS'!G113 -> 25.552688 | F14: ='Actuals FS'!F113 -> 30.08154 | G14: ='Actuals FS'!E113 -> 33.181703 | H14: ='Actuals FS'!D113 -> 31.725573 | I14: ='Forecasted FS'!F140 -> 29.650068 | J14: ='Forecasted FS'!G140 -> 27.201898 | K14: ='Forecasted FS'!H140 -> 24.955869 | L14: ='Forecasted FS'!I140 -> 22.687154 | M14: ='Forecasted FS'!J140 -> 20.624685
B16: =B10+1 -> 2 | C16: Productivity (Efficiency)
B17: a. | C17: Inventory Turnover (x) | D17: ='Actuals FS'!H115 -> 9.804875 | E17: ='Actuals FS'!G115 -> 8.3438725 | F17: ='Actuals FS'!F115 -> 8.3950298 | G17: ='Actuals FS'!E115 -> 9.1463773 | H17: ='Actuals FS'!D115 -> 9.5366809 | I17: ='Forecasted FS'!F142 -> 9.5846039 | J17: ='Forecasted FS'!G142 -> 9.6327677 | K17: ='Forecasted FS'!H142 -> 9.6811736 | L17: ='Forecasted FS'!I142 -> 9.7298227 | M17: ='Forecasted FS'!J142 -> 9.7787163
B18: b. | C18: Days in Inventory | D18: ='Actuals FS'!H116 -> 37.22638 | E18: ='Actuals FS'!G116 -> 43.744676 | F18: ='Actuals FS'!F116 -> 43.478107 | G18: ='Actuals FS'!E116 -> 39.90651 | H18: ='Actuals FS'!D116 -> 38.273274 | I18: ='Forecasted FS'!F143 -> 38.081908 | J18: ='Forecasted FS'!G143 -> 37.891498 | K18: ='Forecasted FS'!H143 -> 37.702041 | L18: ='Forecasted FS'!I143 -> 37.51353 | M18: ='Forecasted FS'!J143 -> 37.325963
B19: c. | C19: Total Asset Turnover (x) | D19: ='Actuals FS'!H117 -> 1.2019614 | E19: ='Actuals FS'!G117 -> 1.1171635 | F19: ='Actuals FS'!F117 -> 1.1108943 | G19: ='Actuals FS'!E117 -> 1.0889091 | H19: ='Actuals FS'!D117 -> 1.0209075 | I19: ='Forecasted FS'!F144 -> 1.0024304 | J19: ='Forecasted FS'!G144 -> 0.92382937 | K19: ='Forecasted FS'!H144 -> 0.85318671 | L19: ='Forecasted FS'!I144 -> 0.79915803 | M19: ='Forecasted FS'!J144 -> 0.7517438
B20: d. | C20: Total Fixed Asset Turnover (x) | D20: ='Actuals FS'!H118 -> 3.4130523 | E20: ='Actuals FS'!G118 -> 2.9312395 | F20: ='Actuals FS'!F118 -> 2.7527676 | G20: ='Actuals FS'!E118 -> 2.815131 | H20: ='Actuals FS'!D118 -> 2.5249203 | I20: ='Forecasted FS'!F145 -> 2.5461491 | J20: ='Forecasted FS'!G145 -> 2.4887797 | K20: ='Forecasted FS'!H145 -> 2.4488385 | L20: ='Forecasted FS'!I145 -> 2.4347275 | M20: ='Forecasted FS'!J145 -> 2.4183083
B21: e. | C21: Days in Payables | D21: ='Actuals FS'!H119 -> 113.48453 | E21: ='Actuals FS'!G119 -> 105.42681 | F21: ='Actuals FS'!F119 -> 100.5917 | G21: ='Actuals FS'!E119 -> 101.78568 | H21: ='Actuals FS'!D119 -> 105.55857 | I21: ='Forecasted FS'!F146 -> 105.03078 | J21: ='Forecasted FS'!G146 -> 104.50562 | K21: ='Forecasted FS'!H146 -> 103.9831 | L21: ='Forecasted FS'!I146 -> 103.46318 | M21: ='Forecasted FS'!J146 -> 102.94586
B22: f. | C22: Cash Conversion Cycle | D22: ='Actuals FS'!H120 -> -53.055183 | E22: ='Actuals FS'!G120 -> -36.129449 | F22: ='Actuals FS'!F120 -> -27.032049 | G22: ='Actuals FS'!E120 -> -28.697463 | H22: ='Actuals FS'!D120 -> -35.559724 | I22: ='Forecasted FS'!F147 -> -37.298802 | J22: ='Forecasted FS'!G147 -> -39.412229 | K22: ='Forecasted FS'!H147 -> -41.325186 | L22: ='Forecasted FS'!I147 -> -43.262496 | M22: ='Forecasted FS'!J147 -> -44.995217
B24: =B16+1 -> 3 | C24: Profitability (Performance)
B25: a. | C25: Operating profit margin (%) | D25: ='Actuals FS'!H122 -> 0.059314 | E25: ='Actuals FS'!G122 -> 0.052954098 | F25: ='Actuals FS'!F122 -> 0.023829582 | G25: ='Actuals FS'!E122 -> 0.064114408 | H25: ='Forecasted FS'!E149 -> 0.10751945 | I25: ='Forecasted FS'!F149 -> 0.12336577 | J25: ='Forecasted FS'!G149 -> 0.14312706 | K25: ='Forecasted FS'!H149 -> 0.15719767 | L25: ='Forecasted FS'!I149 -> 0.17002787 | M25: ='Forecasted FS'!J149 -> 0.17953858
B26: b. | C26: Return on Asset (%) | D26: ='Actuals FS'!H123 -> 0.06641137 | E26: ='Actuals FS'!G123 -> 0.079334394 | F26: ='Actuals FS'!F123 -> -0.0058831793 | G26: ='Actuals FS'!E123 -> 0.057639044 | H26: ='Forecasted FS'!E150 -> 0.09481288 | I26: ='Forecasted FS'!F150 -> 0.098021568 | J26: ='Forecasted FS'!G150 -> 0.10474917 | K26: ='Forecasted FS'!H150 -> 0.10621402 | L26: ='Forecasted FS'!I150 -> 0.10755851 | M26: ='Forecasted FS'!J150 -> 0.10680002
B27: c. | C27: Return on Sales, net profit margin (%) | D27: ='Actuals FS'!H124 -> 0.055252497 | E27: ='Actuals FS'!G124 -> 0.071014129 | F27: ='Actuals FS'!F124 -> -0.005295895 | G27: ='Actuals FS'!E124 -> 0.052932836 | H27: ='Forecasted FS'!E151 -> 0.092871172 | I27: ='Forecasted FS'!F151 -> 0.097783913 | J27: ='Forecasted FS'!G151 -> 0.11338584 | K27: ='Forecasted FS'!H151 -> 0.12449094 | L27: ='Forecasted FS'!I151 -> 0.13458979 | M27: ='Forecasted FS'!J151 -> 0.14206971
B28: d. | C28: Return on Equity (%) | D28: ='Actuals FS'!H125 -> 0.22837352 | E28: ='Actuals FS'!G125 -> 0.24133965 | F28: ='Actuals FS'!F125 -> -0.018638346 | G28: ='Actuals FS'!E125 -> 0.15071207 | H28: ='Forecasted FS'!E152 -> 0.20718257 | I28: ='Forecasted FS'!F152 -> 0.20219793 | J28: ='Forecasted FS'!G152 -> 0.19739359 | K28: ='Forecasted FS'!H152 -> 0.18623385 | L28: ='Forecasted FS'!I152 -> 0.17785675 | M28: ='Forecasted FS'!J152 -> 0.16845038
B29: e. | C29: Return Over Invested Capital (%) | D29: ='Actuals FS'!H126 -> 0.10810323 | E29: ='Actuals FS'!G126 -> 0.088053842 | F29: ='Actuals FS'!F126 -> 0.03622841 | G29: ='Actuals FS'!E126 -> 0.087275703 | H29: ='Forecasted FS'!E153 -> 0.12983255 | I29: ='Forecasted FS'!F153 -> 0.17278183 | J29: ='Forecasted FS'!G153 -> 0.17278603 | K29: ='Forecasted FS'!H153 -> 0.1664498 | L29: ='Forecasted FS'!I153 -> 0.16198466 | M29: ='Forecasted FS'!J153 -> 0.15583335
B30: f. | C30: Sustainable Growth (%) | D30: ='Actuals FS'!H127 -> 0.22837352 | E30: ='Actuals FS'!G127 -> 0.24133965 | F30: ='Actuals FS'!F127 -> -0.018638346 | G30: ='Actuals FS'!E127 -> 0.15071207 | H30: ='Forecasted FS'!E154 -> 0.20718257 | I30: ='Forecasted FS'!F154 -> 0.20219793 | J30: ='Forecasted FS'!G154 -> 0.19739359 | K30: ='Forecasted FS'!H154 -> 0.18623385 | L30: ='Forecasted FS'!I154 -> 0.17785675 | M30: ='Forecasted FS'!J154 -> 0.16845038
B32: =B24+1 -> 4 | C32: Insolvency (Leverage)
B33: a. | C33: Debt Ratio (%) | D33: ='Actuals FS'!H129 -> 0.099055091 | E33: ='Actuals FS'!G129 -> 0.11590564 | F33: ='Actuals FS'!F129 -> 0.14513427 | G33: ='Actuals FS'!E129 -> 0.11047373 | H33: ='Forecasted FS'!E156 -> 0.084211082 | I33: ='Forecasted FS'!F156 -> 0.08064851 | J33: ='Forecasted FS'!G156 -> 0.073888189 | K33: ='Forecasted FS'!H156 -> 0.06622611 | L33: ='Forecasted FS'!I156 -> 0.057935223 | M33: ='Forecasted FS'!J156 -> 0.050202979
B34: b. | C34: Asset to Equity (Equity Multiplier) (x) | D34: ='Actuals FS'!H130 -> 3.4387714 | E34: ='Actuals FS'!G130 -> 3.0420558 | F34: ='Actuals FS'!F130 -> 3.1680738 | G34: ='Actuals FS'!E130 -> 2.6147567 | H34: ='Forecasted FS'!E157 -> 2.1851733 | I34: ='Forecasted FS'!F157 -> 1.9692788 | J34: ='Forecasted FS'!G157 -> 1.8183634 | K34: ='Forecasted FS'!H157 -> 1.7016648 | L34: ='Forecasted FS'!I157 -> 1.6146897 | M34: ='Forecasted FS'!J157 -> 1.5465014
B35: c. | C35: Current Liabilities to Total Debt Ratio (%) | D35: ='Actuals FS'!H131 -> 0.79888876 | E35: ='Actuals FS'!G131 -> 0.74480917 | F35: ='Actuals FS'!F131 -> 0.69826056 | G35: ='Actuals FS'!E131 -> 0.73877284 | H35: ='Forecasted FS'!E158 -> 0.77322951 | I35: ='Forecasted FS'!F158 -> 0.76968316 | J35: ='Forecasted FS'!G158 -> 0.76990137 | K35: ='Forecasted FS'!H158 -> 0.7772493 | L35: ='Forecasted FS'!I158 -> 0.78910175 | M35: ='Forecasted FS'!J158 -> 0.80191812
B36: d. | C36: Interest Coverage (x) | D36: ='Actuals FS'!H132 -> -13.903461 | E36: ='Actuals FS'!G132 -> -13.752902 | F36: ='Actuals FS'!F132 -> -5.1744825 | G36: ='Actuals FS'!E132 -> -11.581395 | H36: ='Forecasted FS'!E159 -> -28.509144 | I36: ='Forecasted FS'!F159 -> -41.177185 | J36: ='Forecasted FS'!G159 -> -52.692631 | K36: ='Forecasted FS'!H159 -> -63.841332 | L36: ='Forecasted FS'!I159 -> -75.957142 | M36: ='Forecasted FS'!J159 -> -88.226487
B37: e. | C37: Total Debt | D37: ='Actuals FS'!H133 -> 31816 | E37: ='Actuals FS'!G133 -> 48744 | F37: ='Actuals FS'!F133 -> 67150 | G37: ='Actuals FS'!E133 -> 58314 | H37: ='Forecasted FS'!E160 -> 52623 | I37: ='Forecasted FS'!F160 -> 57214 | J37: ='Forecasted FS'!G160 -> 61805 | K37: ='Forecasted FS'!H160 -> 64100.5 | L37: ='Forecasted FS'!I160 -> 65248.25 | M37: ='Forecasted FS'!J160 -> 65822.125
B38: f. | C38: Total Debt to EBITDA (x) | D38: ='Actuals FS'!H134 -> 0.75750577 | E38: ='Actuals FS'!G134 -> 0.79650963 | F38: ='Actuals FS'!F134 -> 1.676696 | G38: ='Actuals FS'!E134 -> 0.84775972 | H38: ='Forecasted FS'!E161 -> 0.52427968 | I38: ='Forecasted FS'!F161 -> 0.55114174 | J38: ='Forecasted FS'!G161 -> 0.51162832 | K38: ='Forecasted FS'!H161 -> 0.46797576 | L38: ='Forecasted FS'!I161 -> 0.42139928 | M38: ='Forecasted FS'!J161 -> 0.38105901
B39: g. | C39: Total Debt to Net Worth | D39: ='Actuals FS'!H135 -> 0.34062781 | E39: ='Actuals FS'!G135 -> 0.35259141 | F39: ='Actuals FS'!F135 -> 0.45979609 | G39: ='Actuals FS'!E135 -> 0.28886192 | H39: ='Forecasted FS'!E162 -> 0.18401581 | I39: ='Forecasted FS'!F162 -> 0.1528711 | J39: ='Forecasted FS'!G162 -> 0.12861953 | K39: ='Forecasted FS'!H162 -> 0.10617108 | L39: ='Forecasted FS'!I162 -> 0.08741259 | M39: ='Forecasted FS'!J162 -> 0.072423427
B41: =B32+1 -> 5 | C41: DuPont Analysis. (ROE break-down)
B42: a. | C42: Return on Sales, net profit margin (%) | D42: ='Actuals FS'!H137 -> 0.055252497 | E42: ='Actuals FS'!G137 -> 0.071014129 | F42: ='Actuals FS'!F137 -> -0.005295895 | G42: ='Actuals FS'!E137 -> 0.052932836 | H42: ='Forecasted FS'!E164 -> 0.092871172 | I42: ='Forecasted FS'!F164 -> 0.097783913 | J42: ='Forecasted FS'!G164 -> 0.11338584 | K42: ='Forecasted FS'!H164 -> 0.12449094 | L42: ='Forecasted FS'!I164 -> 0.13458979 | M42: ='Forecasted FS'!J164 -> 0.14206971
B43: b. | C43: Asset Turnover (x) | D43: ='Actuals FS'!H138 -> 1.2019614 | E43: ='Actuals FS'!G138 -> 1.1171635 | F43: ='Actuals FS'!F138 -> 1.1108943 | G43: ='Actuals FS'!E138 -> 1.0889091 | H43: ='Forecasted FS'!E165 -> 1.0209075 | I43: ='Forecasted FS'!F165 -> 1.0024304 | J43: ='Forecasted FS'!G165 -> 0.92382937 | K43: ='Forecasted FS'!H165 -> 0.85318671 | L43: ='Forecasted FS'!I165 -> 0.79915803 | M43: ='Forecasted FS'!J165 -> 0.7517438
B44: c. | C44: Asset to Equity (x) | D44: ='Actuals FS'!H139 -> 3.4387714 | E44: ='Actuals FS'!G139 -> 3.0420558 | F44: ='Actuals FS'!F139 -> 3.1680738 | G44: ='Actuals FS'!E139 -> 2.6147567 | H44: ='Forecasted FS'!E166 -> 2.1851733 | I44: ='Forecasted FS'!F166 -> 1.9692788 | J44: ='Forecasted FS'!G166 -> 1.8183634 | K44: ='Forecasted FS'!H166 -> 1.7016648 | L44: ='Forecasted FS'!I166 -> 1.6146897 | M44: ='Forecasted FS'!J166 -> 1.5465014
B45: d. | C45: Return on Equity (%) | D45: ='Actuals FS'!H140 -> 0.22837352 | E45: ='Actuals FS'!G140 -> 0.24133965 | F45: ='Actuals FS'!F140 -> -0.018638346 | G45: ='Actuals FS'!E140 -> 0.15071207 | H45: ='Forecasted FS'!E167 -> 0.20718257 | I45: ='Forecasted FS'!F167 -> 0.1930318 | J45: ='Forecasted FS'!G167 -> 0.19047206 | K45: ='Forecasted FS'!H167 -> 0.18074065 | L45: ='Forecasted FS'!I167 -> 0.17367362 | M45: ='Forecasted FS'!J167 -> 0.16516639
B47: =B41+1 -> 6 | C47: Dividend & Price Metrics
B48: a. | C48: Price per Share at year end | D48: ='Actuals FS'!H142 -> 201.16 | E48: ='Actuals FS'!G142 -> 42.67 | F48: ='Actuals FS'!F142 -> 100.55 | G48: ='Actuals FS'!D142 -> 228.97 | H48: ='Forecasted FS'!E169 -> 228.97 | I48: ='Forecasted FS'!F169 -> 241.10198 | J48: ='Forecasted FS'!G169 -> 284.8201 | K48: ='Forecasted FS'!H169 -> 318.58696 | L48: ='Forecasted FS'!I169 -> 354.11716 | M48: ='Forecasted FS'!J169 -> 384.30937
B49: b. | C49: Earnings Per Share | D49: ='Actuals FS'!H143 -> 41.82549 | E49: ='Actuals FS'!G143 -> 64.784466 | F49: ='Actuals FS'!F143 -> -0.26715085 | G49: ='Actuals FS'!E143 -> 2.8998284 | H49: ='Forecasted FS'!E170 -> 5.5263502 | I49: ='Forecasted FS'!F170 -> 6.1254358 | J49: ='Forecasted FS'!G170 -> 7.6169874 | K49: ='Forecasted FS'!H170 -> 8.9684418 | L49: ='Forecasted FS'!I170 -> 10.493307 | M49: ='Forecasted FS'!J170 -> 11.987338
B50: c. | C50: Price to Earnings | D50: ='Actuals FS'!H144 -> 4.8095074 | E50: ='Actuals FS'!G144 -> 0.65864555 | F50: ='Actuals FS'!F144 -> -376.37911 | G50: ='Actuals FS'!E144 -> 50.858181 | H50: ='Forecasted FS'!E171 -> 41.432409 | I50: ='Forecasted FS'!F171 -> 39.360789 | J50: ='Forecasted FS'!G171 -> 37.392749 | K50: ='Forecasted FS'!H171 -> 35.523112 | L50: ='Forecasted FS'!I171 -> 33.746956 | M50: ='Forecasted FS'!J171 -> 32.059608
B51: d. | C51: Dividend per Share | D51: ='Actuals FS'!H145 -> 0 | E51: ='Actuals FS'!G145 -> 0 | F51: ='Actuals FS'!F145 -> 0 | G51: ='Actuals FS'!E145 -> 0 | H51: ='Forecasted FS'!E172 -> 0 | I51: ='Forecasted FS'!F172 -> 0 | J51: ='Forecasted FS'!G172 -> 0 | K51: ='Forecasted FS'!H172 -> 0 | L51: ='Forecasted FS'!I172 -> 0 | M51: ='Forecasted FS'!J172 -> 0
B52: e. | C52: Dividend Payout Ratio (%) | D52: ='Actuals FS'!H146 -> 0 | E52: ='Actuals FS'!G146 -> 0 | F52: ='Actuals FS'!F146 -> 0 | G52: ='Actuals FS'!E146 -> 0 | H52: ='Forecasted FS'!E173 -> 0 | I52: ='Forecasted FS'!F173 -> 0 | J52: ='Forecasted FS'!G173 -> 0 | K52: ='Forecasted FS'!H173 -> 0 | L52: ='Forecasted FS'!I173 -> 0 | M52: ='Forecasted FS'!J173 -> 0
B53: f. | C53: Dividend Yield (%) | D53: ='Actuals FS'!H147 -> 0 | E53: ='Actuals FS'!G147 -> 0 | F53: ='Actuals FS'!F147 -> 0 | G53: ='Actuals FS'!E147 -> 0 | H53: ='Forecasted FS'!E174 -> 0 | I53: ='Forecasted FS'!F174 -> 0 | J53: ='Forecasted FS'!G174 -> 0 | K53: ='Forecasted FS'!H174 -> 0 | L53: ='Forecasted FS'!I174 -> 0 | M53: ='Forecasted FS'!J174 -> 0
B55: =B47+1 -> 7 | C55: Margins
B56: a. | C56: Revenue Growth (%) | D56: ='Actuals FS'!H149 -> n.a | E56: ='Actuals FS'!G149 -> 0.21695367 | F56: ='Actuals FS'!F149 -> 0.093995173 | G56: ='Actuals FS'!E149 -> 0.11829574 | H56: ='Forecasted FS'!E176 -> 0.10990892 | I56: ='Forecasted FS'!F176 -> 0.07 | J56: ='Forecasted FS'!G176 -> 0.09 | K56: ='Forecasted FS'!H176 -> 0.09 | L56: ='Forecasted FS'!I176 -> 0.1 | M56: ='Forecasted FS'!J176 -> 0.1
B57: b. | C57: COGS (excluding D&A) as % of Sales | D57: ='Actuals FS'!H150 -> 0.53909973 | E57: ='Actuals FS'!G150 -> 0.5063854 | F57: ='Actuals FS'!F150 -> 0.48038554 | G57: ='Actuals FS'!E150 -> 0.44551615 | H57: ='Forecasted FS'!E177 -> 0.42869996 | I57: ='Forecasted FS'!F177 -> -0.59332396 | J57: ='Forecasted FS'!G177 -> -0.58686817 | K57: ='Forecasted FS'!H177 -> -0.57999777 | L57: ='Forecasted FS'!I177 -> -0.57202908 | M57: ='Forecasted FS'!J177 -> -0.56379382
B58: c. | C58: Gross Profit | D58: ='Actuals FS'!H151 -> 152757 | E58: ='Actuals FS'!G151 -> 197478 | F58: ='Actuals FS'!F151 -> 225152 | G58: ='Actuals FS'!E151 -> 270046 | H58: ='Forecasted FS'!E178 -> 311671 | I58: ='Forecasted FS'!F178 -> 334481.9 | J58: ='Forecasted FS'!G178 -> 368305.53 | K58: ='Forecasted FS'!H178 -> 405508.11 | L58: ='Forecasted FS'!I178 -> 450519.51 | M58: ='Forecasted FS'!J178 -> 500478.11
B59: d. | C59: Gross Margin (%) | D59: ='Actuals FS'!H152 -> 0.39567792 | E59: ='Actuals FS'!G152 -> 0.42032514 | F59: ='Actuals FS'!F152 -> 0.4380534 | G59: ='Actuals FS'!E152 -> 0.46982089 | H59: ='Forecasted FS'!E179 -> 0.48854393 | I59: ='Forecasted FS'!F179 -> 0.49 | J59: ='Forecasted FS'!G179 -> 0.495 | K59: ='Forecasted FS'!H179 -> 0.5 | L59: ='Forecasted FS'!I179 -> 0.505 | M59: ='Forecasted FS'!J179 -> 0.51
B60: e. | C60: SG&A as % of Sales | D60: ='Actuals FS'!H153 -> 0.33655819 | E60: ='Actuals FS'!G153 -> 0.36723908 | F60: ='Actuals FS'!F153 -> 0.41176654 | G60: ='Actuals FS'!E153 -> 0.40437207 | H60: ='Forecasted FS'!E180 -> 0.37982848 | I60: ='Forecasted FS'!F180 -> 0.36543823 | J60: ='Forecasted FS'!G180 -> 0.35067694 | K60: ='Forecasted FS'!H180 -> 0.34160633 | L60: ='Forecasted FS'!I180 -> 0.33377613 | M60: ='Forecasted FS'!J180 -> 0.32926542
B61: f. | C61: R&D as % of Sales | D61: ='Actuals FS'!H154 -> 0.11070703 | E61: ='Actuals FS'!G154 -> 0.11930476 | F61: ='Actuals FS'!F154 -> 0.14244245 | G61: ='Actuals FS'!E154 -> 0.14896353 | H61: ='Forecasted FS'!E181 -> 0.13879262 | I61: ='Forecasted FS'!F181 -> 0.22633547 | J61: ='Forecasted FS'!G181 -> 0.17574506 | K61: ='Forecasted FS'!H181 -> 0.13727463 | L61: ='Forecasted FS'!I181 -> 0.10687898 | M61: ='Forecasted FS'!J181 -> 0.08370282
B62: g. | C62: Interest expense of financial products (% of sales) | D62: ='Actuals FS'!H155 -> 0.0061414688 | E62: ='Actuals FS'!G155 -> 0.031145838 | F62: ='Actuals FS'!F155 -> -0.032697579 | G62: ='Actuals FS'!E155 -> 0.0016319145 | H62: ='Forecasted FS'!E182 -> -0.0035268724 | I62: ='Forecasted FS'!F182 -> -0.0029959737 | J62: ='Forecasted FS'!G182 -> -0.0027162633 | K62: ='Forecasted FS'!H182 -> -0.0024623182 | L62: ='Forecasted FS'!I182 -> -0.0022384711 | M62: ='Forecasted FS'!J182 -> -0.0020349737
B63: h. | C63: EBITDA | D63: ='Actuals FS'!H156 -> 42001 | E63: ='Actuals FS'!G156 -> 61197 | F63: ='Actuals FS'!F156 -> 40049 | G63: ='Actuals FS'!E156 -> 68786 | H63: ='Forecasted FS'!E183 -> 100372 | I63: ='Forecasted FS'!F183 -> 103809.96 | J63: ='Forecasted FS'!G183 -> 120800.59 | K63: ='Forecasted FS'!H183 -> 136973.97 | L63: ='Forecasted FS'!I183 -> 154837.12 | M63: ='Forecasted FS'!J183 -> 172734.73
B64: i. | C64: EBITDA Margin | D64: ='Actuals FS'!H157 -> 0.10879284 | E64: ='Actuals FS'!G157 -> 0.13025571 | F64: ='Actuals FS'!F157 -> 0.077918919 | G64: ='Actuals FS'!E157 -> 0.11967257 | H64: ='Forecasted FS'!E184 -> 0.15733299 | I64: ='Forecasted FS'!F184 -> 0.15207662 | J64: ='Forecasted FS'!G184 -> 0.16235512 | K64: ='Forecasted FS'!H184 -> 0.16889178 | L64: ='Forecasted FS'!I184 -> 0.17356128 | M64: ='Forecasted FS'!J184 -> 0.17602111
B65: j. | C65: NOPAT | D65: ='Actuals FS'!H158 -> 18090.21 | E65: ='Actuals FS'!G158 -> 19654.41 | F65: ='Actuals FS'!F158 -> 9675.92 | G65: ='Actuals FS'!E158 -> 29113.08 | H65: ='Forecasted FS'!E185 -> 54188.47 | I65: ='Forecasted FS'!F185 -> 66527.055 | J65: ='Forecasted FS'!G185 -> 84130.193 | K65: ='Forecasted FS'!H185 -> 100716.99 | L65: ='Forecasted FS'!I185 -> 119831.07 | M65: ='Forecasted FS'!J185 -> 139187.36
B66: k. | C66: Effective Tax Rate | D66: ='Actuals FS'!H159 -> -0.11841343 | E66: ='Actuals FS'!G159 -> -0.12557993 | F66: ='Actuals FS'!F159 -> -0.54194744 | G66: ='Actuals FS'!E159 -> -0.18957851 | H66: ='Forecasted FS'!E186 -> -0.13503075 | I66: ='Forecasted FS'!F186 -> -0.21 | J66: ='Forecasted FS'!G186 -> -0.21 | K66: ='Forecasted FS'!H186 -> -0.21 | L66: ='Forecasted FS'!I186 -> -0.21 | M66: ='Forecasted FS'!J186 -> -0.21
B67: l. | C67: Capex as % of Sales | D67: ='Actuals FS'!H160 -> -0.1039724 | E67: ='Actuals FS'!G160 -> -0.12994921 | F67: ='Actuals FS'!F160 -> -0.12382705 | G67: ='Actuals FS'!E160 -> -0.09173691 | H67: ='Forecasted FS'!E187 -> -0.13010084 | I67: ='Forecasted FS'!F187 -> -0.12853963 | J67: ='Forecasted FS'!G187 -> -0.12699715 | K67: ='Forecasted FS'!H187 -> -0.12547319 | L67: ='Forecasted FS'!I187 -> -0.12396751 | M67: ='Forecasted FS'!J187 -> -0.1224799
B68: m. | C68: Fulfillment Expense (% of sales) | D68: ='Actuals FS'!H161 -> 0.15157331 | E68: ='Actuals FS'!G161 -> 0.15987119 | F68: ='Actuals FS'!F161 -> 0.16401126 | G68: ='Actuals FS'!E161 -> 0.15765721 | H68: ='Forecasted FS'!E188 -> 0.15440647 | I68: ='Forecasted FS'!F188 -> 0.1665281 | J68: ='Forecasted FS'!G188 -> 0.17600034 | K68: ='Forecasted FS'!H188 -> 0.18568844 | L68: ='Forecasted FS'!I188 -> 0.19379121 | M68: ='Forecasted FS'!J188 -> 0.2018952

Sheet Operating Margin
C3: Operating Margin Target Based on Management Expectations
C4: Figures in USD billions, unless told otherwise
C8: Scenario | D8: =DCF!E10 -> Base Case
C10: TARGET | D10: Operating Margin
C11: Revenues | D11: Low | E11: High
C12: =C17 -> 386.064 | D12: =D17 -> 0.11 | E12: =E17 -> 0.11
C13: =C18 -> 469.822 | D13: =D18 -> 0.1125 | E13: =E18 -> 0.1175
D15: Operating Margin | G15: Forecast
C16: Revenues | D16: Low | E16: High | G16: Year | H16: Revenues | I16: Margin
C17: =H17 -> 386.064 | D17: 0.11 | E17: 0.11 | G17: 2020 | H17: ='Actuals FS'!H47/1000 -> 386.064 | I17: ='Actuals FS'!H56/'Actuals FS'!H47 -> 0.059314
C18: =H18 -> 469.822 | D18: =D17+0.25% -> 0.1125 | E18: =E17+0.75% -> 0.1175 | G18: 2021 | H18: ='Actuals FS'!G47/1000 -> 469.822 | I18: ='Actuals FS'!G56/'Actuals FS'!G47 -> 0.052954098
C19: =H19 -> 513.983 | D19: =D18+0.25% -> 0.115 | E19: =E18+0.75% -> 0.125 | G19: 2022 | H19: ='Actuals FS'!F47/1000 -> 513.983 | I19: ='Actuals FS'!F56/'Actuals FS'!F47 -> 0.023829582
C20: =H20 -> 574.785 | D20: =D19+0.25% -> 0.1175 | E20: =E19+0.75% -> 0.1325 | G20: 2023 | H20: ='Actuals FS'!E47/1000 -> 574.785 | I20: ='Actuals FS'!E56/'Actuals FS'!E47 -> 0.064114408
C21: =H21 -> 637.959 | D21: =D20+0.25% -> 0.12 | E21: =E20+0.75% -> 0.14 | G21: 2024 | H21: {=TRANSPOSE(DCF!E27:J27)/1000} -> 637.959 | I21: {=TRANSPOSE(DCF!E28:J28)} -> 0.10990892
C22: =H22 -> 682.61613 | D22: =D21+0.25% -> 0.1225 | E22: =E21+0.75% -> 0.1475 | G22: 2025 | H22: 682.61613 | I22: 0.07
C23: =H23 -> 744.05158 | D23: =D22+0.25% -> 0.125 | E23: =E22+0.75% -> 0.155 | G23: 2026 | H23: 744.05158 | I23: 0.09
C24: =H24 -> 811.01622 | D24: =D23+0.25% -> 0.1275 | E24: =E23+0.75% -> 0.1625 | G24: 2027 | H24: 811.01622 | I24: 0.09
C25: =H25 -> 892.11785 | D25: =D24+0.25% -> 0.13 | E25: =E24+0.75% -> 0.17 | G25: 2028 | H25: 892.11785 | I25: 0.1
C26: =H26 -> 981.32963 | D26: =D25+0.25% -> 0.1325 | E26: =E25+0.75% -> 0.1775 | G26: 2029 | H26: 981.32963 | I26: 0.02

Sheet D&A
C3: Depreciation & Amortization Schedule
C4: Figures in USD millions, unless told otherwise
C8: Depreciation & Amortization Schedule
E10: 2024 | F10: 2025 | G10: =F10+1 -> 2026 | H10: =G10+1 -> 2027 | I10: =H10+1 -> 2028 | J10: =I10+1 -> 2029 | L10: NOTES:
C11: Depreciation | D11: D&A % of Sales
C12: Method - Percentage of Sales Method | D12: ='Forecasted FS'!E102/'Forecasted FS'!E37 -> 0.082756102 | L12: Using a straight line method with the average useful life of depreciable assets
D13: {=TRANSPOSE(E10:J10)} -> 2024 | E13: ='Forecasted FS'!E102 -> 52795 | F13: =E13*(1+$D$12) -> 57164.108 | G13: =F13*(1+$D$12) -> 61894.787 | H13: =G13*(1+$D$12) -> 67016.958 | I13: =H13*(1+$D$12) -> 72563.021 | J13: =I13*(1+$D$12) -> 78568.053
C14: Depreciation for Fiscal Year | D14: 2025 | E14: =SUM(E13:E13) -> 52795 | F14: =SUM(F13:F13) -> 57164.108 | G14: =SUM(G13:G13) -> 61894.787 | H14: =SUM(H13:H13) -> 67016.958 | I14: =SUM(I13:I13) -> 72563.021 | J14: =SUM(J13:J13) -> 78568.053
C15: Capex | D15: 2026 | E15: =-('Actuals FS'!D87+'Actuals FS'!D88) -> 77658 | F15: ='Forecasted FS'!F37*F16 -> -95566.258 | G15: ='Forecasted FS'!G37*G16 -> -107887.48 | H15: ='Forecasted FS'!H37*H16 -> -117597.35 | I15: ='Forecasted FS'!I37*I16 -> -120435.91 | J15: ='Forecasted FS'!J37*J16 -> -127572.85
C16: Capex as % of Sales | D16: 2027 | E16: =E15/'Actuals FS'!D47 -> 0.12172883 | F16: =Scenarios!E57 -> -0.14 | G16: =Scenarios!F57 -> -0.145 | H16: =Scenarios!G57 -> -0.145 | I16: =Scenarios!H57 -> -0.135 | J16: =Scenarios!I57 -> -0.13 | L16: Following scenario assumptions
C17: PP&E, gross | D17: 2028 | E17: ='Actuals FS'!D87 -> -82999 | F17: =E17+F15 -> -178565.26 | G17: =F17+G15 -> -286452.74 | H17: =G17+H15 -> -404050.09 | I17: =H17+I15 -> -524486 | J17: =I17+J15 -> -652058.85
C18: Accumulated Depreciation | D18: 2029 | E18: ='Actuals FS'!D75 -> 52795 | F18: =E18-F14 -> -4369.1084 | G18: =F18-G14 -> -66263.896 | H18: =G18-H14 -> -133280.85 | I18: =H18-I14 -> -205843.87 | J18: =I18-J14 -> -284411.93
C19: PP&E, net | E19: =E17+E18 -> -30204 | F19: =F17+F18 -> -182934.37 | G19: =G17+G18 -> -352716.63 | H19: =H17+H18 -> -537330.94 | I19: =I17+I18 -> -730329.87 | J19: =J17+J18 -> -936470.78
C22: Depreciation & Amortization Expense | E22: =E14 -> 52795 | F22: =F14 -> 57164.108 | G22: =G14 -> 61894.787 | H22: =H14 -> 67016.958 | I22: =I14 -> 72563.021 | J22: =J14 -> 78568.053
C24: Average Useful Life Calculations
D26: 2023 | E26: 2024
C27: PP&E gross depreciable | D27: ='Actuals FS'!E17 -> 204177 | E27: ='Actuals FS'!D17 -> 252665
C28: Average Useful Life (years) | E28: =AVERAGE(D27:E27)/E14 -> 4.326565
C30: Source: Company Information
C31: https://investors.caterpillar.com/financials/quarterly-results/default.aspx

Sheet Bonds
C3: Summary of Corporate Bonds
C4: Figures in USD millions, unless told otherwise
C8: Valuation Date | D8: 46003
C10: Outstanding Corporate Bonds
C12: Bond | D12: Settlement Date | E12: Maturity Date | F12: Maturity (years) | G12: Years left to Maturity | H12: Coupon Rate (%) | I12: Principal | J12: YTM at issuance (%) | K12: Current YTM (%) | L12: Redemption | M12: Frequency | N12: Price at Issuance | O12: Current Price | P12: Duration | Q12: Duration*
B13: 1 | C13: Amazon Conservation DACDL-Notes 2024(33-42) Reg.S | D13: 45642 | E13: 51882 | F13: 17 | G13: =(E13-$D$8)/365 -> 16.106849 | H13: 0.06034 | I13: 1000 | J13: =H13 -> 0.06034 | K13: 0.0582 | L13: 100 | M13: 4 | N13: =PRICE(D13,E13,H13,J13,L13,M13) -> 99.997488 | O13: =PRICE($D$8,E13,H13,K13,L13,M13) -> 102.22357 | P13: =DURATION($D$8,E13,H13,K13,M13) -> 10.380605 | Q13: =MDURATION($D$8,E13,H13,K13,M13) -> 10.231733
B14: 2 | C14: Amazon.com Inc.DL-Notes 2017(17/47) | D14: 42957 | E14: 53926 | F14: 30 | G14: =(E14-$D$8)/365 -> 21.706849 | H14: 0.0405 | I14: 1000 | J14: 0.0409 | K14: 0.0548 | L14: 100 | M14: 2 | N14: =PRICE(D14,E14,H14,J14,L14,M14) -> 99.310625 | O14: =PRICE($D$8,E14,H14,K14,L14,M14) -> 81.974462 | P14: =DURATION($D$8,E14,H14,K14,M14) -> 13.604965 | Q14: =MDURATION($D$8,E14,H14,K14,M14) -> 13.242131
B15: 3 | C15: Amazon.com Inc.DL-Notes 2022(22/27) | D15: 44664 | E15: 46490 | F15: 5 | G15: =(E15-$D$8)/365 -> 1.3342466 | H15: 0.033 | I15: 1000 | J15: 0.0335 | K15: 0.037 | L15: 100 | M15: 2 | N15: =PRICE(D15,E15,H15,J15,L15,M15) -> 99.771568 | O15: =PRICE($D$8,E15,H15,K15,L15,M15) -> 99.479871 | P15: =DURATION($D$8,E15,H15,K15,M15) -> 1.3118173 | Q15: =MDURATION($D$8,E15,H15,K15,M15) -> 1.2879895
B16: 4 | C16: Amazon.com Inc.DL-Notes 2022(22/29) | D16: 44896 | E16: 47453 | F16: 7 | G16: =(E16-$D$8)/365 -> 3.9726027 | H16: 0.0465 | I16: 1000 | J16: 0.0466 | K16: 0.0392 | L16: 100 | M16: 2 | N16: =PRICE(D16,E16,H16,J16,L16,M16) -> 99.940851 | O16: =PRICE($D$8,E16,H16,K16,L16,M16) -> 102.6582 | P16: =DURATION($D$8,E16,H16,K16,M16) -> 3.6701999 | Q16: =MDURATION($D$8,E16,H16,K16,M16) -> 3.5996469
B17: 5 | C17: Amazon.com Inc.DL-Notes 2017(17/57) | D17: 42969 | E17: 57579 | F17: 40 | G17: =(E17-$D$8)/365 -> 31.715068 | H17: 0.0425 | I17: 1000 | J17: 0.0429 | K17: 0.055 | L17: 100 | M17: 2 | N17: =PRICE(D17,E17,H17,J17,L17,M17) -> 99.238299 | O17: =PRICE($D$8,E17,H17,K17,L17,M17) -> 81.336955 | P17: =DURATION($D$8,E17,H17,K17,M17) -> 15.903133 | Q17: =MDURATION($D$8,E17,H17,K17,M17) -> 15.477502
B18: 6 | C18: Amazon.com Inc.DL-Notes 2020(20/30) | D18: 43985 | E18: 47637 | F18: 10 | G18: =(E18-$D$8)/365 -> 4.4767123 | H18: 0.015 | I18: 1000 | J18: 0.0151 | K18: 0.04 | L18: 100 | M18: 2 | N18: =PRICE(D18,E18,H18,J18,L18,M18) -> 99.907507 | O18: =PRICE($D$8,E18,H18,K18,L18,M18) -> 89.848659 | P18: =DURATION($D$8,E18,H18,K18,M18) -> 4.3341579 | Q18: =MDURATION($D$8,E18,H18,K18,M18) -> 4.2491745
B19: 7 | C19: Amazon.com Inc.DL-Notes 2021(21/28) | D19: 44328 | E19: 46885 | F19: 7 | G19: =(E19-$D$8)/365 -> 2.4164384 | H19: 0.0165 | I19: 1000 | J19: 0.0166 | K19: 0.0385 | L19: 100 | M19: 2 | N19: =PRICE(D19,E19,H19,J19,L19,M19) -> 99.934171 | O19: =PRICE($D$8,E19,H19,K19,L19,M19) -> 94.96814 | P19: =DURATION($D$8,E19,H19,K19,M19) -> 2.3747762 | Q19: =MDURATION($D$8,E19,H19,K19,M19) -> 2.3299252
B20: 8 | C20: Amazon.com Inc.DL-Notes 2021(21/26) | D20: 44328 | E20: 46154 | F20: 5 | G20: =(E20-$D$8)/365 -> 0.41369863 | H20: 0.01 | I20: 1000 | J20: 0.0109 | K20: 0.038 | L20: 100 | M20: 2 | N20: =PRICE(D20,E20,H20,J20,L20,M20) -> 99.5632 | O20: =PRICE($D$8,E20,H20,K20,L20,M20) -> 98.850219 | P20: =DURATION($D$8,E20,H20,K20,M20) -> 0.41666667 | Q20: =MDURATION($D$8,E20,H20,K20,M20) -> 0.40889761
B21: 9 | C21: Amazon.com Inc.DL-Notes 2020(20/50) | D21: 43985 | E21: 54942 | F21: 30 | G21: =(E21-$D$8)/365 -> 24.490411 | H21: 0.025 | I21: 1000 | J21: 0.0255 | K21: 0.0548 | L21: 100 | M21: 2 | N21: =PRICE(D21,E21,H21,J21,L21,M21) -> 98.956058 | O21: =PRICE($D$8,E21,H21,K21,L21,M21) -> 60.100159 | P21: =DURATION($D$8,E21,H21,K21,M21) -> 16.321934 | Q21: =MDURATION($D$8,E21,H21,K21,M21) -> 15.88664
B22: 10 | C22: Amazon.com Inc.DL-Notes 2022(22/62) | D22: 44664 | E22: 59274 | F22: 40 | G22: =(E22-$D$8)/365 -> 36.358904 | H22: 0.041 | I22: 1000 | J22: 0.0412 | K22: 0.0548 | L22: 100 | M22: 2 | N22: =PRICE(D22,E22,H22,J22,L22,M22) -> 99.609555 | O22: =PRICE($D$8,E22,H22,K22,L22,M22) -> 78.342917 | P22: =DURATION($D$8,E22,H22,K22,M22) -> 16.888179 | Q22: =MDURATION($D$8,E22,H22,K22,M22) -> 16.437784
B23: 11 | C23: Amazon.com Inc.DL-Notes 2022(22/32) | D23: 44664 | E23: 48317 | F23: 10 | G23: =(E23-$D$8)/365 -> 6.339726 | H23: 0.036 | I23: 1000 | J23: 0.0362 | K23: 0.0426 | L23: 100 | M23: 2 | N23: =PRICE(D23,E23,H23,J23,L23,M23) -> 99.833447 | O23: =PRICE($D$8,E23,H23,K23,L23,M23) -> 96.364413 | P23: =DURATION($D$8,E23,H23,K23,M23) -> 5.6740933 | Q23: =MDURATION($D$8,E23,H23,K23,M23) -> 5.5557557
B24: 12 | C24: Amazon.com Inc.DL-Notes 2017(17/27) | D24: 42969 | E24: 46621 | F24: 10 | G24: =(E24-$D$8)/365 -> 1.6931507 | H24: 0.0315 | I24: 1000 | J24: 0.0317 | K24: 0.0368 | L24: 100 | M24: 2 | N24: =PRICE(D24,E24,H24,J24,L24,M24) -> 99.829744 | O24: =PRICE($D$8,E24,H24,K24,L24,M24) -> 99.133627 | P24: =DURATION($D$8,E24,H24,K24,M24) -> 1.6481354 | Q24: =MDURATION($D$8,E24,H24,K24,M24) -> 1.6183576
B25: 13 | C25: Amazon.com Inc.DL-Notes 2017(17/37) | D25: 42969 | E25: 50274 | F25: 20 | G25: =(E25-$D$8)/365 -> 11.70137 | H25: 0.03875 | I25: 1000 | J25: 0.0389 | K25: 0.0476 | L25: 100 | M25: 2 | N25: =PRICE(D25,E25,H25,J25,L25,M25) -> 99.792841 | O25: =PRICE($D$8,E25,H25,K25,L25,M25) -> 92.127602 | P25: =DURATION($D$8,E25,H25,K25,M25) -> 9.2852082 | Q25: =MDURATION($D$8,E25,H25,K25,M25) -> 9.0693575
... B43: 32 | C43: Amazon.com Inc.DL-Notes 2025(25/65) | D43: 45981 | E43: 60591 | F43: 40 | G43: =(E43-$D$8)/365 -> 39.967123 | H43: 0.0555 | I43: 1000 | J43: 0.0558 | K43: 0.0558 | L43: 100 | M43: 2 | N43: =PRICE(D43,E43,H43,J43,L43,M43) -> 99.521852 | O43: =PRICE($D$8,E43,H43,K43,L43,M43) -> 99.51797 | P43: =DURATION($D$8,E43,H43,K43,M43) -> 16.33595 | Q43: =MDURATION($D$8,E43,H43,K43,M43) -> 15.892547
C44: Min | F44: =MIN(F13:F43) -> 3 | G44: =MIN(G13:G43) -> 0.41369863 | H44: =MIN(H13:H43) -> 0.01 | I44: =MIN(I13:I43) -> 1000 | J44: =MIN(J13:J43) -> 0.0109 | K44: =MIN(K13:K43) -> 0.0368 | N44: =MIN(N13:N43) -> 98.463331 | O44: =MIN(O13:O43) -> 57.238936 | P44: =MIN(P13:P43) -> 0.41666667 | Q44: =MIN(Q13:Q43) -> 0.40889761
C45: Max | F45: =MAX(F13:F43) -> 40 | G45: =MAX(G13:G43) -> 39.967123 | H45: =MAX(H13:H43) -> 0.06034 | I45: =MAX(I13:I43) -> 1000 | J45: =MAX(J13:J43) -> 0.06034 | K45: =MAX(K13:K43) -> 0.0582 | N45: =MAX(N13:N43) -> 100 | O45: =MAX(O13:O43) -> 102.68854 | P45: =MAX(P13:P43) -> 18.400623 | Q45: =MAX(Q13:Q43) -> 17.910764
C46: Median | F46: =MEDIAN(F13:F43) -> 10 | G46: =MEDIAN(G13:G43) -> 8.9863014 | H46: =MEDIAN(H13:H43) -> 0.039 | I46: =MEDIAN(I13:I43) -> 1000 | J46: =MEDIAN(J13:J43) -> 0.0391 | K46: =MEDIAN(K13:K43) -> 0.0455 | N46: =MEDIAN(N13:N43) -> 99.762589 | O46: =MEDIAN(O13:O43) -> 97.240717 | P46: =MEDIAN(P13:P43) -> 7.4103796 | Q46: =MEDIAN(Q13:Q43) -> 7.2455434
C47: Mean | F47: =AVERAGE(F13:F43) -> 18.580645 | G47: =AVERAGE(G13:G43) -> 14.259832 | H47: =AVERAGE(H13:H43) -> 0.036543226 | I47: =AVERAGE(I13:I43) -> 1000 | J47: =AVERAGE(J13:J43) -> 0.036830323 | K47: =AVERAGE(K13:K43) -> 0.046635484 | N47: =AVERAGE(N13:N43) -> 99.623217 | O47: =AVERAGE(O13:O43) -> 90.567721 | P47: =AVERAGE(P13:P43) -> 8.7535128 | Q47: =AVERAGE(Q13:Q43) -> 8.5387254
C49: Source: Morningstar
C50: https://finra-markets.morningstar.com/BondCenter/Default.jsp

Sheet Scenario Summary 
C3: Scenario Summary
C4: Figures in USD millions, unless told otherwise
C8: Scenario Analysis Summary
E10: Bear Case | K10: Base Case | Q10: Bull Case
E11: 2025 | F11: =E11+1 -> 2026 | G11: =F11+1 -> 2027 | H11: =G11+1 -> 2028 | I11: =H11+1 -> 2029 | K11: 2025 | L11: =K11+1 -> 2026 | M11: =L11+1 -> 2027 | N11: =M11+1 -> 2028 | O11: =N11+1 -> 2029 | Q11: 2025 | R11: =Q11+1 -> 2026 | S11: =R11+1 -> 2027 | T11: =S11+1 -> 2028 | U11: =T11+1 -> 2029
D12: Sales Growth (%) | E12: =Scenarios!E20 -> 0.05 | F12: =Scenarios!F20 -> 0.06 | G12: =Scenarios!G20 -> 0.06 | H12: =Scenarios!H20 -> 0.07 | I12: =Scenarios!I20 -> 0.07 | K12: =Scenarios!E18 -> 0.07 | L12: =Scenarios!F18 -> 0.09 | M12: =Scenarios!G18 -> 0.09 | N12: =Scenarios!H18 -> 0.1 | O12: =Scenarios!I18 -> 0.1 | Q12: =Scenarios!E19 -> 0.11 | R12: =Scenarios!F19 -> 0.14 | S12: =Scenarios!G19 -> 0.14 | T12: =Scenarios!H19 -> 0.13 | U12: =Scenarios!I19 -> 0.13
D13: Cost of Sales (% of sales) | E13: =Scenarios!E24 -> 0.515 | F13: =Scenarios!F24 -> 0.52 | G13: =Scenarios!G24 -> 0.525 | H13: =Scenarios!H24 -> 0.53 | I13: =Scenarios!I24 -> 0.535 | K13: =Scenarios!E22 -> 0.51 | L13: =Scenarios!F22 -> 0.505 | M13: =Scenarios!G22 -> 0.5 | N13: =Scenarios!H22 -> 0.495 | O13: =Scenarios!I22 -> 0.49 | Q13: =Scenarios!E23 -> 0.505 | R13: =Scenarios!F23 -> 0.49 | S13: =Scenarios!G23 -> 0.48 | T13: =Scenarios!H23 -> 0.47 | U13: =Scenarios!I23 -> 0.46
D14: Fulfillment Expense (% of sales) | E14: =Scenarios!E28 -> 0.16 | F14: =Scenarios!F28 -> 0.165 | G14: =Scenarios!G28 -> 0.165 | H14: =Scenarios!H28 -> 0.17 | I14: =Scenarios!I28 -> 0.17 | K14: =Scenarios!E26 -> 0.154 | L14: =Scenarios!F26 -> 0.152 | M14: =Scenarios!G26 -> 0.15 | N14: =Scenarios!H26 -> 0.148 | O14: =Scenarios!I26 -> 0.146 | Q14: =Scenarios!E27 -> 0.15 | R14: =Scenarios!F27 -> 0.145 | S14: =Scenarios!G27 -> 0.14 | T14: =Scenarios!H27 -> 0.135 | U14: =Scenarios!I27 -> 0.13
D15: Tech & Infra (% of sales) | E15: =Scenarios!E32 -> -0.15 | F15: =Scenarios!F32 -> -0.155 | G15: =Scenarios!G32 -> -0.16 | H15: =Scenarios!H32 -> -0.16 | I15: =Scenarios!I32 -> -0.16 | K15: =Scenarios!E30 -> -0.145 | L15: =Scenarios!F30 -> -0.145 | M15: =Scenarios!G30 -> -0.14 | N15: =Scenarios!H30 -> -0.135 | O15: =Scenarios!I30 -> -0.13 | Q15: =Scenarios!E31 -> -0.135 | R15: =Scenarios!F31 -> -0.13 | S15: =Scenarios!G31 -> -0.125 | T15: =Scenarios!H31 -> -0.12 | U15: =Scenarios!I31 -> -0.115
D16: S&M + G&A (% of sales) | E16: =Scenarios!E36 -> 0.09 | F16: =Scenarios!F36 -> 0.095 | G16: =Scenarios!G36 -> 0.095 | H16: =Scenarios!H36 -> 0.1 | I16: =Scenarios!I36 -> 0.1 | K16: =Scenarios!E34 -> 0.087 | L16: =Scenarios!F34 -> 0.086 | M16: =Scenarios!G34 -> 0.085 | N16: =Scenarios!H34 -> 0.084 | O16: =Scenarios!I34 -> 0.083 | Q16: =Scenarios!E35 -> 0.085 | R16: =Scenarios!F35 -> 0.08 | S16: =Scenarios!G35 -> 0.075 | T16: =Scenarios!H35 -> 0.07 | U16: =Scenarios!I35 -> 0.065
D17: Effective Tax Rate (%) | E17: =Scenarios!E40 -> -0.18 | F17: =Scenarios!F40 -> -0.19 | G17: =Scenarios!G40 -> -0.2 | H17: =Scenarios!H40 -> -0.21 | I17: =Scenarios!I40 -> -0.21 | K17: =Scenarios!E38 -> -0.15 | L17: =Scenarios!F38 -> -0.16 | M17: =Scenarios!G38 -> -0.17 | N17: =Scenarios!H38 -> -0.17 | O17: =Scenarios!I38 -> -0.17 | Q17: =Scenarios!E39 -> -0.12 | R17: =Scenarios!F39 -> -0.125 | S17: =Scenarios!G39 -> -0.13 | T17: =Scenarios!H39 -> -0.135 | U17: =Scenarios!I39 -> -0.14
D18: Capex (% of sales) | E18: =Scenarios!E60 -> -0.12 | F18: =Scenarios!F60 -> -0.11 | G18: =Scenarios!G60 -> -0.11 | H18: =Scenarios!H60 -> -0.1 | I18: =Scenarios!I60 -> -0.1 | K18: =Scenarios!E58 -> -0.14 | L18: =Scenarios!F58 -> -0.145 | M18: =Scenarios!G58 -> -0.145 | N18: =Scenarios!H58 -> -0.135 | O18: =Scenarios!I58 -> -0.13 | Q18: =Scenarios!E59 -> -0.16 | R18: =Scenarios!F59 -> -0.17 | S18: =Scenarios!G59 -> -0.17 | T18: =Scenarios!H59 -> -0.16 | U18: =Scenarios!I59 -> -0.15
D19: Price Per Sher | E19: =Summary!G29 -> 212.05019 | K19: =Summary!G27 -> 292.99442 | Q19: =Summary!G28 -> 291.61809
D20: Upside | E20: =E19/Summary!$E$10-1 -> -0.062512982 | K20: =K19/Summary!$E$10-1 -> 0.29534647 | Q20: =Q19/Summary!$E$10-1 -> 0.28926163

Sheet Peer Mkt Info
C3: Industry Peers Market Information
C4: In local currency as of 12/11/2025
B7: Market Data
C9: Company Name | D9: Stock Exchange | E9: Symbol | F9: Country | G9: Close Price | H9: Equity Beta | I9: No Shares | J9: % of Total Shares | K9: LCY | L9: LCY/USD FX Rate | M9: Price is USD | N9: Market Cap
B10: 1 | C10: Microsoft Corporation | D10: NASDAQ | E10: MSFT | F10: USA | G10: 483.47 | H10: 1.03 | I10: =7432 -> 7432 | J10: 1 | K10: USD | L10: 1 | M10: =G10/L10 -> 483.47 | N10: =M10*I10*J10 -> 3593149 | O10: Primary competitor to AWS (Azure). Essential for cloud valuation.
B11: =B10+1 -> 2 | C11: Alphabet Inc. | D11: NASDAQ | E11: GOOGL | F11: USA | G11: 312.43 | H11: 0.93 | I11: 5818 | J11: 1 | K11: USD | L11: 1 | M11: =G11/L11 -> 312.43 | N11: =M11*I11*J11 -> 1817717.7 | O11: Competes in Cloud (GCP), Advertising, and Streaming (YouTube).
B12: =B11+1 -> 3 | C12: Meta Platforms, Inc. | D12: NASDAQ | E12: META | F12: USA | G12: 652.71 | H12: 1.48 | I12: 2178 | J12: 1 | K12: USD | L12: 1 | M12: =G12/L12 -> 652.71 | N12: =M12*I12*J12 -> 1421602.4 | O12: Primary competitor in Digital Advertising.
B13: =B12+1 -> 4 | C13: Oracle Corporation | D13: NYSE | E13: ORCL | F13: USA | G13: 198.85 | H13: 1.86 | I13: 2851 | J13: 1 | K13: USD | L13: 1 | M13: =G13/L13 -> 198.85 | N13: =M13*I13*J13 -> 566921.35 | O13: Legacy competitor in enterprise software and cloud infrastructure.
B14: =B13+1 -> 5 | C14: Walmart Inc. | D14: NYSE | E14: WMT | F14: USA | G14: 115.52 | H14: 2.86 | I14: 7970 | J14: 1 | K14: USD | L14: 1 | M14: =G14/L14 -> 115.52 | N14: =M14*I14*J14 -> 920694.4 | O14: The closest direct rival in scale, grocery, and retail logistics.
B15: =B14+1 -> 6 | C15: Costco Wholesale | D15: NASDAQ | E15: COST | F15: USA | G15: 888.48 | H15: 1.12 | I15: 443 | J15: 1 | K15: USD | L15: 1 | M15: =G15/L15 -> 888.48 | N15: =M15*I15*J15 -> 393596.64 | O15: Competes directly with the "Prime" membership model and efficiency.
B16: =B15+1 -> 7 | C16: Target Corporation | D16: NYSE | E16: TGT | F16: USA | G16: 96.97 | H16: 1.46 | I16: 452 | J16: 1 | K16: USD | L16: 1 | M16: =G16/L16 -> 96.97 | N16: =M16*I16*J16 -> 43830.44 | O16: General merchandise retailer; good proxy for consumer spending.
B17: =B16+1 -> 8 | C17: Alibaba Group | D17: NYSE | E17: BABA | F17: China | G17: 156.9 | H17: 0.32 | I17: =374369/G17 -> 2386.0357 | J17: 1 | K17: USD | L17: 1 | M17: =G17/L17 -> 156.9 | N17: =M17*I17*J17 -> 374369 | O17: The "Amazon of China" competes globally in e-commerce and cloud.
B18: =B17+1 -> 9 | C18: Apple Inc. | D18: NASDAQ | E18: AAPL | F18: USA | G18: 278.03 | H18: 1.03 | I18: 14776 | J18: 1 | K18: USD | L18: 1 | M18: =G18/L18 -> 278.03 | N18: =M18*I18*J18 -> 4108171.3 | O18: Essential for "Big Tech" valuation multiples.
B19: =B18+1 -> 10 | C19: Netflix, Inc. | D19: NASDAQ | E19: NFLX | F19: USA | G19: 94.09 | H19: 1.38 | I19: 4242 | J19: 1 | K19: USD | L19: 1 | M19: =G19/L19 -> 94.09 | N19: =M19*I19*J19 -> 399129.78 | O19: The best proxy for Amazon's media investments.
B21: NOTE: Equity beta based on 5 year monthly returns
B23: Source: Yahoo Finance, Pitchbook
B24: *Market data from Yahoo Finance
B25: https://finance.yahoo.com/?guccounter=1
B26: *Number of shares from Pitchbook
B27: https://my.pitchbook.com/dashboard

Sheet Peer Fin Info
C3: Industry Peers Financial Information
C4: Figures in USD millions, unless told otherwise
D8: Peer Financial Data in $ million
D10: Company Name | E10: Ticker Symbol | F10: Country | G10: Financials | H10: Revenues | I10: EBIT | J10: EBITDA | K10: Net Income | L10: Cash & Equiv. | M10: Total Debt | N10: Minority Interest | O10: Pref. Shares | P10: Equity | Q10: Market Cap | R10: EV | S10: D/E
C11: 1 | D11: Microsoft Corporation | E11: MSFT | F11: USA | G11: FY2024 | H11: 293812 | I11: 127218 | J11: 167049 | K11: 104912 | L11: 102005 | M11: 60556 | N11: 0 | O11: 0 | P11: 363076 | Q11: 3556616 | R11: =Q11+M11-L11 -> 3515167 | S11: =M11/P11 -> 0.16678602
C12: =C11+1 -> 2 | D12: Alphabet Inc. | E12: GOOGL | F12: USA | G12: FY2024 | H12: 385476 | I12: 148227 | J12: 167528 | K12: 124251 | L12: 98496 | M12: 33713 | N12: 0 | O12: 0 | P12: 386867 | Q12: 3732202 | R12: =Q12+M12-L12 -> 3667419 | S12: =M12/P12 -> 0.087143644
C13: =C12+1 -> 3 | D13: Meta Platforms, Inc. | E13: META | F13: USA | G13: FY2024 | H13: 189458 | I13: 82861 | J13: 100526 | K13: 58528 | L13: 44448 | M13: 51060 | N13: 0 | O13: 0 | P13: 194066 | Q13: 1623799 | R13: =Q13+M13-L13 -> 1630411 | S13: =M13/P13 -> 0.26310637
C14: =C13+1 -> 4 | D14: Oracle Corporation | E14: ORCL | F14: USA | G14: FY2024 | H14: 61016 | I14: 20629 | J14: 22757 | K14: 15425 | L14: 19766 | M14: 124386 | N14: 0 | O14: 0 | P14: 30457 | Q14: 541565 | R14: =Q14+M14-L14 -> 646185 | S14: =M14/P14 -> 4.0839873
C15: =C14+1 -> 5 | D15: Walmart Inc. | E15: WMT | F15: USA | G15: FY2024 | H15: 703061 | I15: 32874 | J15: 46710 | K15: 23303 | L15: 10582 | M15: 68424 | N15: 0 | O15: 0 | P15: 102512 | Q15: 930118 | R15: =Q15+M15-L15 -> 987960 | S15: =M15/P15 -> 0.66747308
C16: =C15+1 -> 6 | D16: Costco Wholesale | E16: COST | F16: USA | G16: FY2024 | H16: 208391 | I16: 10691 | J16: 13166 | K16: 8302 | L16: 15284 | M16: 8173 | N16: 0 | O16: 0 | P16: 29164 | Q16: 392667 | R16: =Q16+M16-L16 -> 385556 | S16: =M16/P16 -> 0.28024277
C17: =C16+1 -> 7 | D17: Target Corporation | E17: TGT | F17: USA | G17: FY2024 | H17: 105242 | I17: 5301 | J17: 8398 | K17: 3763 | L17: 3822 | M17: 20041 | N17: 0 | O17: 0 | P17: 15501 | Q17: 43909 | R17: =Q17+M17-L17 -> 60128 | S17: =M17/P17 -> 1.2928843
